Workbook

Sheet Resumen
A1: Bachoco: plantas, cuentas en el CRM y oportunidades
A2: Cruce de las 21 cuentas Bachoco del CRM contra el inventario público de plantas, con el historial de oportunidades. Documento de trabajo del 15-oct-2026. Los casos se sustentan solo con oportunidades Elegibles (regla del programa). Los montos son potencial anual registrado, no facturación. Ninguna réplica está confirmada.
A4: Cuentas y plantas (se calculan de las otras hojas)
A5: Indicador | B5: Valor | D5: Cómo se lee
A6: Cuentas Bachoco dadas de alta en el CRM | B6: =COUNTA('Cuentas CRM y homologación'!$B$2:$B$22) -> 21 | D6: Las 21 que pasaste en el archivo Workspace_1.csv.
A7: con sitio público confirmado por domicilio | B7: =COUNTIF('Cuentas CRM y homologación'!$X$2:$X$22,"Sí*") -> 6 | D7: Incluye una cuenta duplicada de Culiacán.
A8: con sitio público por confirmar | B8: =COUNTIF('Cuentas CRM y homologación'!$X$2:$X$22,"Por confirmar*") -> 6 | D8: Hay un sitio parecido (misma ciudad o mismo nombre de complejo), pero el domicilio no coincide o no está publicado.
A9: sin sitio público identificado | B9: =COUNTIF('Cuentas CRM y homologación'!$W$2:$W$22,"Sin sitio*") -> 9 | D9: Ninguna fuente pública las confirma. No quiere decir que no existan.
A10: Filas de la lista pública de Bachoco | B10: =COUNTA('Plantas vs CRM'!$A$2:$A$43) -> 42 | D10: Incluye 1 fila agregada (oficinas regionales de 9 ciudades) y 1 sitio no identificado. Bachoco no publica dónde están la mayoría de sus plantas de alimento e incubadoras.
A11: con cuenta en el CRM | B11: =COUNTIF('Plantas vs CRM'!$K$2:$K$43,"Sí*") -> 5 | D11: Cruce por domicilio.
A12: con cuenta por confirmar | B12: =COUNTIF('Plantas vs CRM'!$K$2:$K$43,"Por confirmar*") -> 6 | D12: Cuenta parecida (misma ciudad o nombre); domicilio distinto o no publicado.
A13: en el mismo municipio que otro sitio (predio por confirmar) | B13: =COUNTIF('Plantas vs CRM'!$K$2:$K$43,"Mismo*") -> 7 | D13: Plantas de rendimiento (subproductos) registradas en SADER; comparten municipio con otro sitio (un rastro, o un complejo sin confirmar en Hermosillo); no se sabe si es el mismo predio.
A14: sin cuenta en el CRM | B14: =COUNTIF('Plantas vs CRM'!$K$2:$K$43,"No") -> 22 | D14: No todas son candidatas a dar de alta: ver la columna "Lectura para dar de alta".
A15: de ellas, con fuente confirmada | B15: =COUNTIFS('Plantas vs CRM'!$K$2:$K$43,"No",'Plantas vs CRM'!$J$2:$J$43,"Confirmado") -> 9 | D15: Incluye negocios que no son de aves (cerdo, huevo, CEDIS).
A16: no aplica (fila agregada o sitio no identificado) | B16: =COUNTIF('Plantas vs CRM'!$K$2:$K$43,"No aplica*") -> 2
A18: Oportunidades en cuentas Bachoco
A19: Indicador | B19: Solo Elegible (regla del programa) | C19: Todo el CRM | D19: Cómo se lee
A20: Oportunidades | B20: =COUNTIFS(Oportunidades!$D$2:$D$71,"Sí",Oportunidades!$Z$2:$Z$71,"Elegible") -> 46 | C20: =COUNTIFS(Oportunidades!$D$2:$D$71,"Sí") -> 68 | D20: Ganadas + perdidas + abiertas. Con todo el CRM son 68 en 18 de las 21 cuentas.
A21: Ganadas | B21: =COUNTIFS(Oportunidades!$D$2:$D$71,"Sí",Oportunidades!$Z$2:$Z$71,"Elegible",Oportunidades!$H$2:$H$71,"Ganada") -> 31 | C21: =COUNTIFS(Oportunidades!$D$2:$D$71,"Sí",Oportunidades!$H$2:$H$71,"Ganada") -> 44
A22: Perdidas | B22: =COUNTIFS(Oportunidades!$D$2:$D$71,"Sí",Oportunidades!$Z$2:$Z$71,"Elegible",Oportunidades!$H$2:$H$71,"Perdida") -> 14 | C22: =COUNTIFS(Oportunidades!$D$2:$D$71,"Sí",Oportunidades!$H$2:$H$71,"Perdida") -> 19
A23: Abiertas | B23: =COUNTIFS(Oportunidades!$D$2:$D$71,"Sí",Oportunidades!$Z$2:$Z$71,"Elegible",Oportunidades!$H$2:$H$71,"Abierta") -> 1 | C23: =COUNTIFS(Oportunidades!$D$2:$D$71,"Sí",Oportunidades!$H$2:$H$71,"Abierta") -> 5 | D23: Foto de cartera; no se suman a las ganadas.
A24: Tasa de ganancia (ganadas / (ganadas + perdidas)) | B24: =B21/(B21+B22) -> 0.68888889 | C24: =C21/(C21+C22) -> 0.6984127 | D24: Las abiertas no cuentan.
A25: Potencial anual de las ganadas, suma bruta (MXN) | B25: =SUMIFS(Oportunidades!$K$2:$K$71,Oportunidades!$D$2:$D$71,"Sí",Oportunidades!$Z$2:$Z$71,"Elegible",Oportunidades!$H$2:$H$71,"Ganada") -> 10591086 | C25: =SUMIFS(Oportunidades!$K$2:$K$71,Oportunidades!$D$2:$D$71,"Sí",Oportunidades!$H$2:$H$71,"Ganada") -> 18956616 | D25: Potencial anual registrado, NO facturación; puede repetir el mismo negocio año con año.
A26: Potencial anual de las ganadas, sin posibles re-registros (MXN) | B26: =SUMIFS(Oportunidades!$K$2:$K$71,Oportunidades!$D$2:$D$71,"Sí",Oportunidades!$Z$2:$Z$71,"Elegible",Oportunidades!$H$2:$H$71,"Ganada",Oportunidades!$L$2:$L$71,"No") -> 9318210.5 | C26: =SUMIFS(Oportunidades!$K$2:$K$71,Oportunidades!$D$2:$D$71,"Sí",Oportunidades!$H$2:$H$71,"Ganada",Oportunidades!$L$2:$L$71,"No") -> 17245843 | D26: Quita ganadas que repiten el monto de otra en la misma zona (pista, no confirmación).
A27: Última oportunidad ganada registrada | B27: =_xlfn.MAXIFS(Oportunidades!$I$2:$I$71,Oportunidades!$D$2:$D$71,"Sí",Oportunidades!$Z$2:$Z$71,"Elegible",Oportunidades!$H$2:$H$71,"Ganada") -> 46216 | C27: =_xlfn.MAXIFS(Oportunidades!$I$2:$I$71,Oportunidades!$D$2:$D$71,"Sí",Oportunidades!$H$2:$H$71,"Ganada") -> 46227 | D27: Fecha de cierre más reciente entre las ganadas.
A29: Cifras que Bachoco declara (no son sitios; no sumar)
A30: Indicador | B30: Valor | D30: Fuente y fecha
A31: Plantas procesadoras de pollo en México | B31: 7 | D31: Reporte Anual 2023 (BMV), al 31-dic-2023, publicado 2024-04/05 (fecha exacta ND): https://www.bmv.com.mx/docs-pub/infoanua/infoanua_1378033_2023_1.pdf. SENASICA 2024 muestra solo 6 rastros de aves de Bachoco. CONFIRMADO como cifra declarada.
A32: Plantas de alimento balanceado | B32: 23 (Reporte Anual 2023); 22 (HIPÓTESIS) | D32: Reporte Anual 2023 (misma URL): CONFIRMADO como cifra declarada; el mismo documento dice 25 en el texto (incluye 2 en EUA). La cifra 22 viene del archivo previo GRUPOS_RANKING.csv, que la atribuye al Informe Anual 2024 (https://grupobachoco.com/wp-content/downloads/2025/Informe-Anual-2024-BMV.pdf, fecha de publicación ND): no pude reabrirlo; atribución no verificada. Ese mismo archivo da 10 procesadoras y 66 centros de distribución, que no cuadran con el Reporte Anual 2023 (7 y más de 100), así que podría ser un documento más antiguo.
A33: Incubadoras | B33: 20 (Reporte Anual 2023); 23 (HIPÓTESIS) | D33: Reporte Anual 2023: CONFIRMADO como cifra declarada. La cifra 23 es del archivo previo GRUPOS_RANKING.csv (atribución no verificada, ver arriba). Otro archivo previo (COMPLEJOS_INTEGRADOS.csv) cita "aprox. 20 de alimento y 24 incubadoras" de fuentes más antiguas. Cifras en conflicto: no se eligió una.
A34: Plantas procesadoras de cerdos / empacadoras (valor agregado) | B34: 4 / 4 | D34: Reporte Anual 2023 (misma URL), al 31-dic-2023.
A35: Centros de distribución en México | B35: más de 100 | D35: Reporte Anual 2023 y 1T25 (https://grupobachoco.com/wp-content/downloads/2025/1T25-BMV.pdf, 2025-04-25). Documentos anteriores dicen 66 y más de 80.
A37: Lo más importante
A38: 1. [CONFIRMADO en el CRM] Bachoco tiene 68 oportunidades en 18 de las 21 cuentas (3 cuentas no tienen ninguna). Siguiendo la regla del programa solo cuentan las Elegibles: 46, de las que 31 son ganadas, 14 perdidas y 1 abierta, con tasa de ganancia de 69%. Su potencial anual registrado suma 10.6 millones de pesos bruto, o 9.3 millones quitando 3 posibles re-registros; no es venta facturada. Las otras 22 oportunidades (13 ganadas, 5 perdidas, 1 abierta y 3 sin decisión por ser posteriores al corte) no entran en el análisis y están en la hoja Clasificación dudosa. Con todo el CRM serían 44 ganadas, 19 perdidas y 5 abiertas.
A39: 2. [CONFIRMADO: estatus y conteo; HIPÓTESIS: la línea de las 5 ganadas que solo dicen "PTI"] Con Elegibles, lo que se gana es la banda en V: 23 ganadas contra 2 perdidas. Manguera industrial: 5 y 1. Manguera hidráulica y neumática: 1 y 4. Bandas síncronas, de poliuretano y micro-V: 1 y 6. De las 23 ganadas de banda en V, 13 se clasificaron por abreviatura (PTI, V-Belts) y no por el sufijo de línea del CRM.
A40: 3. [CONFIRMADO] El Bajío (Celaya) concentra 14 de las 31 ganadas Elegibles, 13 de banda en V y ninguna de manguera. Su última ganada es de junio de 2024 y 11 de esas 14 están a nombre de un propietario marcado inactivo en el CRM.
A41: 4. [CONFIRMADO] Tecamachalco es la cuenta que sigue ganando: 10 ganadas Elegibles (banda en V y manguera industrial Plant Master), la más reciente de julio de 2026. 4 de las 5 ganadas Elegibles de manguera industrial son de Tecamachalco.
A42: 5. [CONFIRMADO en el CRM; clasificación dudosa reportada, no cambiada] Culiacán (tu cuenta) tiene 6 ganadas en el CRM, 5 de manguera y 1 de banda en V, pero ninguna es Elegible: 5 quedaron Excluidas porque la cuenta está segmentada como OEM y 1 está en Revisar (cuenta duplicada, segmentación Corporate). Mientras no se corrija esa clasificación, Culiacán no puede sustentar un caso. Todas están en la hoja Clasificación dudosa.
A43: 6. [CONFIRMADO; motivo no disponible] Noroeste (Obregón, Hermosillo y Mexicali): 6 perdidas Elegibles y ninguna ganada (7 perdidas con todo el CRM). Gómez Palacio: 1 perdida. El CRM no tiene campo de motivo de pérdida.
A44: 7. [CONFIRMADO] Ganadas Elegibles por año de cierre: 2 en 2019, 9 en 2020, 5 en 2021, 5 en 2022, 4 en 2023, 4 en 2024, 1 en 2025, 1 en 2026 (2026 es parcial). No se sabe si bajó la actividad con Bachoco o solo la captura en el CRM.
A45: 8. [CONFIRMADO: 6 rastros TIF de aves con fuente oficial, SENASICA 2024] Tres tienen cuenta en el CRM (Culiacán, Ciénega de Flores y Umán/Mérida), dos están por confirmar (Celaya, y el de Puebla, que el CRM llama Tecamachalco y SENASICA ubica en San Salvador Huixcolotla) y uno no tiene cuenta: Unión de San Antonio, el complejo "Lagos". [HIPÓTESIS: solo prensa] El 3 de mayo de 2026 hubo un incendio en una planta de Lagos de Moreno; no está confirmado que sea el mismo predio. [PENDIENTE] Su reapertura.
A46: 9. [CONFIRMADO por domicilio / POR CONFIRMAR / PENDIENTE] De tus 21 cuentas, 6 se ligan a un sitio público por domicilio, 6 quedan por confirmar y 9 no se pudieron ligar a ninguno (3 de Celaya, 1 de Mérida, Tierra Blanca, Obregón-Navojoa, Gómez Palacio, San Luis Potosí y Mexicali). Eso no quiere decir que no existan: ninguna fuente pública las confirma.
A47: 10. [CONFIRMADO por domicilio] La cuenta "Corp" SÍ es el corporativo: Av. Tecnológico 401, Ciudad Industrial, Celaya, igual al domicilio que Bachoco declara. Pero está registrada como End User; la segmentación "Corporate" está en una cuenta de planta de Culiacán.
A48: 11. [CONFIRMADO: Reporte Anual 2023; HIPÓTESIS: las cifras de otro archivo previo y las ubicaciones] Bachoco declara 23 plantas de alimento y 20 incubadoras en el Reporte Anual 2023; un archivo previo del proyecto cita 22 y 23 que atribuye al Informe Anual 2024, que no pude reabrir (atribución no verificada). La lista pública ubica con municipio 4 plantas de alimento (confirmadas por CAMPI o boletín oficial) y 1 solo con estado (hipótesis), y 3 incubadoras (las 3 hipótesis; una es proyecto de 2015). Para saber cuáles faltan en el CRM hay que pedirlas a los distribuidores o a Bachoco.
... A52: Hojas de este archivo
A53: Resumen | B53: Cifras clave y lo más importante.
A54: Plantas vs CRM | B54: Lista pública de sitios de Bachoco contra tus cuentas del CRM: cuáles ya tienes, cuáles faltan y dónde están.
A55: Cuentas CRM y homologación | B55: Tus 21 cuentas con lo que se detectó mal registrado y la propuesta de cómo dejarlas igual.
A56: Casos fuente | B56: Qué se ha ganado en Bachoco, por zona y por línea, y las 12 ganadas Elegibles de mayor potencial. Trae un selector: Solo Elegible o Todo el CRM.
A57: Zona x Línea | B57: Mapa de dónde se ha ganado, perdido o hay abierta cada línea (los ceros son zonas sin registro). Mismo selector.
A58: Clasificación dudosa | B58: Las 22 oportunidades que el programa no marcó Elegible (13 ganadas, 5 perdidas, 1 abierta y 3 sin decisión), con su motivo. Se reportan; no se cambiaron.
A59: Réplicas por validar | B59: Candidatas para llevar un caso ganado a otra planta, con lo que falta comprobar.
A60: Reglas de homologación | B60: Reglas propuestas para registrar igual las cuentas con el mismo End Market y subcategoría.
A61: Pendientes y preguntas | B61: Lo que no se pudo confirmar y quién puede responder.
A62: Oportunidades | B62: Las 70 oportunidades de Bachoco con su nomenclatura completa (base de todo lo anterior).
A64: Notas de método
A65: Fuentes. Cuentas: el archivo Workspace_1.csv que pasó Marcos (21 cuentas); no se guarda en el repositorio porque trae nombres, correos y teléfonos de contactos de Bachoco. Oportunidades: IR Opportunity Detail Analysis-_MXN.xlsx, hoja Datos_OPP (70 con "Bachoco" en la cuenta o en el nombre; 2 están capturadas en cuentas de distribuidor y no se cuentan). Decisión y motivo del programa: Base_Simbiosis.xlsx, hoja DETALLE (corte al 12-ago-2026; el archivo IR trae además registros posteriores, hasta al menos el 31-ago-2026, por eso 3 abiertas no tienen decisión). No se modificó ningún archivo original.
A66: Universo. Siguiendo la regla del programa, los casos se sustentan solo con oportunidades Elegible. Las hojas Zona x Línea y Casos fuente traen un selector para ver "Solo Elegible" (valor inicial) o "Todo el CRM". Las 22 oportunidades que no son Elegible (13 ganadas, 5 perdidas, 1 abierta Excluida y 3 sin decisión) están en la hoja Clasificación dudosa con el motivo del programa; no se cambió ninguna clasificación.
A67: Montos. Son potencial anual registrado en el CRM, no facturación. Varias ganadas repiten el mismo monto en la misma zona; por eso se muestra la suma bruta y la suma sin posibles re-registros (pista, no confirmación). Hay además montos idénticos entre zonas distintas y otra lectura posible: potencial por escalón. Ninguna cifra es venta real.
A68: Línea de producto. Se tomó de la nomenclatura de cada oportunidad: sufijo de línea del CRM o abreviatura, con el mapeo de la guía de alta de oportunidades de Gates (HID = FP-HYDRAULICS, MI = FP-IND HOSE & CPLG, PTI = PT-V-BELTS); esa guía no está en el repositorio. 17 de las 30 ganadas de banda en V (todo el CRM) se clasificaron por abreviatura, 9 de ellas porque el nombre solo dice "PTI". No se infieren máquinas, números de parte ni intervalos de reemplazo.
A69: Competidores. Una marca nombrada en la nomenclatura (por ejemplo Optibelt) no prueba que haya sido una conversión: el prefijo 2.2 es el tipo de oportunidad y el CRM tipifica esas oportunidades como Replacement / Existing Business. Que hayan desplazado a esa marca es hipótesis. El CRM no tiene campo de motivo de ganar o perder: motivo no disponible.
A70: Los propietarios del CRM son históricos. Nadie debe recibir trabajo sin confirmar que sigue activo; los marcados "Inactive" no deben recibir trabajo y primero hay que designar quién recupera su expediente.
A71: Los nombres de región (31 Centro, 32 Pacífico, 33 Sureste, 34 Noreste, 35 Norte, 36 Península, 37 Noroeste, 38 Bajío) vienen de la hoja Team del archivo IR; el CRM de oportunidades solo trae el número. No se guardaron nombres, correos ni teléfonos de contactos de Bachoco en este archivo; están en el CRM. Etiquetas: CONFIRMADO = dato del CRM o fuente oficial citada; HIPÓTESIS = fuente débil o inferencia; PENDIENTE = sin dato.

Sheet Plantas vs CRM
A1: ID sitio | B1: Tipo de instalación | C1: Nombre público | D1: Municipio | E1: Estado | F1: Domicilio público | G1: Capacidad publicada | H1: Fuente (URL) | I1: Fecha de publicación de la fuente | J1: Verificación de la fuente | K1: ¿Tenemos cuenta en el CRM? | L1: Cuenta(s) CRM relacionada(s) | M1: Base del cruce | N1: Ganadas (todo el CRM) | O1: Perdidas (todo el CRM) | P1: Abiertas (todo el CRM) | Q1: Ganadas Elegibles | R1: Perdidas Elegibles | S1: Observaciones | T1: Lectura para dar de alta en el CRM
A2: BCH-001 | B2: Oficina corporativa | C2: Oficinas corporativas Grupo Bachoco (Industrias Bachoco, S.A. de C.V.) | D2: Celaya | E2: Guanajuato | F2: Avenida Tecnológico No. 401, Ciudad Industrial, C.P. 38010 | G2: ND | H2: https://www.bmv.com.mx/docs-pub/infoanua/infoanua_1378033_2023_1.pdf | https://www.bmv.com.mx/en/issuers/profile/BACHOCO-5113 | https://bachoco.com/aviso-de-privacidad.html | https://www.sec.gov/Archives/edgar/data/1044896/000141057822001105/iba-20211231x20f.htm | I2: 2024-04/05 (fecha exacta ND) | ND (perfil sin fecha) | ND (aviso sin fecha; pie 2025) | 2022-04-29 | J2: Confirmado | K2: Sí | L2: Bachoco S.A. de C.V. - Corp | M2: Domicilio coincide: Av. Tecnológico No. 401, Ciudad Industrial, CP 38010, Celaya (cuenta "Corp"). La verificó la lista pública con el Reporte Anual 2023, el perfil de la BMV y el aviso de privacidad de bachoco.com. | N2: =SUMIFS('Cuentas CRM y homologación'!$P$2:$P$22,'Cuentas CRM y homologación'!$W$2:$W$22,$A2) -> 1 | O2: =SUMIFS('Cuentas CRM y homologación'!$Q$2:$Q$22,'Cuentas CRM y homologación'!$W$2:$W$22,$A2) -> 0 | P2: =SUMIFS('Cuentas CRM y homologación'!$R$2:$R$22,'Cuentas CRM y homologación'!$W$2:$W$22,$A2) -> 0 | Q2: =SUMIFS('Cuentas CRM y homologación'!$S$2:$S$22,'Cuentas CRM y homologación'!$W$2:$W$22,$A2) -> 1 | R2: =SUMIFS('Cuentas CRM y homologación'!$T$2:$T$22,'Cuentas CRM y homologación'!$W$2:$W$22,$A2) -> 0 | S2: La cuenta "Corp" SÍ es el corporativo por domicilio. Ojo: su segmentación en el CRM es End User; la segmentación "Corporate" está en una cuenta de Culiacán. | T2: -
A3: BCH-002 | B3: Oficinas regionales (fila agregada) | C3: Oficinas regionales de ex complejos productivos (hoy Unidades de Negocio) - fila agregada de 9 ciudades | D3: Mérida; Coatzacoalcos; Tecamachalco; Celaya; Lagos de Moreno; Monterrey; Gómez Palacio; Culiacán; Hermosillo | E3: Yucatán; Veracruz; Puebla; Guanajuato; Jalisco; Nuevo León; Durango; Sinaloa; Sonora | F3: PENDIENTE | G3: ND | H3: https://www.bmv.com.mx/docs-pub/infoanua/infoanua_1378033_2023_1.pdf | https://www.sec.gov/Archives/edgar/data/1044896/000114420419021974/tv518925_20f.htm | I3: 2024-04/05 (fecha exacta ND) | 2019-04-29 | J3: Confirmado | K3: No aplica (fila agregada) | L3: - | M3: Fila agregada de 9 ciudades (Mérida, Coatzacoalcos, Tecamachalco, Celaya, Lagos de Moreno, Monterrey, Gómez Palacio, Culiacán, Hermosillo) donde Bachoco tenía oficinas de complejo; hoy son "Unidades de Negocio". No son oficinas corporativas y no publican domicilio. Hay cuentas del CRM en Mérida, Coatzacoalcos, Tecamachalco, Celaya, Gómez Palacio, Culiacán y Hermosillo; no se puede saber si alguna es la oficina. | N3: =SUMIFS('Cuentas CRM y homologación'!$P$2:$P$22,'Cuentas CRM y homologación'!$W$2:$W$22,$A3) -> 0 | O3: =SUMIFS('Cuentas CRM y homologación'!$Q$2:$Q$22,'Cuentas CRM y homologación'!$W$2:$W$22,$A3) -> 0 | P3: =SUMIFS('Cuentas CRM y homologación'!$R$2:$R$22,'Cuentas CRM y homologación'!$W$2:$W$22,$A3) -> 0 | Q3: =SUMIFS('Cuentas CRM y homologación'!$S$2:$S$22,'Cuentas CRM y homologación'!$W$2:$W$22,$A3) -> 0 | R3: =SUMIFS('Cuentas CRM y homologación'!$T$2:$T$22,'Cuentas CRM y homologación'!$W$2:$W$22,$A3) -> 0 | S3: Vigencia a 2026 no verificada (fuentes de 2024 y 2019). | T3: -
A4: BCH-010 | B4: Procesadora de aves (rastro TIF) | C4: Rastro / planta procesadora de aves TIF A-363 (División Bajío) | D4: Celaya | E4: Guanajuato | F4: Km. 5 Carretera Celaya-Salamanca, Segunda Fracción de Crespo, C.P. 38020 | G4: ND | H4: https://campo.nl.gob.mx/pdf/directorios/Directorio_TIF.pdf | https://www.am.com.mx/celaya/2023/3/1/drenaje-tapado-de-rastro-de-bachoco-causaria-malos-olores-en-celaya-649603.html | https://www.agricultura.gob.mx/sites/default/files/sagarpa/document/2025/12/04/2250/04122025-padron-plantas-rendimiento.csv | I4: 2024 (año indicado en el documento; fecha exacta ND) | 2023-03-01 | 2025-12-04 (inferida de la ruta del URL) | J4: Confirmado | K4: Por confirmar | L4: Bachoco, S.A. de C.V. - Planta procesadora de aves Guanajuato - Guanajuato | M4: La cuenta "Planta procesadora de aves Guanajuato - Guanajuato" tiene domicilio "Av el Vergel, San Isidro Crespo" (CP 36003). Directorios comerciales ubican el rastro en "Parque Industrial El Vergel" y "San Isidro de Crespo", pero el domicilio oficial de SENASICA es Km 5 Carr. Celaya-Salamanca, Segunda Fracción de Crespo (CP 38020). El CP del CRM no coincide. | N4: =SUMIFS('Cuentas CRM y homologación'!$P$2:$P$22,'Cuentas CRM y homologación'!$W$2:$W$22,$A4) -> 11 | O4: =SUMIFS('Cuentas CRM y homologación'!$Q$2:$Q$22,'Cuentas CRM y homologación'!$W$2:$W$22,$A4) -> 3 | P4: =SUMIFS('Cuentas CRM y homologación'!$R$2:$R$22,'Cuentas CRM y homologación'!$W$2:$W$22,$A4) -> 0 | Q4: =SUMIFS('Cuentas CRM y homologación'!$S$2:$S$22,'Cuentas CRM y homologación'!$W$2:$W$22,$A4) -> 10 | R4: =SUMIFS('Cuentas CRM y homologación'!$T$2:$T$22,'Cuentas CRM y homologación'!$W$2:$W$22,$A4) -> 3 | S4: Mismo nombre de lugar (Crespo / El Vergel), domicilio distinto: falta confirmar en visita. Es la cuenta con más ganadas (11 en todo el CRM, 10 Elegibles). | T4: -
A5: BCH-011 | B5: Procesadora de aves (rastro TIF) | C5: Rastro / planta procesadora de aves TIF A-183 (División Occidente, conocida como 'Lagos de Moreno') | D5: Unión de San Antonio | E5: Jalisco | F5: Carretera Lagos - U. de San Antonio Km. 13.5, Unión de San Antonio, C.P. 47570 | G5: ND | H5: https://campo.nl.gob.mx/pdf/directorios/Directorio_TIF.pdf | https://www.agricultura.gob.mx/sites/default/files/sagarpa/document/2025/12/04/2250/04122025-padron-plantas-rendimiento.csv | I5: 2024 (año indicado en el documento; fecha exacta ND) | 2025-12-04 (inferida de la ruta del URL) | J5: Confirmado | K5: No | L5: - | M5: No hay cuenta del CRM en Unión de San Antonio ni en Lagos de Moreno. | N5: =SUMIFS('Cuentas CRM y homologación'!$P$2:$P$22,'Cuentas CRM y homologación'!$W$2:$W$22,$A5) -> 0 | O5: =SUMIFS('Cuentas CRM y homologación'!$Q$2:$Q$22,'Cuentas CRM y homologación'!$W$2:$W$22,$A5) -> 0 | P5: =SUMIFS('Cuentas CRM y homologación'!$R$2:$R$22,'Cuentas CRM y homologación'!$W$2:$W$22,$A5) -> 0 | Q5: =SUMIFS('Cuentas CRM y homologación'!$S$2:$S$22,'Cuentas CRM y homologación'!$W$2:$W$22,$A5) -> 0 | R5: =SUMIFS('Cuentas CRM y homologación'!$T$2:$T$22,'Cuentas CRM y homologación'!$W$2:$W$22,$A5) -> 0 | S5: La oportunidad O-00218689 "7.1 PCC C2B-Bachoco Lagos- Bamac Guadalajara" (perdida, 2020) está capturada en la cuenta de Celaya/Guanajuato, no en una cuenta propia de Lagos; que se refiera a este sitio es HIPÓTESIS (solo por el nombre). El 2026-05-03 hubo un incendio en una planta de Lagos de Moreno (ver BCH-012); no está confirmado que sea este predio. | T5: Fuente confirmada: candidato a dar de alta si interesa.
A6: BCH-012 | B6: Procesadora de aves | C6: Planta Bachoco en Lagos de Moreno (siniestrada el 2026-05-03) | D6: Lagos de Moreno | E6: Jalisco | F6: Autopista León-Aguascalientes, cruce con Ramal Paso de la Mesa (descripción de prensa citando a Protección Civil Jalisco; sin calle ni km) | G6: ND | H6: https://lasillarota.com/guanajuato/estado/2026/5/11/tras-incendio-en-planta-de-bachoco-trabajadores-son-reubicados-en-celaya-puebla-nl-598777.html | https://www.elfinanciero.com.mx/estados/2026/05/04/incendio-en-planta-de-bachoco-en-lagos-de-moreno-deja-3-personas-intoxicadas-esto-sabemos/ | https://www.milenio.com/comunidad/bachoco-suspende-operaciones-incendio-trabajadores-reubicados | https://www.unotv.com/estados/jalisco/fuego-devora-planta-de-bachoco-en-lagos-de-moreno-jalisco-videos/ | I6: 2026-05-11 | 2026-05-04 | 2026-05-05 | 2026-05-04 | J6: Hipótesis | K6: No | L6: - | M6: No hay cuenta del CRM en Lagos de Moreno. | N6: =SUMIFS('Cuentas CRM y homologación'!$P$2:$P$22,'Cuentas CRM y homologación'!$W$2:$W$22,$A6) -> 0 | O6: =SUMIFS('Cuentas CRM y homologación'!$Q$2:$Q$22,'Cuentas CRM y homologación'!$W$2:$W$22,$A6) -> 0 | P6: =SUMIFS('Cuentas CRM y homologación'!$R$2:$R$22,'Cuentas CRM y homologación'!$W$2:$W$22,$A6) -> 0 | Q6: =SUMIFS('Cuentas CRM y homologación'!$S$2:$S$22,'Cuentas CRM y homologación'!$W$2:$W$22,$A6) -> 0 | R6: =SUMIFS('Cuentas CRM y homologación'!$T$2:$T$22,'Cuentas CRM y homologación'!$W$2:$W$22,$A6) -> 0 | S6: Fuente: solo prensa. Posible duplicado de BCH-011: la ubicación descrita por la prensa (autopista León-Aguascalientes) no es la del TIF (carretera a Unión de San Antonio). Reapertura PENDIENTE. | T6: Posible duplicado de BCH-011: no dar de alta por separado.
A7: BCH-013 | B7: Procesadora de aves (rastro TIF) | C7: Rastro / planta procesadora de aves TIF A-423 (Complejo Noreste / Monterrey) | D7: Ciénega de Flores | E7: Nuevo León | F7: Autopista Monterrey-Nuevo Laredo Km. 34+200, C.P. 65550 | G7: ND | H7: https://campo.nl.gob.mx/pdf/directorios/Directorio_TIF.pdf | https://www.agricultura.gob.mx/sites/default/files/sagarpa/document/2025/12/04/2250/04122025-padron-plantas-rendimiento.csv | I7: 2024 (año indicado en el documento; fecha exacta ND) | 2025-12-04 (inferida de la ruta del URL) | J7: Confirmado | K7: Sí | L7: BACHOCO SA de CV - Cienega de Flores | M7: Domicilio coincide en carretera y kilómetro: Autopista Monterrey-Nuevo Laredo Km 34 (CP 65555 en el CRM; 65550 en SENASICA). | N7: =SUMIFS('Cuentas CRM y homologación'!$P$2:$P$22,'Cuentas CRM y homologación'!$W$2:$W$22,$A7) -> 1 | O7: =SUMIFS('Cuentas CRM y homologación'!$Q$2:$Q$22,'Cuentas CRM y homologación'!$W$2:$W$22,$A7) -> 0 | P7: =SUMIFS('Cuentas CRM y homologación'!$R$2:$R$22,'Cuentas CRM y homologación'!$W$2:$W$22,$A7) -> 1 | Q7: =SUMIFS('Cuentas CRM y homologación'!$S$2:$S$22,'Cuentas CRM y homologación'!$W$2:$W$22,$A7) -> 0 | R7: =SUMIFS('Cuentas CRM y homologación'!$T$2:$T$22,'Cuentas CRM y homologación'!$W$2:$W$22,$A7) -> 0 | S7: Cuenta creada el 6-abr-2026, con 1 ganada (jul-2026) y 1 abierta. | T7: -
A8: BCH-014 | B8: Procesadora de aves (rastro TIF) | C8: Rastro / planta procesadora de aves TIF A-326 (Complejo Sureste, 'Tecamachalco') | D8: San Salvador Huixcolotla | E8: Puebla | F8: Carretera Federal Puebla-Tehuacán Km. 53, San Salvador Huixcolotla, C.P. 75440 | G8: ND | H8: https://campo.nl.gob.mx/pdf/directorios/Directorio_TIF.pdf | https://www.agricultura.gob.mx/sites/default/files/sagarpa/document/2025/12/04/2250/04122025-padron-plantas-rendimiento.csv | I8: 2024 (año indicado en el documento; fecha exacta ND) | 2025-12-04 (inferida de la ruta del URL) | J8: Confirmado | K8: Por confirmar | L8: Bachoco, S.A. De C.V. - Tecamachalco | M8: El predio oficial del rastro está en San Salvador Huixcolotla (Km 53 Puebla-Tehuacán, CP 75440); "Tecamachalco" es el nombre histórico del complejo. La cuenta del CRM dice Tecamachalco, Barrio de San Juan (CP 75484), domicilio que viene de directorios no oficiales. | N8: =SUMIFS('Cuentas CRM y homologación'!$P$2:$P$22,'Cuentas CRM y homologación'!$W$2:$W$22,$A8) -> 10 | O8: =SUMIFS('Cuentas CRM y homologación'!$Q$2:$Q$22,'Cuentas CRM y homologación'!$W$2:$W$22,$A8) -> 5 | P8: =SUMIFS('Cuentas CRM y homologación'!$R$2:$R$22,'Cuentas CRM y homologación'!$W$2:$W$22,$A8) -> 0 | Q8: =SUMIFS('Cuentas CRM y homologación'!$S$2:$S$22,'Cuentas CRM y homologación'!$W$2:$W$22,$A8) -> 10 | R8: =SUMIFS('Cuentas CRM y homologación'!$T$2:$T$22,'Cuentas CRM y homologación'!$W$2:$W$22,$A8) -> 3 | S8: Misma operación por nombre de complejo, domicilio distinto. Falta confirmar en visita si la cuenta es el rastro de Huixcolotla. | T8: -
A9: BCH-015 | B9: Procesadora de aves (rastro TIF) | C9: Rastro / planta procesadora de aves TIF A-124 (Complejo Noroeste) | D9: Culiacán | E9: Sinaloa | F9: Carretera al Dorado Km. 13.5, Culiacán, C.P. 80100 (Apartado Postal 607) | G9: ND | H9: https://campo.nl.gob.mx/pdf/directorios/Directorio_TIF.pdf | https://www.agricultura.gob.mx/sites/default/files/sagarpa/document/2025/12/04/2250/04122025-padron-plantas-rendimiento.csv | I9: 2024 (año indicado en el documento; fecha exacta ND) | 2025-12-04 (inferida de la ruta del URL) | J9: Confirmado | K9: Sí | L9: Bachoco S.A. de C.V. - Planta Culiacan | BACHOCO Planta Culiacan | M9: Domicilio coincide: Carretera al Dorado Km 13.5, Culiacán. Las dos cuentas del CRM de Culiacán tienen el mismo domicilio (CP 80300 y 80130; SENASICA 80100). | N9: =SUMIFS('Cuentas CRM y homologación'!$P$2:$P$22,'Cuentas CRM y homologación'!$W$2:$W$22,$A9) -> 6 | O9: =SUMIFS('Cuentas CRM y homologación'!$Q$2:$Q$22,'Cuentas CRM y homologación'!$W$2:$W$22,$A9) -> 2 | P9: =SUMIFS('Cuentas CRM y homologación'!$R$2:$R$22,'Cuentas CRM y homologación'!$W$2:$W$22,$A9) -> 0 | Q9: =SUMIFS('Cuentas CRM y homologación'!$S$2:$S$22,'Cuentas CRM y homologación'!$W$2:$W$22,$A9) -> 0 | R9: =SUMIFS('Cuentas CRM y homologación'!$T$2:$T$22,'Cuentas CRM y homologación'!$W$2:$W$22,$A9) -> 0 | S9: Dos cuentas para el mismo sitio (una con segmentación OEM, otra Corporate). | T9: -
A10: BCH-016 | B10: Procesadora de aves (rastro TIF) | C10: Rastro / planta procesadora de aves TIF A-234 (Complejo Península) | D10: Mérida (SENASICA) / Umán (SADER y CP 97390) | E10: Yucatán | F10: Carr. Mérida-Umán Km. 14.5, C.P. 97390 | G10: ND | H10: https://campo.nl.gob.mx/pdf/directorios/Directorio_TIF.pdf | https://www.agricultura.gob.mx/sites/default/files/sagarpa/document/2025/12/04/2250/04122025-padron-plantas-rendimiento.csv | https://www.poresto.com/yucatan/2026/2/16/joaquin-diaz-mena-impulsa-mayor-inversion-empresarial-para-generar-empleos-en-yucatan.html | I10: 2024 (año indicado en el documento; fecha exacta ND) | 2025-12-04 (inferida de la ruta del URL) | 2026-02-16 | J10: Confirmado | K10: Sí | L10: Industrias Bachoco S.A. de C.V. - Uman, Yucatan. | M10: Domicilio coincide: Carretera Mérida-Umán Km 14.5, CP 97390 (cuenta "Industrias Bachoco ... Umán"). SENASICA lo llama Mérida; el CP es de Umán. | N10: =SUMIFS('Cuentas CRM y homologación'!$P$2:$P$22,'Cuentas CRM y homologación'!$W$2:$W$22,$A10) -> 1 | O10: =SUMIFS('Cuentas CRM y homologación'!$Q$2:$Q$22,'Cuentas CRM y homologación'!$W$2:$W$22,$A10) -> 0 | P10: =SUMIFS('Cuentas CRM y homologación'!$R$2:$R$22,'Cuentas CRM y homologación'!$W$2:$W$22,$A10) -> 0 | Q10: =SUMIFS('Cuentas CRM y homologación'!$S$2:$S$22,'Cuentas CRM y homologación'!$W$2:$W$22,$A10) -> 1 | R10: =SUMIFS('Cuentas CRM y homologación'!$T$2:$T$22,'Cuentas CRM y homologación'!$W$2:$W$22,$A10) -> 0 | S10: Mérida y Umán son el mismo rastro. La cuenta "Industrias Bachoco ... Mérida" (Calle Benito Juárez 21) NO es este domicilio. | T10: -
A11: BCH-017 | B11: Procesadora de aves | C11: Séptima planta procesadora de pollo declarada (no identificada) | D11: PENDIENTE | E11: PENDIENTE | F11: PENDIENTE | G11: ND | H11: https://www.bmv.com.mx/docs-pub/infoanua/infoanua_1378033_2023_1.pdf | I11: 2024-04/05 (fecha exacta ND) | J11: Pendiente | K11: No aplica | L11: - | M11: Sitio no identificado. | N11: =SUMIFS('Cuentas CRM y homologación'!$P$2:$P$22,'Cuentas CRM y homologación'!$W$2:$W$22,$A11) -> 0 | O11: =SUMIFS('Cuentas CRM y homologación'!$Q$2:$Q$22,'Cuentas CRM y homologación'!$W$2:$W$22,$A11) -> 0 | P11: =SUMIFS('Cuentas CRM y homologación'!$R$2:$R$22,'Cuentas CRM y homologación'!$W$2:$W$22,$A11) -> 0 | Q11: =SUMIFS('Cuentas CRM y homologación'!$S$2:$S$22,'Cuentas CRM y homologación'!$W$2:$W$22,$A11) -> 0 | R11: =SUMIFS('Cuentas CRM y homologación'!$T$2:$T$22,'Cuentas CRM y homologación'!$W$2:$W$22,$A11) -> 0 | S11: El Reporte Anual 2023 declara 7 plantas de pollo y SENASICA muestra 6 rastros de aves a nombre de Bachoco. | T11: -
A12: BCH-018 | B12: Complejo sin confirmar | C12: Complejo Hermosillo (planta procesadora de aves y/o planta de alimento: no confirmadas) | D12: Hermosillo | E12: Sonora | F12: PENDIENTE | G12: ND | H12: https://www.bmv.com.mx/docs-pub/infoanua/infoanua_1378033_2023_1.pdf | https://www.agricultura.gob.mx/sites/default/files/sagarpa/document/2025/12/04/2250/04122025-padron-plantas-rendimiento.csv | I12: 2024-04/05 (fecha exacta ND) | 2025-12-04 (inferida de la ruta del URL) | J12: Pendiente | K12: Por confirmar | L12: Bchoco S.A. de C.V. - Planta Hermosillo | M12: La cuenta "Bchoco ... Hermosillo" (Carretera Sahurita Km 3.5, Parque Industrial, CP 83299, tal como está en el CRM) coincide en ciudad con el ex complejo Hermosillo. No hay domicilio verificado de la planta de aves. | N12: =SUMIFS('Cuentas CRM y homologación'!$P$2:$P$22,'Cuentas CRM y homologación'!$W$2:$W$22,$A12) -> 0 | O12: =SUMIFS('Cuentas CRM y homologación'!$Q$2:$Q$22,'Cuentas CRM y homologación'!$W$2:$W$22,$A12) -> 1 | P12: =SUMIFS('Cuentas CRM y homologación'!$R$2:$R$22,'Cuentas CRM y homologación'!$W$2:$W$22,$A12) -> 0 | Q12: =SUMIFS('Cuentas CRM y homologación'!$S$2:$S$22,'Cuentas CRM y homologación'!$W$2:$W$22,$A12) -> 0 | R12: =SUMIFS('Cuentas CRM y homologación'!$T$2:$T$22,'Cuentas CRM y homologación'!$W$2:$W$22,$A12) -> 1 | S12: El CP 83299 es el mismo del rastro porcino TIF 66 de Norson (BCH-032): riesgo de mezclar sitios. Confirmar en visita qué instalación es. | T12: -
A13: BCH-019 | B13: Complejo sin confirmar | C13: Planta procesadora de aves Coatzacoalcos (Complejo Istmo): operación actual no confirmada | D13: Coatzacoalcos | E13: Veracruz | F13: PENDIENTE | G13: ND | H13: https://www.bmv.com.mx/docs-pub/infoanua/infoanua_1378033_2023_1.pdf | https://rinacional.tecnm.mx/handle/TecNM/6281 | I13: 2024-04/05 (fecha exacta ND) | 2009-05 | J13: Pendiente | K13: Por confirmar | L13: Bachoco, S.A. de C.V. - Planta Coatzacoalcos | M13: La cuenta "Planta Coatzacoalcos" (Carretera Transístmica Km 7.5) coincide en ciudad con el ex complejo Coatzacoalcos. La única evidencia pública de operación es una tesis de 2009. | N13: =SUMIFS('Cuentas CRM y homologación'!$P$2:$P$22,'Cuentas CRM y homologación'!$W$2:$W$22,$A13) -> 1 | O13: =SUMIFS('Cuentas CRM y homologación'!$Q$2:$Q$22,'Cuentas CRM y homologación'!$W$2:$W$22,$A13) -> 1 | P13: =SUMIFS('Cuentas CRM y homologación'!$R$2:$R$22,'Cuentas CRM y homologación'!$W$2:$W$22,$A13) -> 0 | Q13: =SUMIFS('Cuentas CRM y homologación'!$S$2:$S$22,'Cuentas CRM y homologación'!$W$2:$W$22,$A13) -> 1 | R13: =SUMIFS('Cuentas CRM y homologación'!$T$2:$T$22,'Cuentas CRM y homologación'!$W$2:$W$22,$A13) -> 1 | S13: Tiene 1 ganada (2024) y 1 perdida (2025) registradas en el CRM. Falta confirmar qué instalación es. | T13: -
A14: BCH-020 | B14: Planta de rendimiento (subproductos) | C14: Planta de rendimiento Bachoco - Celaya | D14: Celaya | E14: Guanajuato | F14: PENDIENTE (el padrón solo da municipio y CP 38010) | G14: ND | H14: https://www.agricultura.gob.mx/sites/default/files/sagarpa/document/2025/12/04/2250/04122025-padron-plantas-rendimiento.csv | I14: 2025-12-04 (inferida de la ruta del URL) | J14: Confirmado | K14: Mismo municipio que BCH-010; predio por confirmar | L14: - | M14: Planta de rendimiento (subproductos) registrada en SADER en Celaya con CP 38010; el rastro BCH-010 tiene CP 38020. No se sabe si es el mismo predio. | N14: =SUMIFS('Cuentas CRM y homologación'!$P$2:$P$22,'Cuentas CRM y homologación'!$W$2:$W$22,$A14) -> 0 | O14: =SUMIFS('Cuentas CRM y homologación'!$Q$2:$Q$22,'Cuentas CRM y homologación'!$W$2:$W$22,$A14) -> 0 | P14: =SUMIFS('Cuentas CRM y homologación'!$R$2:$R$22,'Cuentas CRM y homologación'!$W$2:$W$22,$A14) -> 0 | Q14: =SUMIFS('Cuentas CRM y homologación'!$S$2:$S$22,'Cuentas CRM y homologación'!$W$2:$W$22,$A14) -> 0 | R14: =SUMIFS('Cuentas CRM y homologación'!$T$2:$T$22,'Cuentas CRM y homologación'!$W$2:$W$22,$A14) -> 0 | S14: Las cuentas 2, 4 (Corp) y 6 del CRM también tienen CP 38010; no basta para ligarlas. | T14: -
A15: BCH-021 | B15: Planta de rendimiento (subproductos) | C15: Planta de rendimiento Bachoco - Hermosillo ('planta sonora') | D15: Hermosillo | E15: Sonora | F15: PENDIENTE (el padrón solo da municipio y CP 83243) | G15: ND | H15: https://www.agricultura.gob.mx/sites/default/files/sagarpa/document/2025/12/04/2250/04122025-padron-plantas-rendimiento.csv | I15: 2025-12-04 (inferida de la ruta del URL) | J15: Confirmado | K15: Mismo municipio que BCH-018; predio por confirmar | L15: - | M15: Planta de rendimiento registrada en SADER en Hermosillo (CP 83243). BCH-018 (complejo Hermosillo) no está confirmado como planta de aves. | N15: =SUMIFS('Cuentas CRM y homologación'!$P$2:$P$22,'Cuentas CRM y homologación'!$W$2:$W$22,$A15) -> 0 | O15: =SUMIFS('Cuentas CRM y homologación'!$Q$2:$Q$22,'Cuentas CRM y homologación'!$W$2:$W$22,$A15) -> 0 | P15: =SUMIFS('Cuentas CRM y homologación'!$R$2:$R$22,'Cuentas CRM y homologación'!$W$2:$W$22,$A15) -> 0 | Q15: =SUMIFS('Cuentas CRM y homologación'!$S$2:$S$22,'Cuentas CRM y homologación'!$W$2:$W$22,$A15) -> 0 | R15: =SUMIFS('Cuentas CRM y homologación'!$T$2:$T$22,'Cuentas CRM y homologación'!$W$2:$W$22,$A15) -> 0 | T15: -
A16: BCH-022 | B16: Planta de rendimiento (subproductos) | C16: Planta de rendimiento Bachoco - Culiacán | D16: Culiacán | E16: Sinaloa | F16: PENDIENTE (el padrón solo da municipio y CP 80110) | G16: ND | H16: https://www.agricultura.gob.mx/sites/default/files/sagarpa/document/2025/12/04/2250/04122025-padron-plantas-rendimiento.csv | I16: 2025-12-04 (inferida de la ruta del URL) | J16: Confirmado | K16: Mismo municipio que BCH-015; predio por confirmar | L16: - | M16: Planta de rendimiento registrada en SADER en Culiacán con CP 80110; el rastro BCH-015 tiene CP 80100. No se sabe si es el mismo predio. | N16: =SUMIFS('Cuentas CRM y homologación'!$P$2:$P$22,'Cuentas CRM y homologación'!$W$2:$W$22,$A16) -> 0 | O16: =SUMIFS('Cuentas CRM y homologación'!$Q$2:$Q$22,'Cuentas CRM y homologación'!$W$2:$W$22,$A16) -> 0 | P16: =SUMIFS('Cuentas CRM y homologación'!$R$2:$R$22,'Cuentas CRM y homologación'!$W$2:$W$22,$A16) -> 0 | Q16: =SUMIFS('Cuentas CRM y homologación'!$S$2:$S$22,'Cuentas CRM y homologación'!$W$2:$W$22,$A16) -> 0 | R16: =SUMIFS('Cuentas CRM y homologación'!$T$2:$T$22,'Cuentas CRM y homologación'!$W$2:$W$22,$A16) -> 0 | T16: -
A17: BCH-023 | B17: Planta de rendimiento (subproductos) | C17: Planta de rendimiento Bachoco - 'planta tecamachalco' (en Huixcolotla) | D17: San Salvador Huixcolotla | E17: Puebla | F17: PENDIENTE (el padrón solo da municipio y CP 75482) | G17: ND | H17: https://www.agricultura.gob.mx/sites/default/files/sagarpa/document/2025/12/04/2250/04122025-padron-plantas-rendimiento.csv | I17: 2025-12-04 (inferida de la ruta del URL) | J17: Confirmado | K17: Mismo municipio que BCH-014; predio por confirmar | L17: - | M17: Planta de rendimiento registrada en SADER en Huixcolotla con CP 75482; el rastro BCH-014 tiene CP 75440. | N17: =SUMIFS('Cuentas CRM y homologación'!$P$2:$P$22,'Cuentas CRM y homologación'!$W$2:$W$22,$A17) -> 0 | O17: =SUMIFS('Cuentas CRM y homologación'!$Q$2:$Q$22,'Cuentas CRM y homologación'!$W$2:$W$22,$A17) -> 0 | P17: =SUMIFS('Cuentas CRM y homologación'!$R$2:$R$22,'Cuentas CRM y homologación'!$W$2:$W$22,$A17) -> 0 | Q17: =SUMIFS('Cuentas CRM y homologación'!$S$2:$S$22,'Cuentas CRM y homologación'!$W$2:$W$22,$A17) -> 0 | R17: =SUMIFS('Cuentas CRM y homologación'!$T$2:$T$22,'Cuentas CRM y homologación'!$W$2:$W$22,$A17) -> 0 | T17: -
A18: BCH-024 | B18: Planta de rendimiento (subproductos) | C18: Planta de rendimiento Bachoco - 'planta lagos' (en Unión de San Antonio) | D18: Unión de San Antonio | E18: Jalisco | F18: PENDIENTE (el padrón solo da municipio y CP 47450) | G18: ND | H18: https://www.agricultura.gob.mx/sites/default/files/sagarpa/document/2025/12/04/2250/04122025-padron-plantas-rendimiento.csv | I18: 2025-12-04 (inferida de la ruta del URL) | J18: Confirmado | K18: Mismo municipio que BCH-011; predio por confirmar | L18: - | M18: Planta de rendimiento registrada en SADER en Unión de San Antonio con CP 47450; el rastro BCH-011 tiene CP 47570 (SENASICA). Dos fuentes oficiales dan CP distinto. | N18: =SUMIFS('Cuentas CRM y homologación'!$P$2:$P$22,'Cuentas CRM y homologación'!$W$2:$W$22,$A18) -> 0 | O18: =SUMIFS('Cuentas CRM y homologación'!$Q$2:$Q$22,'Cuentas CRM y homologación'!$W$2:$W$22,$A18) -> 0 | P18: =SUMIFS('Cuentas CRM y homologación'!$R$2:$R$22,'Cuentas CRM y homologación'!$W$2:$W$22,$A18) -> 0 | Q18: =SUMIFS('Cuentas CRM y homologación'!$S$2:$S$22,'Cuentas CRM y homologación'!$W$2:$W$22,$A18) -> 0 | R18: =SUMIFS('Cuentas CRM y homologación'!$T$2:$T$22,'Cuentas CRM y homologación'!$W$2:$W$22,$A18) -> 0 | T18: -
A19: BCH-025 | B19: Planta de rendimiento (subproductos) | C19: Planta de rendimiento Bachoco - 'planta nuevo leon' (Ciénega de Flores) | D19: Ciénega de Flores | E19: Nuevo León | F19: PENDIENTE (el padrón solo da municipio y CP 65550) | G19: ND | H19: https://www.agricultura.gob.mx/sites/default/files/sagarpa/document/2025/12/04/2250/04122025-padron-plantas-rendimiento.csv | I19: 2025-12-04 (inferida de la ruta del URL) | J19: Confirmado | K19: Mismo municipio que BCH-013; predio por confirmar | L19: - | M19: Planta de rendimiento registrada en SADER en Ciénega de Flores con el mismo CP 65550 que el rastro. Mismo complejo probable (HIPÓTESIS por CP igual). | N19: =SUMIFS('Cuentas CRM y homologación'!$P$2:$P$22,'Cuentas CRM y homologación'!$W$2:$W$22,$A19) -> 0 | O19: =SUMIFS('Cuentas CRM y homologación'!$Q$2:$Q$22,'Cuentas CRM y homologación'!$W$2:$W$22,$A19) -> 0 | P19: =SUMIFS('Cuentas CRM y homologación'!$R$2:$R$22,'Cuentas CRM y homologación'!$W$2:$W$22,$A19) -> 0 | Q19: =SUMIFS('Cuentas CRM y homologación'!$S$2:$S$22,'Cuentas CRM y homologación'!$W$2:$W$22,$A19) -> 0 | R19: =SUMIFS('Cuentas CRM y homologación'!$T$2:$T$22,'Cuentas CRM y homologación'!$W$2:$W$22,$A19) -> 0 | T19: -
A20: BCH-026 | B20: Planta de rendimiento (subproductos) | C20: Planta de rendimiento Bachoco - Umán | D20: Umán | E20: Yucatán | F20: PENDIENTE (el padrón solo da municipio y CP 97390) | G20: ND | H20: https://www.agricultura.gob.mx/sites/default/files/sagarpa/document/2025/12/04/2250/04122025-padron-plantas-rendimiento.csv | I20: 2025-12-04 (inferida de la ruta del URL) | J20: Confirmado | K20: Mismo municipio que BCH-016; predio por confirmar | L20: - | M20: Planta de rendimiento registrada en SADER en Umán con el mismo CP 97390 que el rastro. Mismo complejo probable (HIPÓTESIS por CP igual). | N20: =SUMIFS('Cuentas CRM y homologación'!$P$2:$P$22,'Cuentas CRM y homologación'!$W$2:$W$22,$A20) -> 0 | O20: =SUMIFS('Cuentas CRM y homologación'!$Q$2:$Q$22,'Cuentas CRM y homologación'!$W$2:$W$22,$A20) -> 0 | P20: =SUMIFS('Cuentas CRM y homologación'!$R$2:$R$22,'Cuentas CRM y homologación'!$W$2:$W$22,$A20) -> 0 | Q20: =SUMIFS('Cuentas CRM y homologación'!$S$2:$S$22,'Cuentas CRM y homologación'!$W$2:$W$22,$A20) -> 0 | R20: =SUMIFS('Cuentas CRM y homologación'!$T$2:$T$22,'Cuentas CRM y homologación'!$W$2:$W$22,$A20) -> 0 | T20: -
A21: BCH-030 | B21: Planta porcina (rastro TIF) | C21: Rastro porcino TIF 57 - Sonora Agropecuaria, S.A. de C.V. (SASA) | D21: Navojoa | E21: Sonora | F21: Carretera México-Nogales Km. 1778, Col. Parque Industrial, C.P. 85895 | G21: ND | H21: https://campo.nl.gob.mx/pdf/directorios/Directorio_TIF.pdf | https://www.bmv.com.mx/docs-pub/infoanua/infoanua_1378033_2023_1.pdf | https://bmeditores.mx/porcicultura/rastro-tif-de-sonora-fuera-de-operacion-por-polo-opormex-pide-respuesta-urgente/ | I21: 2024 (año indicado en el documento; fecha exacta ND) | 2024-04/05 (fecha exacta ND) | 2026-10-01 | J21: Confirmado | K21: No | L21: - | M21: Sin cuenta del CRM en Navojoa. | N21: =SUMIFS('Cuentas CRM y homologación'!$P$2:$P$22,'Cuentas CRM y homologación'!$W$2:$W$22,$A21) -> 0 | O21: =SUMIFS('Cuentas CRM y homologación'!$Q$2:$Q$22,'Cuentas CRM y homologación'!$W$2:$W$22,$A21) -> 0 | P21: =SUMIFS('Cuentas CRM y homologación'!$R$2:$R$22,'Cuentas CRM y homologación'!$W$2:$W$22,$A21) -> 0 | Q21: =SUMIFS('Cuentas CRM y homologación'!$S$2:$S$22,'Cuentas CRM y homologación'!$W$2:$W$22,$A21) -> 0 | R21: =SUMIFS('Cuentas CRM y homologación'!$T$2:$T$22,'Cuentas CRM y homologación'!$W$2:$W$22,$A21) -> 0 | S21: Subsidiaria de Bachoco (Sonora Agropecuaria). No es de aves. No confundir con Grupo Kowi (otra empresa, también en Navojoa), cuyo rastro se inundó por el huracán Polo (nota de BM Editores, 2026-10-01); no hay reporte de efectos en la subsidiaria de Bachoco (pendiente). | T21: Fuente confirmada; es el negocio porcino (otra operación).
A22: BCH-031 | B22: Planta porcina (rastro TIF) | C22: Rastro porcino TIF 467 - Sonora Agropecuaria, S.A. de C.V. (SASA) | D22: Atotonilco el Alto | E22: Jalisco | F22: Km. 86.1 Carretera Guadalajara-La Piedad, municipio de Atotonilco el Alto, C.P. 47750 | G22: ND | H22: https://campo.nl.gob.mx/pdf/directorios/Directorio_TIF.pdf | https://www.bmv.com.mx/docs-pub/infoanua/infoanua_1378033_2023_1.pdf | I22: 2024 (año indicado en el documento; fecha exacta ND) | 2024-04/05 (fecha exacta ND) | J22: Confirmado | K22: No | L22: - | M22: Sin cuenta del CRM en Atotonilco el Alto. | N22: =SUMIFS('Cuentas CRM y homologación'!$P$2:$P$22,'Cuentas CRM y homologación'!$W$2:$W$22,$A22) -> 0 | O22: =SUMIFS('Cuentas CRM y homologación'!$Q$2:$Q$22,'Cuentas CRM y homologación'!$W$2:$W$22,$A22) -> 0 | P22: =SUMIFS('Cuentas CRM y homologación'!$R$2:$R$22,'Cuentas CRM y homologación'!$W$2:$W$22,$A22) -> 0 | Q22: =SUMIFS('Cuentas CRM y homologación'!$S$2:$S$22,'Cuentas CRM y homologación'!$W$2:$W$22,$A22) -> 0 | R22: =SUMIFS('Cuentas CRM y homologación'!$T$2:$T$22,'Cuentas CRM y homologación'!$W$2:$W$22,$A22) -> 0 | S22: Subsidiaria de Bachoco (Sonora Agropecuaria); rastro porcino. | T22: Fuente confirmada; es el negocio porcino (otra operación).
A23: BCH-032 | B23: Planta porcina (rastro TIF) | C23: Rastro porcino TIF 66 (Norson; razón social en SENASICA: Frigorífico Agropecuaria Sonorense, S. de R.L. de C.V.) | D23: Hermosillo | E23: Sonora | F23: Calle de la Plata S/N, Parque Industrial, C.P. 83299 | G23: ND | H23: https://campo.nl.gob.mx/pdf/directorios/Directorio_TIF.pdf | https://en.grupobachoco.com/wp-content/downloads/2023/Bachoco-Norson-July-2023-ENG.pdf | https://expansion.mx/empresas/2023/07/12/bachoco-concluye-compra-norson-holding | I23: 2024 (año indicado en el documento; fecha exacta ND) | 2023-07-12 | 2023-07-12 | J23: Hipótesis | K23: No | L23: - | M23: Sin cuenta del CRM identificada como Norson. | N23: =SUMIFS('Cuentas CRM y homologación'!$P$2:$P$22,'Cuentas CRM y homologación'!$W$2:$W$22,$A23) -> 0 | O23: =SUMIFS('Cuentas CRM y homologación'!$Q$2:$Q$22,'Cuentas CRM y homologación'!$W$2:$W$22,$A23) -> 0 | P23: =SUMIFS('Cuentas CRM y homologación'!$R$2:$R$22,'Cuentas CRM y homologación'!$W$2:$W$22,$A23) -> 0 | Q23: =SUMIFS('Cuentas CRM y homologación'!$S$2:$S$22,'Cuentas CRM y homologación'!$W$2:$W$22,$A23) -> 0 | R23: =SUMIFS('Cuentas CRM y homologación'!$T$2:$T$22,'Cuentas CRM y homologación'!$W$2:$W$22,$A23) -> 0 | S23: Pertenece a Bachoco desde la compra de Norson (jul-2023), pero la razón social en SENASICA no dice Norson: hipótesis. | T23: Evidencia débil: confirmar antes de dar de alta.
A24: BCH-033 | B24: Planta porcina (rastro TIF) | C24: Rastro porcino/bovino TIF 62 (Norson; razón social en SENASICA: Promotora Comercial Alpro, S. de R.L. de C.V.) | D24: Hermosillo | E24: Sonora | F24: Boulevard de los Ganaderos S/N, Sector Industrial Presa, C.P. 83293 | G24: ND | H24: https://campo.nl.gob.mx/pdf/directorios/Directorio_TIF.pdf | https://en.grupobachoco.com/wp-content/downloads/2023/Bachoco-Norson-July-2023-ENG.pdf | I24: 2024 (año indicado en el documento; fecha exacta ND) | 2023-07-12 | J24: Hipótesis | K24: No | L24: - | M24: Sin cuenta del CRM identificada como Norson. | N24: =SUMIFS('Cuentas CRM y homologación'!$P$2:$P$22,'Cuentas CRM y homologación'!$W$2:$W$22,$A24) -> 0 | O24: =SUMIFS('Cuentas CRM y homologación'!$Q$2:$Q$22,'Cuentas CRM y homologación'!$W$2:$W$22,$A24) -> 0 | P24: =SUMIFS('Cuentas CRM y homologación'!$R$2:$R$22,'Cuentas CRM y homologación'!$W$2:$W$22,$A24) -> 0 | Q24: =SUMIFS('Cuentas CRM y homologación'!$S$2:$S$22,'Cuentas CRM y homologación'!$W$2:$W$22,$A24) -> 0 | R24: =SUMIFS('Cuentas CRM y homologación'!$T$2:$T$22,'Cuentas CRM y homologación'!$W$2:$W$22,$A24) -> 0 | S24: Misma observación que BCH-032. | T24: Evidencia débil: confirmar antes de dar de alta.
A25: BCH-040 | B25: Valor agregado | C25: Trosi de Carne, S.A. de C.V. (Trosi) | D25: Monterrey | E25: Nuevo León | F25: PENDIENTE | G25: ND | H25: https://www.bmv.com.mx/docs-pub/infoanua/infoanua_1378033_2023_1.pdf | I25: 2024-04/05 (fecha exacta ND) | J25: Hipótesis | K25: No | L25: - | M25: Sin cuenta del CRM en Monterrey identificada como Trosi. | N25: =SUMIFS('Cuentas CRM y homologación'!$P$2:$P$22,'Cuentas CRM y homologación'!$W$2:$W$22,$A25) -> 0 | O25: =SUMIFS('Cuentas CRM y homologación'!$Q$2:$Q$22,'Cuentas CRM y homologación'!$W$2:$W$22,$A25) -> 0 | P25: =SUMIFS('Cuentas CRM y homologación'!$R$2:$R$22,'Cuentas CRM y homologación'!$W$2:$W$22,$A25) -> 0 | Q25: =SUMIFS('Cuentas CRM y homologación'!$S$2:$S$22,'Cuentas CRM y homologación'!$W$2:$W$22,$A25) -> 0 | R25: =SUMIFS('Cuentas CRM y homologación'!$T$2:$T$22,'Cuentas CRM y homologación'!$W$2:$W$22,$A25) -> 0 | S25: Domicilio pendiente. | T25: Evidencia débil: confirmar antes de dar de alta.
A26: BCH-041 | B26: Valor agregado | C26: RYC Alimentos, S.A. de C.V. (2 plantas multiproteína) | D26: Puebla | E26: Puebla | F26: PENDIENTE | G26: ND | H26: https://www.sec.gov/Archives/edgar/data/1044896/000141057822001105/iba-20211231x20f.htm | https://www.bmv.com.mx/docs-pub/infoanua/infoanua_1378033_2023_1.pdf | I26: 2022-04-29 | 2024-04/05 (fecha exacta ND) | J26: Confirmado | K26: No | L26: - | M26: Sin cuenta del CRM en Puebla identificada como RYC. | N26: =SUMIFS('Cuentas CRM y homologación'!$P$2:$P$22,'Cuentas CRM y homologación'!$W$2:$W$22,$A26) -> 0 | O26: =SUMIFS('Cuentas CRM y homologación'!$Q$2:$Q$22,'Cuentas CRM y homologación'!$W$2:$W$22,$A26) -> 0 | P26: =SUMIFS('Cuentas CRM y homologación'!$R$2:$R$22,'Cuentas CRM y homologación'!$W$2:$W$22,$A26) -> 0 | Q26: =SUMIFS('Cuentas CRM y homologación'!$S$2:$S$22,'Cuentas CRM y homologación'!$W$2:$W$22,$A26) -> 0 | R26: =SUMIFS('Cuentas CRM y homologación'!$T$2:$T$22,'Cuentas CRM y homologación'!$W$2:$W$22,$A26) -> 0 | S26: RYC Alimentos pertenece a Bachoco desde ene-2022 (2 plantas multiproteína en Puebla); domicilios pendientes. | T26: Fuente confirmada: candidato a dar de alta si interesa.
A27: BCH-042 | B27: Alimento para mascotas | C27: Proveedora La Perla, S.A. de C.V. (alimento para mascotas) | D27: PENDIENTE (Querétaro) | E27: Querétaro | F27: PENDIENTE | G27: ND | H27: https://www.bmv.com.mx/docs-pub/infoanua/infoanua_1378033_2023_1.pdf | https://www.sec.gov/Archives/edgar/data/1044896/000141057822001105/iba-20211231x20f.htm | I27: 2024-04/05 (fecha exacta ND) | 2022-04-29 | J27: Confirmado | K27: No | L27: - | M27: Sin cuenta del CRM identificada como La Perla. | N27: =SUMIFS('Cuentas CRM y homologación'!$P$2:$P$22,'Cuentas CRM y homologación'!$W$2:$W$22,$A27) -> 0 | O27: =SUMIFS('Cuentas CRM y homologación'!$Q$2:$Q$22,'Cuentas CRM y homologación'!$W$2:$W$22,$A27) -> 0 | P27: =SUMIFS('Cuentas CRM y homologación'!$R$2:$R$22,'Cuentas CRM y homologación'!$W$2:$W$22,$A27) -> 0 | Q27: =SUMIFS('Cuentas CRM y homologación'!$S$2:$S$22,'Cuentas CRM y homologación'!$W$2:$W$22,$A27) -> 0 | R27: =SUMIFS('Cuentas CRM y homologación'!$T$2:$T$22,'Cuentas CRM y homologación'!$W$2:$W$22,$A27) -> 0 | S27: Planta de alimento para mascotas en Querétaro; municipio y domicilio pendientes. | T27: Fuente confirmada: candidato a dar de alta si interesa.
A28: BCH-050 | B28: Alimento balanceado | C28: Planta CAMPI Mérida | D28: Mérida | E28: Yucatán | F28: Calle 17 No. 400x20, Ciudad Industrial | G28: 40 toneladas/hora | H28: https://campi-alimentos.com/plantas/ | https://campi-alimentos.com/nosotros/ | I28: ND (sin fecha) | ND (sin fecha) | J28: Confirmado | K28: Por confirmar | L28: Bachoco, S.A. de C.V. - Planta De Alimentos 1 Bachoco S.A. De C.V. | M28: La cuenta "Planta De Alimentos 1" (José María Castro SN, Ciudad Industrial, Mérida, CP 97288) coincide en tipo (alimento) y zona (Ciudad Industrial) con la planta CAMPI; las calles no coinciden (Calle 17 No. 400 x 20). | N28: =SUMIFS('Cuentas CRM y homologación'!$P$2:$P$22,'Cuentas CRM y homologación'!$W$2:$W$22,$A28) -> 0 | O28: =SUMIFS('Cuentas CRM y homologación'!$Q$2:$Q$22,'Cuentas CRM y homologación'!$W$2:$W$22,$A28) -> 0 | P28: =SUMIFS('Cuentas CRM y homologación'!$R$2:$R$22,'Cuentas CRM y homologación'!$W$2:$W$22,$A28) -> 0 | Q28: =SUMIFS('Cuentas CRM y homologación'!$S$2:$S$22,'Cuentas CRM y homologación'!$W$2:$W$22,$A28) -> 0 | R28: =SUMIFS('Cuentas CRM y homologación'!$T$2:$T$22,'Cuentas CRM y homologación'!$W$2:$W$22,$A28) -> 0 | S28: Dos cuentas del CRM (la 15 y la 19) caen en la Ciudad Industrial de Mérida (CP 97288) y solo se conoce una planta pública ahí. Confirmar si son la misma. | T28: -
A29: BCH-051 | B29: Alimento balanceado | C29: Planta CAMPI Cuautla | D29: Cuautla | E29: Morelos | F29: Vía de FFCC México-Puebla No. 3, Col. Cuatlixco | G29: 19 toneladas/hora | H29: https://campi-alimentos.com/plantas/ | I29: ND (sin fecha) | J29: Confirmado | K29: Sí | L29: Bachoco S.A de C.V - Cuautla | M29: Mismo municipio, calle y número: CRM "México Puebla 3, Estrella, Cuautla" y CAMPI "Vía de FFCC México-Puebla No. 3, Col. Cuatlixco". La colonia no coincide. | N29: =SUMIFS('Cuentas CRM y homologación'!$P$2:$P$22,'Cuentas CRM y homologación'!$W$2:$W$22,$A29) -> 0 | O29: =SUMIFS('Cuentas CRM y homologación'!$Q$2:$Q$22,'Cuentas CRM y homologación'!$W$2:$W$22,$A29) -> 0 | P29: =SUMIFS('Cuentas CRM y homologación'!$R$2:$R$22,'Cuentas CRM y homologación'!$W$2:$W$22,$A29) -> 0 | Q29: =SUMIFS('Cuentas CRM y homologación'!$S$2:$S$22,'Cuentas CRM y homologación'!$W$2:$W$22,$A29) -> 0 | R29: =SUMIFS('Cuentas CRM y homologación'!$T$2:$T$22,'Cuentas CRM y homologación'!$W$2:$W$22,$A29) -> 0 | S29: Cuenta sin oportunidades registradas. Es planta de alimento balanceado, no de aves. La página de CAMPI no tiene fecha: vigencia no verificada. | T29: -
A30: BCH-052 | B30: Alimento balanceado | C30: Planta CAMPI Chinameca | D30: Chinameca | E30: Veracruz | F30: Calle Altamirano s/n | G30: 20 toneladas/hora | H30: https://campi-alimentos.com/plantas/ | I30: ND (sin fecha) | J30: Confirmado | K30: No | L30: - | M30: Sin cuenta del CRM en Chinameca. | N30: =SUMIFS('Cuentas CRM y homologación'!$P$2:$P$22,'Cuentas CRM y homologación'!$W$2:$W$22,$A30) -> 0 | O30: =SUMIFS('Cuentas CRM y homologación'!$Q$2:$Q$22,'Cuentas CRM y homologación'!$W$2:$W$22,$A30) -> 0 | P30: =SUMIFS('Cuentas CRM y homologación'!$R$2:$R$22,'Cuentas CRM y homologación'!$W$2:$W$22,$A30) -> 0 | Q30: =SUMIFS('Cuentas CRM y homologación'!$S$2:$S$22,'Cuentas CRM y homologación'!$W$2:$W$22,$A30) -> 0 | R30: =SUMIFS('Cuentas CRM y homologación'!$T$2:$T$22,'Cuentas CRM y homologación'!$W$2:$W$22,$A30) -> 0 | S30: Es la presencia verificable de Bachoco en el Istmo; no hay evidencia pública de planta en Tierra Blanca. | T30: Fuente confirmada: candidato a dar de alta si interesa.
A31: BCH-053 | B31: Alimento balanceado | C31: Planta de Alimentos Grupo Bachoco (Operación Monterrey) | D31: Salinas Victoria | E31: Nuevo León | F31: PENDIENTE | G31: ND | H31: https://www.nl.gob.mx/es/boletines/asiste-secretaria-de-medio-ambiente-presentacion-de-inversion-ambiental-de-grupo-bachoco | https://www.notimx.mx/2026/07/bachoco-impulsa-una-operacion-mas.html | I31: 2026-07-22 | 2026-07-23 | J31: Confirmado | K31: No | L31: - | M31: Sin cuenta del CRM en Salinas Victoria. | N31: =SUMIFS('Cuentas CRM y homologación'!$P$2:$P$22,'Cuentas CRM y homologación'!$W$2:$W$22,$A31) -> 0 | O31: =SUMIFS('Cuentas CRM y homologación'!$Q$2:$Q$22,'Cuentas CRM y homologación'!$W$2:$W$22,$A31) -> 0 | P31: =SUMIFS('Cuentas CRM y homologación'!$R$2:$R$22,'Cuentas CRM y homologación'!$W$2:$W$22,$A31) -> 0 | Q31: =SUMIFS('Cuentas CRM y homologación'!$S$2:$S$22,'Cuentas CRM y homologación'!$W$2:$W$22,$A31) -> 0 | R31: =SUMIFS('Cuentas CRM y homologación'!$T$2:$T$22,'Cuentas CRM y homologación'!$W$2:$W$22,$A31) -> 0 | S31: Proyecto ambiental de más de MXN 31 millones ejecutado o presentado en jul-2026 (boletín del Gobierno de Nuevo León); es de control ambiental, no de ampliación. Otra fuente (NotiMx) dice que el monto no se divulgó. | T31: Fuente confirmada: candidato a dar de alta si interesa.
A32: BCH-054 | B32: Alimento balanceado | C32: Planta Forrajera de Querétaro (CAMPI, división Bajío) | D32: PENDIENTE (Querétaro) | E32: Querétaro | F32: PENDIENTE | G32: ND | H32: https://campi-alimentos.com/nosotros/ | I32: ND (sin fecha) | J32: Hipótesis | K32: No | L32: - | M32: Sin cuenta del CRM en Querétaro. | N32: =SUMIFS('Cuentas CRM y homologación'!$P$2:$P$22,'Cuentas CRM y homologación'!$W$2:$W$22,$A32) -> 0 | O32: =SUMIFS('Cuentas CRM y homologación'!$Q$2:$Q$22,'Cuentas CRM y homologación'!$W$2:$W$22,$A32) -> 0 | P32: =SUMIFS('Cuentas CRM y homologación'!$R$2:$R$22,'Cuentas CRM y homologación'!$W$2:$W$22,$A32) -> 0 | Q32: =SUMIFS('Cuentas CRM y homologación'!$S$2:$S$22,'Cuentas CRM y homologación'!$W$2:$W$22,$A32) -> 0 | R32: =SUMIFS('Cuentas CRM y homologación'!$T$2:$T$22,'Cuentas CRM y homologación'!$W$2:$W$22,$A32) -> 0 | S32: Solo un sitio de CAMPI menciona la planta forrajera de Querétaro; sin fecha ni domicilio. | T32: Evidencia débil: confirmar antes de dar de alta.
... A43: BCH-090 | B43: Laboratorio | C43: Laboratorio de vacunas y farmacéuticos veterinarios (PEC LAB; posible vínculo con Pecuarius, no confirmado) | D43: PENDIENTE | E43: PENDIENTE | F43: PENDIENTE | G43: ND | H43: https://www.bmv.com.mx/docs-pub/infoanua/infoanua_1378033_2023_1.pdf | https://bmeditores.mx/avicultura/reconocen-a-grupo-bachoco-en-personalidad-del-sector-pecuario/ | I43: 2024-04/05 (fecha exacta ND) | 2025-03-12 | J43: Pendiente | K43: No | L43: - | M43: Sin cuenta del CRM identificada como laboratorio. | N43: =SUMIFS('Cuentas CRM y homologación'!$P$2:$P$22,'Cuentas CRM y homologación'!$W$2:$W$22,$A43) -> 0 | O43: =SUMIFS('Cuentas CRM y homologación'!$Q$2:$Q$22,'Cuentas CRM y homologación'!$W$2:$W$22,$A43) -> 0 | P43: =SUMIFS('Cuentas CRM y homologación'!$R$2:$R$22,'Cuentas CRM y homologación'!$W$2:$W$22,$A43) -> 0 | Q43: =SUMIFS('Cuentas CRM y homologación'!$S$2:$S$22,'Cuentas CRM y homologación'!$W$2:$W$22,$A43) -> 0 | R43: =SUMIFS('Cuentas CRM y homologación'!$T$2:$T$22,'Cuentas CRM y homologación'!$W$2:$W$22,$A43) -> 0 | S43: Ubicación pendiente. | T43: Sin ubicación publicada.

Sheet Cuentas CRM y homologación
A1: N° | B1: Cuenta en el CRM (nombre actual) | C1: Municipio (según domicilio) | D1: Estado | E1: Zona | F1: Domicilio registrado en el CRM | G1: Propietario CRM (histórico) | H1: Propietarios que aparecen en sus oportunidades | I1: Segmentación actual | J1: End Market actual | K1: Subcategoría actual | L1: Industria primaria actual | M1: Fecha de creación | N1: Creada por | O1: Contacto principal registrado | P1: Ganadas (todo el CRM) | Q1: Perdidas (todo el CRM) | R1: Abiertas (todo el CRM) | S1: Ganadas Elegibles | T1: Perdidas Elegibles | U1: Última ganada (todo el CRM) | V1: Problemas detectados (todos CONFIRMADO en el CRM) | W1: Sitio público asociado (ver hoja Plantas vs CRM) | X1: Base del cruce con el sitio público | Y1: PROPUESTA: nombre | Z1: PROPUESTA: End Market | AA1: PROPUESTA: Subcategoría | AB1: PROPUESTA: Segmentación | AC1: Acción sugerida y quién decide
A2: 1 | B2: Bachoco | C2: Ciudad Obregón | D2: Sonora | E2: Noroeste (Sonora/BC) | F2: Internacional 1848, 85065 Ciudad Obregón, Sonora,85065 CIUDAD OBREGON, SONORA,MEXICO | G2: Cesar Vázquez | H2: Johnatan Inactive Murillo | I2: End User | J2: Food & Beverage | K2: Manufacturing - Food Processing | L2: (vacío) | M2: 10-3-2023 12:20 PM | N2: Johnatan.MurilloVelarde | O2: No | P2: =COUNTIFS(Oportunidades!$C$2:$C$71,$B2,Oportunidades!$H$2:$H$71,"Ganada") -> 0 | Q2: =COUNTIFS(Oportunidades!$C$2:$C$71,$B2,Oportunidades!$H$2:$H$71,"Perdida") -> 2 | R2: =COUNTIFS(Oportunidades!$C$2:$C$71,$B2,Oportunidades!$H$2:$H$71,"Abierta") -> 0 | S2: =COUNTIFS(Oportunidades!$C$2:$C$71,$B2,Oportunidades!$H$2:$H$71,"Ganada",Oportunidades!$Z$2:$Z$71,"Elegible") -> 0 | T2: =COUNTIFS(Oportunidades!$C$2:$C$71,$B2,Oportunidades!$H$2:$H$71,"Perdida",Oportunidades!$Z$2:$Z$71,"Elegible") -> 1 | U2: =IF(P2=0,"-",_xlfn.MAXIFS(Oportunidades!$I$2:$I$71,Oportunidades!$C$2:$C$71,$B2,Oportunidades!$H$2:$H$71,"Ganada")) -> - | V2: Propietario no aparece en la hoja Team del archivo IR: confirmar vigencia; Sin contacto principal; Sin correo del contacto principal; Sin teléfono | W2: BCH-080 | X2: Por confirmar. La cuenta "Bachoco" (Av. Internacional 1848, Cd. Obregón) coincide en municipio con el CEDIS; la fuente no da domicilio. | Y2: Bachoco, S.A. de C.V. - Ciudad Obregón | Z2: Food & Beverage | AA2: Manufacturing - Food Processing | AB2: End User | AC2: Confirmar con quien la lleva (su propietario no aparece en la hoja Team) qué instalación es; revisar si es duplicada de la cuenta 8. Decide: dueño de la cuenta y administrador del CRM.
A3: 2 | B3: BACHOCO S.A. DE C.V. | C3: Celaya | D3: Guanajuato | E3: Bajío (Celaya) | F3: Av. Norte 11 Esq. Poniente 4 Cd. Industrial Celaya, Gto.,38010 CELAYA GTO, GUANAJUATO,MEXICO | G3: Ulises Sanchez | H3: Froylan Santiago Inactive Alcántara | I3: End User | J3: Food & Beverage | K3: Manufacturing - Food Processing | L3: (vacío) | M3: 6-1-2021 09:30 AM | N3: DATA.MIGRATION | O3: Sí | P3: =COUNTIFS(Oportunidades!$C$2:$C$71,$B3,Oportunidades!$H$2:$H$71,"Ganada") -> 3 | Q3: =COUNTIFS(Oportunidades!$C$2:$C$71,$B3,Oportunidades!$H$2:$H$71,"Perdida") -> 0 | R3: =COUNTIFS(Oportunidades!$C$2:$C$71,$B3,Oportunidades!$H$2:$H$71,"Abierta") -> 0 | S3: =COUNTIFS(Oportunidades!$C$2:$C$71,$B3,Oportunidades!$H$2:$H$71,"Ganada",Oportunidades!$Z$2:$Z$71,"Elegible") -> 0 | T3: =COUNTIFS(Oportunidades!$C$2:$C$71,$B3,Oportunidades!$H$2:$H$71,"Perdida",Oportunidades!$Z$2:$Z$71,"Elegible") -> 0 | U3: =IF(P3=0,"-",_xlfn.MAXIFS(Oportunidades!$I$2:$I$71,Oportunidades!$C$2:$C$71,$B3,Oportunidades!$H$2:$H$71,"Ganada")) -> 44527 | W3: Sin sitio público identificado | X3: Misma Ciudad Industrial de Celaya que la oficina corporativa (BCH-001), pero otro domicilio (Av. Norte 11 esq. Poniente 4). Ninguna fuente pública ubica una instalación ahí. | Y3: Bachoco, S.A. de C.V. - Celaya - [tipo por confirmar] | Z3: Food & Beverage | AA3: Manufacturing - Food Processing | AB3: End User | AC3: Preguntar a quien lleva la cuenta (propietario en el CRM: Ulises Sánchez; confirmar que sigue activo) si es un sitio distinto o duplicado de la cuenta Corp. Comparte contacto principal con Corp y con la cuenta 6. La planta de rendimiento BCH-020 tiene el mismo CP 38010, pero eso no basta para ligarla.
A4: 3 | B4: Bachoco, S.A. De C.V. - Tecamachalco | C4: Tecamachalco | D4: Puebla | E4: Puebla (Tecamachalco) | F4: México 150, Barrio de San Juan,,75484 TECAMACHALCO, PUEBLA,MEXICO | G4: Eliasib Luna | H4: Eliasib Luna; Alejandro Avila | I4: End User | J4: Food & Beverage | K4: Manufacturing - Food Processing | L4: (vacío) | M4: 6-1-2021 09:39 AM | N4: DATA.MIGRATION | O4: Sí | P4: =COUNTIFS(Oportunidades!$C$2:$C$71,$B4,Oportunidades!$H$2:$H$71,"Ganada") -> 10 | Q4: =COUNTIFS(Oportunidades!$C$2:$C$71,$B4,Oportunidades!$H$2:$H$71,"Perdida") -> 5 | R4: =COUNTIFS(Oportunidades!$C$2:$C$71,$B4,Oportunidades!$H$2:$H$71,"Abierta") -> 0 | S4: =COUNTIFS(Oportunidades!$C$2:$C$71,$B4,Oportunidades!$H$2:$H$71,"Ganada",Oportunidades!$Z$2:$Z$71,"Elegible") -> 10 | T4: =COUNTIFS(Oportunidades!$C$2:$C$71,$B4,Oportunidades!$H$2:$H$71,"Perdida",Oportunidades!$Z$2:$Z$71,"Elegible") -> 3 | U4: =IF(P4=0,"-",_xlfn.MAXIFS(Oportunidades!$I$2:$I$71,Oportunidades!$C$2:$C$71,$B4,Oportunidades!$H$2:$H$71,"Ganada")) -> 46216 | W4: BCH-014 | X4: Por confirmar. El predio oficial del rastro está en San Salvador Huixcolotla (Km 53 Puebla-Tehuacán, CP 75440); "Tecamachalco" es el nombre histórico del complejo. La cuenta del CRM dice Tecamachalco, Barrio de San Juan (CP 75484), domicilio que viene de directorios no oficiales. | Y4: Bachoco, S.A. de C.V. - Tecamachalco (o San Salvador Huixcolotla si se confirma que es el rastro) | Z4: Food & Beverage | AA4: Manufacturing - Food Processing | AB4: End User | AC4: Confirmar en visita el domicilio real del sitio atendido. Es la cuenta con ganadas más recientes (jul-2026).
A5: 4 | B5: Bachoco S.A. de C.V. - Corp | C5: Celaya | D5: Guanajuato | E5: Bajío (Celaya) | F5: Av. Tecnológico N° 401, Ciudad Industrial,38010 CELAYA, GUANAJUATO,MEXICO | G5: Ulises Sanchez | H5: Ulises Sanchez | I5: End User | J5: Food & Beverage | K5: Manufacturing - Food Processing | L5: (vacío) | M5: 6-1-2021 09:45 AM | N5: DATA.MIGRATION | O5: Sí | P5: =COUNTIFS(Oportunidades!$C$2:$C$71,$B5,Oportunidades!$H$2:$H$71,"Ganada") -> 1 | Q5: =COUNTIFS(Oportunidades!$C$2:$C$71,$B5,Oportunidades!$H$2:$H$71,"Perdida") -> 0 | R5: =COUNTIFS(Oportunidades!$C$2:$C$71,$B5,Oportunidades!$H$2:$H$71,"Abierta") -> 0 | S5: =COUNTIFS(Oportunidades!$C$2:$C$71,$B5,Oportunidades!$H$2:$H$71,"Ganada",Oportunidades!$Z$2:$Z$71,"Elegible") -> 1 | T5: =COUNTIFS(Oportunidades!$C$2:$C$71,$B5,Oportunidades!$H$2:$H$71,"Perdida",Oportunidades!$Z$2:$Z$71,"Elegible") -> 0 | U5: =IF(P5=0,"-",_xlfn.MAXIFS(Oportunidades!$I$2:$I$71,Oportunidades!$C$2:$C$71,$B5,Oportunidades!$H$2:$H$71,"Ganada")) -> 43946 | W5: BCH-001 | X5: Sí. Domicilio coincide: Av. Tecnológico No. 401, Ciudad Industrial, CP 38010, Celaya (cuenta "Corp"). La verificó la lista pública con el Reporte Anual 2023, el perfil de la BMV y el aviso de privacidad de bachoco.com. | Y5: Bachoco, S.A. de C.V. - Celaya - Corporativo | Z5: Food & Beverage | AA5: Manufacturing - Food Processing | AB5: End User | AC5: Dejar como cuenta corporativa. Pregunta para el administrador del CRM: ¿la segmentación correcta de una cuenta corporativa es "Corporate" o "End User"? Hoy la de Culiacán dice Corporate y esta dice End User.
A6: 5 | B6: Bachoco S.A. De C.V. - Veracruz | C6: Tierra Blanca | D6: Veracruz | E6: Veracruz | F6: Tierra Blanca-Sayula de Alemán, 5151 Centro,95150 TIERRA BLANCA, VERACRUZ,MEXICO | G6: Eliasib Luna | H6: Eliasib Luna | I6: End User | J6: Food & Beverage | K6: (vacío) | L6: (vacío) | M6: 6-1-2021 09:44 AM | N6: DATA.MIGRATION | O6: Sí | P6: =COUNTIFS(Oportunidades!$C$2:$C$71,$B6,Oportunidades!$H$2:$H$71,"Ganada") -> 3 | Q6: =COUNTIFS(Oportunidades!$C$2:$C$71,$B6,Oportunidades!$H$2:$H$71,"Perdida") -> 0 | R6: =COUNTIFS(Oportunidades!$C$2:$C$71,$B6,Oportunidades!$H$2:$H$71,"Abierta") -> 0 | S6: =COUNTIFS(Oportunidades!$C$2:$C$71,$B6,Oportunidades!$H$2:$H$71,"Ganada",Oportunidades!$Z$2:$Z$71,"Elegible") -> 3 | T6: =COUNTIFS(Oportunidades!$C$2:$C$71,$B6,Oportunidades!$H$2:$H$71,"Perdida",Oportunidades!$Z$2:$Z$71,"Elegible") -> 0 | U6: =IF(P6=0,"-",_xlfn.MAXIFS(Oportunidades!$I$2:$I$71,Oportunidades!$C$2:$C$71,$B6,Oportunidades!$H$2:$H$71,"Ganada")) -> 45015 | V6: Subcategoría de End Market vacía | W6: Sin sitio público identificado (PEN-03) | X6: Ninguna fuente pública ubica una instalación de Bachoco en Tierra Blanca; el TIF de Tierra Blanca es de otra empresa. Sí hay planta CAMPI en Chinameca, Veracruz. | Y6: Bachoco, S.A. de C.V. - Tierra Blanca | Z6: Food & Beverage | AA6: Manufacturing - Food Processing | AB6: End User | AC6: Confirmar qué instalación es (3 ganadas con RYASA Veracruz y SNR Córdoba). Falta Subcategoría de End Market.
A7: 6 | B7: Bachoco S.A. de C.V - Guanajuato | C7: Celaya | D7: Guanajuato | E7: Bajío (Celaya) | F7: Norte II 2, Cd Industrial de Celaya,38010 CELAYA, GUANAJUATO,MEXICO | G7: Ulises Sanchez | H7: Ulises Sanchez; Froylan Santiago Inactive Alcántara | I7: End User | J7: Food & Beverage | K7: Manufacturing - Food Processing | L7: (vacío) | M7: 6-1-2021 09:29 AM | N7: DATA.MIGRATION | O7: Sí | P7: =COUNTIFS(Oportunidades!$C$2:$C$71,$B7,Oportunidades!$H$2:$H$71,"Ganada") -> 3 | Q7: =COUNTIFS(Oportunidades!$C$2:$C$71,$B7,Oportunidades!$H$2:$H$71,"Perdida") -> 0 | R7: =COUNTIFS(Oportunidades!$C$2:$C$71,$B7,Oportunidades!$H$2:$H$71,"Abierta") -> 0 | S7: =COUNTIFS(Oportunidades!$C$2:$C$71,$B7,Oportunidades!$H$2:$H$71,"Ganada",Oportunidades!$Z$2:$Z$71,"Elegible") -> 1 | T7: =COUNTIFS(Oportunidades!$C$2:$C$71,$B7,Oportunidades!$H$2:$H$71,"Perdida",Oportunidades!$Z$2:$Z$71,"Elegible") -> 0 | U7: =IF(P7=0,"-",_xlfn.MAXIFS(Oportunidades!$I$2:$I$71,Oportunidades!$C$2:$C$71,$B7,Oportunidades!$H$2:$H$71,"Ganada")) -> 43701 | W7: Sin sitio público identificado | X7: Misma Ciudad Industrial de Celaya que BCH-001; otro domicilio (Norte II 2). Mismo contacto principal que Corp y la cuenta 2. | Y7: Bachoco, S.A. de C.V. - Celaya - [tipo por confirmar] | Z7: Food & Beverage | AA7: Manufacturing - Food Processing | AB7: End User | AC7: Validar si es duplicada de Corp o de la cuenta 2; si lo es, unir conservando sus 3 ganadas. La planta de rendimiento BCH-020 tiene el mismo CP 38010, pero eso no basta para ligarla.
A8: 7 | B8: Bachoco, S.A. de C.V. - Planta Coatzacoalcos | C8: Coatzacoalcos | D8: Veracruz | E8: Veracruz | F8: CARR TRANSISTMICA KM 7.5,96400 COATZACOALCOS, VERACRUZ,MEXICO | G8: Alejandro Avila | H8: Eliasib Luna | I8: End User | J8: Food & Beverage | K8: (vacío) | L8: (vacío) | M8: 6-1-2021 09:45 AM | N8: DATA.MIGRATION | O8: Sí | P8: =COUNTIFS(Oportunidades!$C$2:$C$71,$B8,Oportunidades!$H$2:$H$71,"Ganada") -> 1 | Q8: =COUNTIFS(Oportunidades!$C$2:$C$71,$B8,Oportunidades!$H$2:$H$71,"Perdida") -> 1 | R8: =COUNTIFS(Oportunidades!$C$2:$C$71,$B8,Oportunidades!$H$2:$H$71,"Abierta") -> 0 | S8: =COUNTIFS(Oportunidades!$C$2:$C$71,$B8,Oportunidades!$H$2:$H$71,"Ganada",Oportunidades!$Z$2:$Z$71,"Elegible") -> 1 | T8: =COUNTIFS(Oportunidades!$C$2:$C$71,$B8,Oportunidades!$H$2:$H$71,"Perdida",Oportunidades!$Z$2:$Z$71,"Elegible") -> 1 | U8: =IF(P8=0,"-",_xlfn.MAXIFS(Oportunidades!$I$2:$I$71,Oportunidades!$C$2:$C$71,$B8,Oportunidades!$H$2:$H$71,"Ganada")) -> 45378 | V8: Subcategoría de End Market vacía | W8: BCH-019 | X8: Por confirmar. La cuenta "Planta Coatzacoalcos" (Carretera Transístmica Km 7.5) coincide en ciudad con el ex complejo Coatzacoalcos. La única evidencia pública de operación es una tesis de 2009. | Y8: Bachoco, S.A. de C.V. - Coatzacoalcos | Z8: Food & Beverage | AA8: Manufacturing - Food Processing | AB8: End User | AC8: Confirmar qué instalación es (no hay evidencia pública reciente; el Reporte Anual 2023 la lista como ex complejo con oficina, BCH-002, sin domicilio público). Falta Subcategoría de End Market. Propietario de la cuenta (Alejandro Avila) distinto al de sus oportunidades (Eliasib Luna): definir uno.
A9: 8 | B9: Bachoco, Planta Procesadora De Alimentos | C9: Ciudad Obregón | D9: Sonora | E9: Noroeste (Sonora/BC) | F9: Cd Obregón - Navojoa, 85065,85150 CIUDAD OBREGÓN, SONORA,MEXICO | G9: Dan Weller | I9: End User | J9: Agriculture | K9: Agriculture Equipment | L9: (vacío) | M9: 15-4-2026 08:35 AM | N9: oicintegration.prod | O9: Sí | P9: =COUNTIFS(Oportunidades!$C$2:$C$71,$B9,Oportunidades!$H$2:$H$71,"Ganada") -> 0 | Q9: =COUNTIFS(Oportunidades!$C$2:$C$71,$B9,Oportunidades!$H$2:$H$71,"Perdida") -> 0 | R9: =COUNTIFS(Oportunidades!$C$2:$C$71,$B9,Oportunidades!$H$2:$H$71,"Abierta") -> 0 | S9: =COUNTIFS(Oportunidades!$C$2:$C$71,$B9,Oportunidades!$H$2:$H$71,"Ganada",Oportunidades!$Z$2:$Z$71,"Elegible") -> 0 | T9: =COUNTIFS(Oportunidades!$C$2:$C$71,$B9,Oportunidades!$H$2:$H$71,"Perdida",Oportunidades!$Z$2:$Z$71,"Elegible") -> 0 | U9: =IF(P9=0,"-",_xlfn.MAXIFS(Oportunidades!$I$2:$I$71,Oportunidades!$C$2:$C$71,$B9,Oportunidades!$H$2:$H$71,"Ganada")) -> - | V9: End Market distinto a Food & Beverage (Agriculture / Agriculture Equipment); Propietario no aparece en la hoja Team del archivo IR: confirmar vigencia; Sin oportunidades registradas | W9: Sin sitio público identificado | X9: Domicilio "Cd. Obregón-Navojoa" es genérico. Creada por integración el 15-abr-2026 con End Market Agriculture. No se pudo ligar a un sitio público (Navojoa tiene un rastro porcino de una subsidiaria, BCH-030; sin confirmar). | Y9: Bachoco, S.A. de C.V. - Ciudad Obregón - [tipo por confirmar] | Z9: Food & Beverage | AA9: Manufacturing - Food Processing | AB9: End User | AC9: Validar si es duplicada de la cuenta 1. Corregir End Market a Food & Beverage si se mantiene. Propietario (Dan Weller) no aparece en la hoja Team.
A10: 9 | B10: Bachoco S.A. de C.V. - Planta Gomez Palacio | C10: Gómez Palacio | D10: Durango | E10: Durango (Gómez Palacio) | F10: Cuarta 438, Parque Industrial Lagunero, 35078 Gómez Palacio, Dgo.,, Gomez Palacio,35078 GOMEZ PALACIO, DURANGO,MEXICO | G10: Jose Osbaldo Rodriguez Hernandez | H10: Armando Inactive Hernández; Jose Osbaldo Rodriguez Hernandez | I10: End User | J10: Food & Beverage | K10: Manufacturing - Food Processing | L10: (vacío) | M10: 9-2-2023 11:31 PM | N10: jonathan.gomez | O10: Sí | P10: =COUNTIFS(Oportunidades!$C$2:$C$71,$B10,Oportunidades!$H$2:$H$71,"Ganada") -> 0 | Q10: =COUNTIFS(Oportunidades!$C$2:$C$71,$B10,Oportunidades!$H$2:$H$71,"Perdida") -> 1 | R10: =COUNTIFS(Oportunidades!$C$2:$C$71,$B10,Oportunidades!$H$2:$H$71,"Abierta") -> 1 | S10: =COUNTIFS(Oportunidades!$C$2:$C$71,$B10,Oportunidades!$H$2:$H$71,"Ganada",Oportunidades!$Z$2:$Z$71,"Elegible") -> 0 | T10: =COUNTIFS(Oportunidades!$C$2:$C$71,$B10,Oportunidades!$H$2:$H$71,"Perdida",Oportunidades!$Z$2:$Z$71,"Elegible") -> 1 | U10: =IF(P10=0,"-",_xlfn.MAXIFS(Oportunidades!$I$2:$I$71,Oportunidades!$C$2:$C$71,$B10,Oportunidades!$H$2:$H$71,"Ganada")) -> - | W10: Sin sitio público identificado (PEN-04) | X10: Bachoco no tiene TIF en Durango; los TIF de Gómez Palacio son de Pilgrim's Pride. El domicilio del CRM está en el Parque Industrial Lagunero. | Y10: Bachoco, S.A. de C.V. - Gómez Palacio | Z10: Food & Beverage | AA10: Manufacturing - Food Processing | AB10: End User | AC10: Confirmar qué instalación es antes de invertir tiempo. No confundir con Pilgrim's. Tiene la abierta 812577 "7.1 / TPU / Bachoco / BRR Torreón" (región 35). El Reporte Anual 2023 lista Gómez Palacio como ex complejo con oficina (BCH-002), sin domicilio público.
A11: 10 | B11: Bachoco S.A. de C.V. - Planta Culiacan | C11: Culiacán | D11: Sinaloa | E11: Sinaloa (Culiacán) | F11: Carretera al Dorado Km 13.5,Quemadito, Culiacan,80300 CULIACAN, SINALOA,MEXICO | G11: Marcos Arevalo | H11: Marcos Arevalo | I11: OEM | J11: Food & Beverage | K11: Manufacturing - Food Processing | L11: (vacío) | M11: 1-10-2021 12:23 PM | N11: marcos.arevalo | O11: Sí | P11: =COUNTIFS(Oportunidades!$C$2:$C$71,$B11,Oportunidades!$H$2:$H$71,"Ganada") -> 5 | Q11: =COUNTIFS(Oportunidades!$C$2:$C$71,$B11,Oportunidades!$H$2:$H$71,"Perdida") -> 2 | R11: =COUNTIFS(Oportunidades!$C$2:$C$71,$B11,Oportunidades!$H$2:$H$71,"Abierta") -> 0 | S11: =COUNTIFS(Oportunidades!$C$2:$C$71,$B11,Oportunidades!$H$2:$H$71,"Ganada",Oportunidades!$Z$2:$Z$71,"Elegible") -> 0 | T11: =COUNTIFS(Oportunidades!$C$2:$C$71,$B11,Oportunidades!$H$2:$H$71,"Perdida",Oportunidades!$Z$2:$Z$71,"Elegible") -> 0 | U11: =IF(P11=0,"-",_xlfn.MAXIFS(Oportunidades!$I$2:$I$71,Oportunidades!$C$2:$C$71,$B11,Oportunidades!$H$2:$H$71,"Ganada")) -> 45520 | V11: Segmentación 'OEM' (la mayoría de las cuentas Bachoco es End User) | W11: BCH-015 | X11: Sí. Domicilio coincide: Carretera al Dorado Km 13.5, Culiacán. Las dos cuentas del CRM de Culiacán tienen el mismo domicilio (CP 80300 y 80130; SENASICA 80100). | Y11: Bachoco, S.A. de C.V. - Culiacán | Z11: Food & Beverage | AA11: Manufacturing - Food Processing | AB11: End User | AC11: Cuenta de Marcos. Cambiar segmentación OEM a End User si se confirma que usa el producto en su proceso; con OEM el programa dejó fuera 5 ganadas. Decide: Marcos.
A12: 11 | B12: BACHOCO SA de CV - Cienega de Flores | C12: Ciénega de Flores | D12: Nuevo León | E12: Nuevo León (Ciénega de Flores) | F12: Autop. Monterrey - Nuevo laredo 34,Centro de Cienega de Flores, Cienega de Flores,65555 CIENEGA DE FLORES, NUEVO LEÓN,MEXICO | G12: Emmanuel Quintanilla | H12: Emmanuel Quintanilla | I12: Exporter/Trading Company | J12: Food & Beverage | K12: Manufacturing - Food Processing | L12: (vacío) | M12: 6-4-2026 08:35 AM | N12: emmanuel.quintanilla | O12: Sí | P12: =COUNTIFS(Oportunidades!$C$2:$C$71,$B12,Oportunidades!$H$2:$H$71,"Ganada") -> 1 | Q12: =COUNTIFS(Oportunidades!$C$2:$C$71,$B12,Oportunidades!$H$2:$H$71,"Perdida") -> 0 | R12: =COUNTIFS(Oportunidades!$C$2:$C$71,$B12,Oportunidades!$H$2:$H$71,"Abierta") -> 1 | S12: =COUNTIFS(Oportunidades!$C$2:$C$71,$B12,Oportunidades!$H$2:$H$71,"Ganada",Oportunidades!$Z$2:$Z$71,"Elegible") -> 0 | T12: =COUNTIFS(Oportunidades!$C$2:$C$71,$B12,Oportunidades!$H$2:$H$71,"Perdida",Oportunidades!$Z$2:$Z$71,"Elegible") -> 0 | U12: =IF(P12=0,"-",_xlfn.MAXIFS(Oportunidades!$I$2:$I$71,Oportunidades!$C$2:$C$71,$B12,Oportunidades!$H$2:$H$71,"Ganada")) -> 46227 | V12: Segmentación 'Exporter/Trading Company' (la mayoría de las cuentas Bachoco es End User) | W12: BCH-013 | X12: Sí. Domicilio coincide en carretera y kilómetro: Autopista Monterrey-Nuevo Laredo Km 34 (CP 65555 en el CRM; 65550 en SENASICA). | Y12: Bachoco, S.A. de C.V. - Ciénega de Flores | Z12: Food & Beverage | AA12: Manufacturing - Food Processing | AB12: End User | AC12: Segmentación "Exporter/Trading Company" dejó fuera su ganada de jul-2026 ("Segmento intermediario"). Cambiar a End User si se confirma. Decide el propietario de la cuenta en el CRM (Emmanuel Quintanilla; confirmar vigencia).
A13: 12 | B13: BACHOCO Planta Culiacan | C13: Culiacán | D13: Sinaloa | E13: Sinaloa (Culiacán) | F13: Carretera el Dorado Km. 13,5,Quemadito, Culiacan,80130 CULIACAN, SINALOA,MEXICO | G13: Fernando Reyes | H13: Marcos Arevalo | I13: Corporate | J13: Food & Beverage | K13: Manufacturing - Food Processing | L13: (vacío) | M13: 10-3-2023 03:13 PM | N13: fernando.reyestzintzun | O13: Sí | P13: =COUNTIFS(Oportunidades!$C$2:$C$71,$B13,Oportunidades!$H$2:$H$71,"Ganada") -> 1 | Q13: =COUNTIFS(Oportunidades!$C$2:$C$71,$B13,Oportunidades!$H$2:$H$71,"Perdida") -> 0 | R13: =COUNTIFS(Oportunidades!$C$2:$C$71,$B13,Oportunidades!$H$2:$H$71,"Abierta") -> 0 | S13: =COUNTIFS(Oportunidades!$C$2:$C$71,$B13,Oportunidades!$H$2:$H$71,"Ganada",Oportunidades!$Z$2:$Z$71,"Elegible") -> 0 | T13: =COUNTIFS(Oportunidades!$C$2:$C$71,$B13,Oportunidades!$H$2:$H$71,"Perdida",Oportunidades!$Z$2:$Z$71,"Elegible") -> 0 | U13: =IF(P13=0,"-",_xlfn.MAXIFS(Oportunidades!$I$2:$I$71,Oportunidades!$C$2:$C$71,$B13,Oportunidades!$H$2:$H$71,"Ganada")) -> 45225 | V13: Segmentación 'Corporate' (la mayoría de las cuentas Bachoco es End User); Sin correo del contacto principal | W13: BCH-015 | X13: Sí (duplicada). Mismo domicilio que la cuenta 10 (Carretera al Dorado Km 13.5, Quemadito). | Y13: Unir con la cuenta 10 (mismo domicilio) | Z13: Food & Beverage | AA13: Manufacturing - Food Processing | AB13: End User | AC13: Unir con la cuenta 10 conservando su ganada 650190 "7.1 HID BACHOCO Planta Culiacan RYASA Culiacan". Decide: administrador del CRM, con los propietarios de ambas.
A14: 13 | B14: BACHOCO, S.A. DE C.V - Planta de alimentos division Bajio | C14: Celaya | D14: Guanajuato | E14: Bajío (Celaya) | F14: Panamericana 2675, Zona Industrial,,38020 CELAYA, GUANAJUATO,MEXICO | G14: Ulises Sanchez | H14: Ulises Sanchez; Froylan Santiago Inactive Alcántara | I14: End User | J14: Food & Beverage | K14: Manufacturing - Food Processing | L14: (vacío) | M14: 6-1-2021 09:40 AM | N14: DATA.MIGRATION | O14: Sí | P14: =COUNTIFS(Oportunidades!$C$2:$C$71,$B14,Oportunidades!$H$2:$H$71,"Ganada") -> 2 | Q14: =COUNTIFS(Oportunidades!$C$2:$C$71,$B14,Oportunidades!$H$2:$H$71,"Perdida") -> 0 | R14: =COUNTIFS(Oportunidades!$C$2:$C$71,$B14,Oportunidades!$H$2:$H$71,"Abierta") -> 0 | S14: =COUNTIFS(Oportunidades!$C$2:$C$71,$B14,Oportunidades!$H$2:$H$71,"Ganada",Oportunidades!$Z$2:$Z$71,"Elegible") -> 2 | T14: =COUNTIFS(Oportunidades!$C$2:$C$71,$B14,Oportunidades!$H$2:$H$71,"Perdida",Oportunidades!$Z$2:$Z$71,"Elegible") -> 0 | U14: =IF(P14=0,"-",_xlfn.MAXIFS(Oportunidades!$I$2:$I$71,Oportunidades!$C$2:$C$71,$B14,Oportunidades!$H$2:$H$71,"Ganada")) -> 44741 | W14: Sin sitio público identificado (CP 38020 igual al del rastro BCH-010) | X14: El CP 38020 es el mismo del rastro TIF de Celaya (BCH-010), pero la calle es distinta (Panamericana 2675). El único sitio público de "división Bajío" es una planta forrajera de CAMPI en Querétaro, sin confirmar (BCH-054). | Y14: Bachoco, S.A. de C.V. - Celaya - Planta de alimento (por confirmar) | Z14: Food & Beverage | AA14: Manufacturing - Food Processing | AB14: End User | AC14: Confirmar si es la planta de alimento, el rastro u otra instalación. Tiene 2 ganadas registradas: O-00245158 "2.2 Pti Bachoco RYASA" y 569067 "7.1 PTI- BACHOCO, S.A. DE C.V - Planta de alimentos division Bajio PT-V-BELTS-569067- RYASA QRO" (potencial anual registrado, 1.5 millones MXN bruto).
A15: 14 | B15: Bachoco, S.A. de C.V. - Planta procesadora de aves Guanajuato - Guanajuato | C15: San Isidro Crespo (Celaya) | D15: Guanajuato | E15: Bajío (Celaya) | F15: Av el Vergel,36003 SAN ISIDRO CRESPO, GUANAJUATO,MEXICO | G15: Felipe Inactive Jiménez | H15: Alejandro Inactive Escobedo Meza; Froylan Santiago Inactive Alcántara; Marcos Arevalo | I15: End User | J15: Food & Beverage | K15: Manufacturing - Food Processing | L15: (vacío) | M15: 6-1-2021 09:38 AM | N15: DATA.MIGRATION | O15: Sí | P15: =COUNTIFS(Oportunidades!$C$2:$C$71,$B15,Oportunidades!$H$2:$H$71,"Ganada") -> 11 | Q15: =COUNTIFS(Oportunidades!$C$2:$C$71,$B15,Oportunidades!$H$2:$H$71,"Perdida") -> 3 | R15: =COUNTIFS(Oportunidades!$C$2:$C$71,$B15,Oportunidades!$H$2:$H$71,"Abierta") -> 0 | S15: =COUNTIFS(Oportunidades!$C$2:$C$71,$B15,Oportunidades!$H$2:$H$71,"Ganada",Oportunidades!$Z$2:$Z$71,"Elegible") -> 10 | T15: =COUNTIFS(Oportunidades!$C$2:$C$71,$B15,Oportunidades!$H$2:$H$71,"Perdida",Oportunidades!$Z$2:$Z$71,"Elegible") -> 3 | U15: =IF(P15=0,"-",_xlfn.MAXIFS(Oportunidades!$I$2:$I$71,Oportunidades!$C$2:$C$71,$B15,Oportunidades!$H$2:$H$71,"Ganada")) -> 45463 | V15: Propietario marcado como inactivo en el CRM | W15: BCH-010 | X15: Por confirmar. La cuenta "Planta procesadora de aves Guanajuato - Guanajuato" tiene domicilio "Av el Vergel, San Isidro Crespo" (CP 36003). Directorios comerciales ubican el rastro en "Parque Industrial El Vergel" y "San Isidro de Crespo", pero el domicilio oficial de SENASICA es Km 5 Carr. Celaya-Salamanca, Segunda Fracción de Crespo (CP 38020). El CP del CRM no coincide. | Y15: Bachoco, S.A. de C.V. - Celaya - Planta procesadora de aves (TIF A-363) si se confirma | Z15: Food & Beverage | AA15: Manufacturing - Food Processing | AB15: End User | AC15: Cuenta con más ganadas (11 en todo el CRM, 10 Elegibles) y propietario inactivo en el CRM: confirmar quién la lleva hoy en la región Bajío antes de asignar trabajo. CP 36003 no coincide con 38020.
A16: 15 | B16: Bachoco, S.A. de C.V. - Planta De Alimentos 1 Bachoco S.A. De C.V. | C16: Mérida | D16: Yucatán | E16: Yucatán (Mérida/Umán) | F16: José María Castro SN, Cd Industrial, 97288 Mérida, Yuc.,97288 MERIDA, YUCATÁN,MEXICO | G16: Cesar Vázquez | I16: End User | J16: Food & Beverage | K16: (vacío) | L16: (vacío) | M16: 6-1-2021 09:31 AM | N16: DATA.MIGRATION | O16: Sí | P16: =COUNTIFS(Oportunidades!$C$2:$C$71,$B16,Oportunidades!$H$2:$H$71,"Ganada") -> 0 | Q16: =COUNTIFS(Oportunidades!$C$2:$C$71,$B16,Oportunidades!$H$2:$H$71,"Perdida") -> 0 | R16: =COUNTIFS(Oportunidades!$C$2:$C$71,$B16,Oportunidades!$H$2:$H$71,"Abierta") -> 0 | S16: =COUNTIFS(Oportunidades!$C$2:$C$71,$B16,Oportunidades!$H$2:$H$71,"Ganada",Oportunidades!$Z$2:$Z$71,"Elegible") -> 0 | T16: =COUNTIFS(Oportunidades!$C$2:$C$71,$B16,Oportunidades!$H$2:$H$71,"Perdida",Oportunidades!$Z$2:$Z$71,"Elegible") -> 0 | U16: =IF(P16=0,"-",_xlfn.MAXIFS(Oportunidades!$I$2:$I$71,Oportunidades!$C$2:$C$71,$B16,Oportunidades!$H$2:$H$71,"Ganada")) -> - | V16: Subcategoría de End Market vacía; Propietario no aparece en la hoja Team del archivo IR: confirmar vigencia; Sin correo del contacto principal; Sin oportunidades registradas | W16: BCH-050 | X16: Por confirmar. La cuenta "Planta De Alimentos 1" (José María Castro SN, Ciudad Industrial, Mérida, CP 97288) coincide en tipo (alimento) y zona (Ciudad Industrial) con la planta CAMPI; las calles no coinciden (Calle 17 No. 400 x 20). | Y16: Bachoco, S.A. de C.V. - Mérida - Planta de alimento | Z16: Food & Beverage | AA16: Manufacturing - Food Processing | AB16: End User | AC16: Sin oportunidades. Falta Subcategoría de End Market. Confirmar si es la planta CAMPI. Propietario (Cesar Vázquez) no aparece en la hoja Team.
A17: 16 | B17: Bachoco S.A de C.V - Cuautla | C17: Cuautla | D17: Morelos | E17: Morelos (Cuautla) | F17: MEXICO PUEBLA 3, ESTRELLA, 62747 Cuautla, Morelos,, MEXICO PUEBLA 3, ESTRELLA,62747 CUAUTLA, MORELOS,MEXICO | G17: Christopher Torres | I17: End User | J17: Food & Beverage | K17: Manufacturing - Food Processing | L17: (vacío) | M17: 6-10-2022 03:16 PM | N17: christopher.torres | O17: No | P17: =COUNTIFS(Oportunidades!$C$2:$C$71,$B17,Oportunidades!$H$2:$H$71,"Ganada") -> 0 | Q17: =COUNTIFS(Oportunidades!$C$2:$C$71,$B17,Oportunidades!$H$2:$H$71,"Perdida") -> 0 | R17: =COUNTIFS(Oportunidades!$C$2:$C$71,$B17,Oportunidades!$H$2:$H$71,"Abierta") -> 0 | S17: =COUNTIFS(Oportunidades!$C$2:$C$71,$B17,Oportunidades!$H$2:$H$71,"Ganada",Oportunidades!$Z$2:$Z$71,"Elegible") -> 0 | T17: =COUNTIFS(Oportunidades!$C$2:$C$71,$B17,Oportunidades!$H$2:$H$71,"Perdida",Oportunidades!$Z$2:$Z$71,"Elegible") -> 0 | U17: =IF(P17=0,"-",_xlfn.MAXIFS(Oportunidades!$I$2:$I$71,Oportunidades!$C$2:$C$71,$B17,Oportunidades!$H$2:$H$71,"Ganada")) -> - | V17: Sin contacto principal; Sin correo del contacto principal; Sin teléfono; Sin oportunidades registradas | W17: BCH-051 | X17: Sí. Mismo municipio, calle y número: CRM "México Puebla 3, Estrella, Cuautla" y CAMPI "Vía de FFCC México-Puebla No. 3, Col. Cuatlixco". La colonia no coincide. | Y17: Bachoco, S.A. de C.V. - Cuautla - Planta de alimento | Z17: Food & Beverage | AA17: Manufacturing - Food Processing | AB17: End User | AC17: Sin contacto principal ni oportunidades: capturar contacto de mantenimiento o compras en la primera visita.
A18: 17 | B18: Bachoco S.A. de C.V. - San Luis Potosi | C18: San Luis Potosí | D18: San Luis Potosí | E18: San Luis Potosí | F18: Av Salk 4665,,El Aguaje, El Aguaje,78385 SAN LUIS POTOSI, SAN LUIS POTOSÍ | G18: Alejandro Velasco | H18: Alejandro Velasco | I18: End User | J18: Food & Beverage | K18: Manufacturing - Food Processing | L18: (vacío) | M18: 24-8-2026 02:18 PM | N18: miguelalejandro.velasco | O18: Sí | P18: =COUNTIFS(Oportunidades!$C$2:$C$71,$B18,Oportunidades!$H$2:$H$71,"Ganada") -> 0 | Q18: =COUNTIFS(Oportunidades!$C$2:$C$71,$B18,Oportunidades!$H$2:$H$71,"Perdida") -> 0 | R18: =COUNTIFS(Oportunidades!$C$2:$C$71,$B18,Oportunidades!$H$2:$H$71,"Abierta") -> 2 | S18: =COUNTIFS(Oportunidades!$C$2:$C$71,$B18,Oportunidades!$H$2:$H$71,"Ganada",Oportunidades!$Z$2:$Z$71,"Elegible") -> 0 | T18: =COUNTIFS(Oportunidades!$C$2:$C$71,$B18,Oportunidades!$H$2:$H$71,"Perdida",Oportunidades!$Z$2:$Z$71,"Elegible") -> 0 | U18: =IF(P18=0,"-",_xlfn.MAXIFS(Oportunidades!$I$2:$I$71,Oportunidades!$C$2:$C$71,$B18,Oportunidades!$H$2:$H$71,"Ganada")) -> - | V18: Sin correo del contacto principal | W18: Sin sitio público identificado (PEN-02) | X18: Ninguna fuente pública ubica una instalación de Bachoco en San Luis Potosí (el TIF A-206 de SLP es de Pilgrim's Pride). Cuenta creada el 24-ago-2026 con 2 abiertas. | Y18: Bachoco, S.A. de C.V. - San Luis Potosí | Z18: Food & Beverage | AA18: Manufacturing - Food Processing | AB18: End User | AC18: Preguntar a quien la capturó (propietario en el CRM: Alejandro Velasco) qué instalación es; la cuenta es reciente y tiene 2 abiertas.
A19: 18 | B19: Bachoco S.A. DE C.V. - Planta procesadora de aves Sonora | C19: Mexicali | D19: Baja California | E19: Noroeste (Sonora/BC) | F19: Av Galaxia, PIMSA I, Mexicali, B.C.,21355 MEXICALI, BAJA CALIFORNIA,MEXICO | G19: Cesar Vázquez | H19: Abel Inactive Valenzuela; Johnatan Inactive Murillo | I19: End User | J19: Food & Beverage | K19: (vacío) | L19: (vacío) | M19: 6-1-2021 09:32 AM | N19: DATA.MIGRATION | O19: Sí | P19: =COUNTIFS(Oportunidades!$C$2:$C$71,$B19,Oportunidades!$H$2:$H$71,"Ganada") -> 0 | Q19: =COUNTIFS(Oportunidades!$C$2:$C$71,$B19,Oportunidades!$H$2:$H$71,"Perdida") -> 4 | R19: =COUNTIFS(Oportunidades!$C$2:$C$71,$B19,Oportunidades!$H$2:$H$71,"Abierta") -> 0 | S19: =COUNTIFS(Oportunidades!$C$2:$C$71,$B19,Oportunidades!$H$2:$H$71,"Ganada",Oportunidades!$Z$2:$Z$71,"Elegible") -> 0 | T19: =COUNTIFS(Oportunidades!$C$2:$C$71,$B19,Oportunidades!$H$2:$H$71,"Perdida",Oportunidades!$Z$2:$Z$71,"Elegible") -> 4 | U19: =IF(P19=0,"-",_xlfn.MAXIFS(Oportunidades!$I$2:$I$71,Oportunidades!$C$2:$C$71,$B19,Oportunidades!$H$2:$H$71,"Ganada")) -> - | V19: Subcategoría de End Market vacía; Propietario no aparece en la hoja Team del archivo IR: confirmar vigencia; Sin correo del contacto principal; El nombre dice Sonora pero el domicilio es Mexicali, Baja California | W19: Sin sitio público identificado (PEN-01) | X19: El nombre dice Sonora pero el domicilio (Av. Galaxia, PIMSA I) es de Mexicali, BC. No hay instalación de Bachoco identificada en Mexicali (el TIF de Mexicali es de SuKarne); el mapa 2021 muestra 3 CEDIS en Baja California sin municipio. | Y19: Bachoco, S.A. de C.V. - Mexicali | Z19: Food & Beverage | AA19: Manufacturing - Food Processing | AB19: End User | AC19: Cambiar el nombre (Sonora no corresponde). Confirmar qué instalación es: 4 oportunidades perdidas. Propietario (Cesar Vázquez) no aparece en la hoja Team. Falta Subcategoría de End Market.
A20: 19 | B20: Industrias Bachoco SA de CV - Merida, Yucatan. | C20: Mérida | D20: Yucatán | E20: Yucatán (Mérida/Umán) | F20: Calle Benito Juárez 21, Cd Industrial,,97288 MERIDA, YUCATÁN,MEXICO | G20: Ricardo Narvaez | H20: Alejandro Inactive Escobedo Meza; Eliasib Luna | I20: End User | J20: Food & Beverage | K20: Manufacturing - Food Processing | L20: (vacío) | M20: 6-1-2021 09:36 AM | N20: DATA.MIGRATION | O20: Sí | P20: =COUNTIFS(Oportunidades!$C$2:$C$71,$B20,Oportunidades!$H$2:$H$71,"Ganada") -> 2 | Q20: =COUNTIFS(Oportunidades!$C$2:$C$71,$B20,Oportunidades!$H$2:$H$71,"Perdida") -> 0 | R20: =COUNTIFS(Oportunidades!$C$2:$C$71,$B20,Oportunidades!$H$2:$H$71,"Abierta") -> 1 | S20: =COUNTIFS(Oportunidades!$C$2:$C$71,$B20,Oportunidades!$H$2:$H$71,"Ganada",Oportunidades!$Z$2:$Z$71,"Elegible") -> 2 | T20: =COUNTIFS(Oportunidades!$C$2:$C$71,$B20,Oportunidades!$H$2:$H$71,"Perdida",Oportunidades!$Z$2:$Z$71,"Elegible") -> 0 | U20: =IF(P20=0,"-",_xlfn.MAXIFS(Oportunidades!$I$2:$I$71,Oportunidades!$C$2:$C$71,$B20,Oportunidades!$H$2:$H$71,"Ganada")) -> 44120 | V20: Propietario registrado es el NSM: confirmar quién lleva realmente la cuenta | W20: Sin sitio público identificado (Ciudad Industrial de Mérida; ver BCH-050) | X20: Calle Benito Juárez 21, Ciudad Industrial, Mérida (CP 97288): no coincide con el domicilio del rastro (Umán, km 14.5) ni con el de la planta CAMPI (Calle 17). | Y20: Bachoco, S.A. de C.V. - Mérida - [tipo por confirmar] | Z20: Food & Beverage | AA20: Manufacturing - Food Processing | AB20: End User | AC20: Confirmar qué instalación es. Su propietario en el CRM es el NSM: definir quién la lleva. Tiene la abierta 810579 "2.2 PTV Continental Bachoco Mérida Eissa Mérida" (potencial anual registrado 450,000).
A21: 20 | B21: Industrias Bachoco S.A. de C.V. - Uman, Yucatan. | C21: Umán | D21: Yucatán | E21: Yucatán (Mérida/Umán) | F21: Carretera Merida - Uman km 14.5,97390 UMAN, YUCATÁN,MEXICO | G21: Ricardo Narvaez | H21: Alejandro Inactive Escobedo Meza | I21: End User | J21: Food & Beverage | K21: Manufacturing - Food Processing | L21: (vacío) | M21: 22-5-2024 05:45 PM | N21: alejandro.escobedomeza | O21: Sí | P21: =COUNTIFS(Oportunidades!$C$2:$C$71,$B21,Oportunidades!$H$2:$H$71,"Ganada") -> 1 | Q21: =COUNTIFS(Oportunidades!$C$2:$C$71,$B21,Oportunidades!$H$2:$H$71,"Perdida") -> 0 | R21: =COUNTIFS(Oportunidades!$C$2:$C$71,$B21,Oportunidades!$H$2:$H$71,"Abierta") -> 0 | S21: =COUNTIFS(Oportunidades!$C$2:$C$71,$B21,Oportunidades!$H$2:$H$71,"Ganada",Oportunidades!$Z$2:$Z$71,"Elegible") -> 1 | T21: =COUNTIFS(Oportunidades!$C$2:$C$71,$B21,Oportunidades!$H$2:$H$71,"Perdida",Oportunidades!$Z$2:$Z$71,"Elegible") -> 0 | U21: =IF(P21=0,"-",_xlfn.MAXIFS(Oportunidades!$I$2:$I$71,Oportunidades!$C$2:$C$71,$B21,Oportunidades!$H$2:$H$71,"Ganada")) -> 45437 | V21: Propietario registrado es el NSM: confirmar quién lleva realmente la cuenta | W21: BCH-016 | X21: Sí. Domicilio coincide: Carretera Mérida-Umán Km 14.5, CP 97390 (cuenta "Industrias Bachoco ... Umán"). SENASICA lo llama Mérida; el CP es de Umán. | Y21: Bachoco, S.A. de C.V. - Umán - Planta procesadora de aves (TIF A-234) | Z21: Food & Beverage | AA21: Manufacturing - Food Processing | AB21: End User | AC21: Propietario en el CRM es el NSM: definir quién la lleva.
A22: 21 | B22: Bchoco S.A. de C.V. - Planta Hermosillo | C22: Hermosillo | D22: Sonora | E22: Noroeste (Sonora/BC) | F22: Carretera Sahurita Km 3.5, Parque Industrial,83299 HERMOSILLO, SONORA,MEXICO | G22: Cesar Vázquez | H22: Johnatan Inactive Murillo | I22: End User | J22: Food & Beverage | K22: (vacío) | L22: (vacío) | M22: 6-1-2021 09:35 AM | N22: DATA.MIGRATION | O22: Sí | P22: =COUNTIFS(Oportunidades!$C$2:$C$71,$B22,Oportunidades!$H$2:$H$71,"Ganada") -> 0 | Q22: =COUNTIFS(Oportunidades!$C$2:$C$71,$B22,Oportunidades!$H$2:$H$71,"Perdida") -> 1 | R22: =COUNTIFS(Oportunidades!$C$2:$C$71,$B22,Oportunidades!$H$2:$H$71,"Abierta") -> 0 | S22: =COUNTIFS(Oportunidades!$C$2:$C$71,$B22,Oportunidades!$H$2:$H$71,"Ganada",Oportunidades!$Z$2:$Z$71,"Elegible") -> 0 | T22: =COUNTIFS(Oportunidades!$C$2:$C$71,$B22,Oportunidades!$H$2:$H$71,"Perdida",Oportunidades!$Z$2:$Z$71,"Elegible") -> 1 | U22: =IF(P22=0,"-",_xlfn.MAXIFS(Oportunidades!$I$2:$I$71,Oportunidades!$C$2:$C$71,$B22,Oportunidades!$H$2:$H$71,"Ganada")) -> - | V22: Subcategoría de End Market vacía; Propietario no aparece en la hoja Team del archivo IR: confirmar vigencia; Sin correo del contacto principal; Error de ortografía en el nombre ('Bchoco') | W22: BCH-018 | X22: Por confirmar. La cuenta "Bchoco ... Hermosillo" (Carretera Sahurita Km 3.5, Parque Industrial, CP 83299, tal como está en el CRM) coincide en ciudad con el ex complejo Hermosillo. No hay domicilio verificado de la planta de aves. | Y22: Bachoco, S.A. de C.V. - Hermosillo | Z22: Food & Beverage | AA22: Manufacturing - Food Processing | AB22: End User | AC22: Corregir "Bchoco". Confirmar qué instalación es (CP igual al de un rastro porcino de Norson). Falta Subcategoría de End Market.

Sheet Casos fuente
A1: Qué ha funcionado en Bachoco: resumen por zona y por línea
A2: Montos = potencial anual registrado en el CRM, NO facturación. "Sin re-registros" quita las ganadas que repiten el mismo monto en la misma zona (posible renovación del mismo negocio dada de alta otra vez; es una pista, no una confirmación; otra lectura posible es potencial por escalón). Celda amarilla: elige "Solo Elegible" (regla del programa) o "Todo el CRM". Las dos columnas de texto de la derecha son fijas y consideran solo ganadas Elegibles.
A3: Universo (elige): | B3: Solo Elegible | C3: criterio: | D3: =IF(B3="Solo Elegible","Elegible","*") -> Elegible
A5: Zona | B5: Ganadas | C5: Perdidas | D5: Abiertas | E5: Tasa de ganancia (ganadas / (ganadas + perdidas)) | F5: Potencial anual ganadas, suma bruta MXN | G5: Potencial anual ganadas, sin re-registros MXN | H5: Primer año con ganada | I5: Última ganada | J5: Líneas ganadas, solo Elegibles (texto fijo) | K5: Distribuidores en las ganadas Elegibles (texto fijo)
A6: Bajío (Celaya) | B6: =COUNTIFS(Oportunidades!$E$2:$E$71,$A6,Oportunidades!$H$2:$H$71,"Ganada",Oportunidades!$D$2:$D$71,"Sí",Oportunidades!$Z$2:$Z$71,$D$3) -> 14 | C6: =COUNTIFS(Oportunidades!$E$2:$E$71,$A6,Oportunidades!$H$2:$H$71,"Perdida",Oportunidades!$D$2:$D$71,"Sí",Oportunidades!$Z$2:$Z$71,$D$3) -> 3 | D6: =COUNTIFS(Oportunidades!$E$2:$E$71,$A6,Oportunidades!$H$2:$H$71,"Abierta",Oportunidades!$D$2:$D$71,"Sí",Oportunidades!$Z$2:$Z$71,$D$3) -> 0 | E6: =IF(B6+C6=0,"-",B6/(B6+C6)) -> 0.82352941 | F6: =SUMIFS(Oportunidades!$K$2:$K$71,Oportunidades!$E$2:$E$71,$A6,Oportunidades!$H$2:$H$71,"Ganada",Oportunidades!$D$2:$D$71,"Sí",Oportunidades!$Z$2:$Z$71,$D$3) -> 6555549.4 | G6: =SUMIFS(Oportunidades!$K$2:$K$71,Oportunidades!$E$2:$E$71,$A6,Oportunidades!$H$2:$H$71,"Ganada",Oportunidades!$D$2:$D$71,"Sí",Oportunidades!$Z$2:$Z$71,$D$3,Oportunidades!$L$2:$L$71,"No") -> 5282674.4 | H6: =IF(B6=0,"-",_xlfn.MINIFS(Oportunidades!$J$2:$J$71,Oportunidades!$E$2:$E$71,$A6,Oportunidades!$H$2:$H$71,"Ganada",Oportunidades!$D$2:$D$71,"Sí",Oportunidades!$Z$2:$Z$71,$D$3)) -> 2019 | I6: =IF(B6=0,"-",_xlfn.MAXIFS(Oportunidades!$I$2:$I$71,Oportunidades!$E$2:$E$71,$A6,Oportunidades!$H$2:$H$71,"Ganada",Oportunidades!$D$2:$D$71,"Sí",Oportunidades!$Z$2:$Z$71,$D$3)) -> 45463 | J6: Banda en V (13); Transmisión (sin detalle) (1) | K6: RYASA Querétaro (12); RYASA Celaya (1); (sin distribuidor en el registro) (1)
A7: Puebla (Tecamachalco) | B7: =COUNTIFS(Oportunidades!$E$2:$E$71,$A7,Oportunidades!$H$2:$H$71,"Ganada",Oportunidades!$D$2:$D$71,"Sí",Oportunidades!$Z$2:$Z$71,$D$3) -> 10 | C7: =COUNTIFS(Oportunidades!$E$2:$E$71,$A7,Oportunidades!$H$2:$H$71,"Perdida",Oportunidades!$D$2:$D$71,"Sí",Oportunidades!$Z$2:$Z$71,$D$3) -> 3 | D7: =COUNTIFS(Oportunidades!$E$2:$E$71,$A7,Oportunidades!$H$2:$H$71,"Abierta",Oportunidades!$D$2:$D$71,"Sí",Oportunidades!$Z$2:$Z$71,$D$3) -> 0 | E7: =IF(B7+C7=0,"-",B7/(B7+C7)) -> 0.76923077 | F7: =SUMIFS(Oportunidades!$K$2:$K$71,Oportunidades!$E$2:$E$71,$A7,Oportunidades!$H$2:$H$71,"Ganada",Oportunidades!$D$2:$D$71,"Sí",Oportunidades!$Z$2:$Z$71,$D$3) -> 2475322.2 | G7: =SUMIFS(Oportunidades!$K$2:$K$71,Oportunidades!$E$2:$E$71,$A7,Oportunidades!$H$2:$H$71,"Ganada",Oportunidades!$D$2:$D$71,"Sí",Oportunidades!$Z$2:$Z$71,$D$3,Oportunidades!$L$2:$L$71,"No") -> 2475322.2 | H7: =IF(B7=0,"-",_xlfn.MINIFS(Oportunidades!$J$2:$J$71,Oportunidades!$E$2:$E$71,$A7,Oportunidades!$H$2:$H$71,"Ganada",Oportunidades!$D$2:$D$71,"Sí",Oportunidades!$Z$2:$Z$71,$D$3)) -> 2020 | I7: =IF(B7=0,"-",_xlfn.MAXIFS(Oportunidades!$I$2:$I$71,Oportunidades!$E$2:$E$71,$A7,Oportunidades!$H$2:$H$71,"Ganada",Oportunidades!$D$2:$D$71,"Sí",Oportunidades!$Z$2:$Z$71,$D$3)) -> 46216 | J7: Banda en V (6); Manguera industrial (4) | K7: Lamuño Puebla (7); Binasa Puebla (2); RILSA 2000 Puebla (1)
A8: Sinaloa (Culiacán) | B8: =COUNTIFS(Oportunidades!$E$2:$E$71,$A8,Oportunidades!$H$2:$H$71,"Ganada",Oportunidades!$D$2:$D$71,"Sí",Oportunidades!$Z$2:$Z$71,$D$3) -> 0 | C8: =COUNTIFS(Oportunidades!$E$2:$E$71,$A8,Oportunidades!$H$2:$H$71,"Perdida",Oportunidades!$D$2:$D$71,"Sí",Oportunidades!$Z$2:$Z$71,$D$3) -> 0 | D8: =COUNTIFS(Oportunidades!$E$2:$E$71,$A8,Oportunidades!$H$2:$H$71,"Abierta",Oportunidades!$D$2:$D$71,"Sí",Oportunidades!$Z$2:$Z$71,$D$3) -> 0 | E8: =IF(B8+C8=0,"-",B8/(B8+C8)) -> - | F8: =SUMIFS(Oportunidades!$K$2:$K$71,Oportunidades!$E$2:$E$71,$A8,Oportunidades!$H$2:$H$71,"Ganada",Oportunidades!$D$2:$D$71,"Sí",Oportunidades!$Z$2:$Z$71,$D$3) -> 0 | G8: =SUMIFS(Oportunidades!$K$2:$K$71,Oportunidades!$E$2:$E$71,$A8,Oportunidades!$H$2:$H$71,"Ganada",Oportunidades!$D$2:$D$71,"Sí",Oportunidades!$Z$2:$Z$71,$D$3,Oportunidades!$L$2:$L$71,"No") -> 0 | H8: =IF(B8=0,"-",_xlfn.MINIFS(Oportunidades!$J$2:$J$71,Oportunidades!$E$2:$E$71,$A8,Oportunidades!$H$2:$H$71,"Ganada",Oportunidades!$D$2:$D$71,"Sí",Oportunidades!$Z$2:$Z$71,$D$3)) -> - | I8: =IF(B8=0,"-",_xlfn.MAXIFS(Oportunidades!$I$2:$I$71,Oportunidades!$E$2:$E$71,$A8,Oportunidades!$H$2:$H$71,"Ganada",Oportunidades!$D$2:$D$71,"Sí",Oportunidades!$Z$2:$Z$71,$D$3)) -> - | J8: - | K8: -
A9: Veracruz | B9: =COUNTIFS(Oportunidades!$E$2:$E$71,$A9,Oportunidades!$H$2:$H$71,"Ganada",Oportunidades!$D$2:$D$71,"Sí",Oportunidades!$Z$2:$Z$71,$D$3) -> 4 | C9: =COUNTIFS(Oportunidades!$E$2:$E$71,$A9,Oportunidades!$H$2:$H$71,"Perdida",Oportunidades!$D$2:$D$71,"Sí",Oportunidades!$Z$2:$Z$71,$D$3) -> 1 | D9: =COUNTIFS(Oportunidades!$E$2:$E$71,$A9,Oportunidades!$H$2:$H$71,"Abierta",Oportunidades!$D$2:$D$71,"Sí",Oportunidades!$Z$2:$Z$71,$D$3) -> 0 | E9: =IF(B9+C9=0,"-",B9/(B9+C9)) -> 0.8 | F9: =SUMIFS(Oportunidades!$K$2:$K$71,Oportunidades!$E$2:$E$71,$A9,Oportunidades!$H$2:$H$71,"Ganada",Oportunidades!$D$2:$D$71,"Sí",Oportunidades!$Z$2:$Z$71,$D$3) -> 993288.57 | G9: =SUMIFS(Oportunidades!$K$2:$K$71,Oportunidades!$E$2:$E$71,$A9,Oportunidades!$H$2:$H$71,"Ganada",Oportunidades!$D$2:$D$71,"Sí",Oportunidades!$Z$2:$Z$71,$D$3,Oportunidades!$L$2:$L$71,"No") -> 993288.57 | H9: =IF(B9=0,"-",_xlfn.MINIFS(Oportunidades!$J$2:$J$71,Oportunidades!$E$2:$E$71,$A9,Oportunidades!$H$2:$H$71,"Ganada",Oportunidades!$D$2:$D$71,"Sí",Oportunidades!$Z$2:$Z$71,$D$3)) -> 2019 | I9: =IF(B9=0,"-",_xlfn.MAXIFS(Oportunidades!$I$2:$I$71,Oportunidades!$E$2:$E$71,$A9,Oportunidades!$H$2:$H$71,"Ganada",Oportunidades!$D$2:$D$71,"Sí",Oportunidades!$Z$2:$Z$71,$D$3)) -> 45378 | J9: Banda en V (3); Manguera hidráulica (1) | K9: RYASA Veracruz (2); SNR Córdoba (1); Comimsa Coatzacoalcos (1)
A10: Yucatán (Mérida/Umán) | B10: =COUNTIFS(Oportunidades!$E$2:$E$71,$A10,Oportunidades!$H$2:$H$71,"Ganada",Oportunidades!$D$2:$D$71,"Sí",Oportunidades!$Z$2:$Z$71,$D$3) -> 3 | C10: =COUNTIFS(Oportunidades!$E$2:$E$71,$A10,Oportunidades!$H$2:$H$71,"Perdida",Oportunidades!$D$2:$D$71,"Sí",Oportunidades!$Z$2:$Z$71,$D$3) -> 0 | D10: =COUNTIFS(Oportunidades!$E$2:$E$71,$A10,Oportunidades!$H$2:$H$71,"Abierta",Oportunidades!$D$2:$D$71,"Sí",Oportunidades!$Z$2:$Z$71,$D$3) -> 1 | E10: =IF(B10+C10=0,"-",B10/(B10+C10)) -> 1 | F10: =SUMIFS(Oportunidades!$K$2:$K$71,Oportunidades!$E$2:$E$71,$A10,Oportunidades!$H$2:$H$71,"Ganada",Oportunidades!$D$2:$D$71,"Sí",Oportunidades!$Z$2:$Z$71,$D$3) -> 566925.29 | G10: =SUMIFS(Oportunidades!$K$2:$K$71,Oportunidades!$E$2:$E$71,$A10,Oportunidades!$H$2:$H$71,"Ganada",Oportunidades!$D$2:$D$71,"Sí",Oportunidades!$Z$2:$Z$71,$D$3,Oportunidades!$L$2:$L$71,"No") -> 566925.29 | H10: =IF(B10=0,"-",_xlfn.MINIFS(Oportunidades!$J$2:$J$71,Oportunidades!$E$2:$E$71,$A10,Oportunidades!$H$2:$H$71,"Ganada",Oportunidades!$D$2:$D$71,"Sí",Oportunidades!$Z$2:$Z$71,$D$3)) -> 2020 | I10: =IF(B10=0,"-",_xlfn.MAXIFS(Oportunidades!$I$2:$I$71,Oportunidades!$E$2:$E$71,$A10,Oportunidades!$H$2:$H$71,"Ganada",Oportunidades!$D$2:$D$71,"Sí",Oportunidades!$Z$2:$Z$71,$D$3)) -> 45437 | J10: Poly Chain (PCC) (1); Manguera industrial (1); Banda en V (1) | K10: EISSA Mérida (3)
A11: Nuevo León (Ciénega de Flores) | B11: =COUNTIFS(Oportunidades!$E$2:$E$71,$A11,Oportunidades!$H$2:$H$71,"Ganada",Oportunidades!$D$2:$D$71,"Sí",Oportunidades!$Z$2:$Z$71,$D$3) -> 0 | C11: =COUNTIFS(Oportunidades!$E$2:$E$71,$A11,Oportunidades!$H$2:$H$71,"Perdida",Oportunidades!$D$2:$D$71,"Sí",Oportunidades!$Z$2:$Z$71,$D$3) -> 0 | D11: =COUNTIFS(Oportunidades!$E$2:$E$71,$A11,Oportunidades!$H$2:$H$71,"Abierta",Oportunidades!$D$2:$D$71,"Sí",Oportunidades!$Z$2:$Z$71,$D$3) -> 0 | E11: =IF(B11+C11=0,"-",B11/(B11+C11)) -> - | F11: =SUMIFS(Oportunidades!$K$2:$K$71,Oportunidades!$E$2:$E$71,$A11,Oportunidades!$H$2:$H$71,"Ganada",Oportunidades!$D$2:$D$71,"Sí",Oportunidades!$Z$2:$Z$71,$D$3) -> 0 | G11: =SUMIFS(Oportunidades!$K$2:$K$71,Oportunidades!$E$2:$E$71,$A11,Oportunidades!$H$2:$H$71,"Ganada",Oportunidades!$D$2:$D$71,"Sí",Oportunidades!$Z$2:$Z$71,$D$3,Oportunidades!$L$2:$L$71,"No") -> 0 | H11: =IF(B11=0,"-",_xlfn.MINIFS(Oportunidades!$J$2:$J$71,Oportunidades!$E$2:$E$71,$A11,Oportunidades!$H$2:$H$71,"Ganada",Oportunidades!$D$2:$D$71,"Sí",Oportunidades!$Z$2:$Z$71,$D$3)) -> - | I11: =IF(B11=0,"-",_xlfn.MAXIFS(Oportunidades!$I$2:$I$71,Oportunidades!$E$2:$E$71,$A11,Oportunidades!$H$2:$H$71,"Ganada",Oportunidades!$D$2:$D$71,"Sí",Oportunidades!$Z$2:$Z$71,$D$3)) -> - | J11: - | K11: -
A12: Noroeste (Sonora/BC) | B12: =COUNTIFS(Oportunidades!$E$2:$E$71,$A12,Oportunidades!$H$2:$H$71,"Ganada",Oportunidades!$D$2:$D$71,"Sí",Oportunidades!$Z$2:$Z$71,$D$3) -> 0 | C12: =COUNTIFS(Oportunidades!$E$2:$E$71,$A12,Oportunidades!$H$2:$H$71,"Perdida",Oportunidades!$D$2:$D$71,"Sí",Oportunidades!$Z$2:$Z$71,$D$3) -> 6 | D12: =COUNTIFS(Oportunidades!$E$2:$E$71,$A12,Oportunidades!$H$2:$H$71,"Abierta",Oportunidades!$D$2:$D$71,"Sí",Oportunidades!$Z$2:$Z$71,$D$3) -> 0 | E12: =IF(B12+C12=0,"-",B12/(B12+C12)) -> 0 | F12: =SUMIFS(Oportunidades!$K$2:$K$71,Oportunidades!$E$2:$E$71,$A12,Oportunidades!$H$2:$H$71,"Ganada",Oportunidades!$D$2:$D$71,"Sí",Oportunidades!$Z$2:$Z$71,$D$3) -> 0 | G12: =SUMIFS(Oportunidades!$K$2:$K$71,Oportunidades!$E$2:$E$71,$A12,Oportunidades!$H$2:$H$71,"Ganada",Oportunidades!$D$2:$D$71,"Sí",Oportunidades!$Z$2:$Z$71,$D$3,Oportunidades!$L$2:$L$71,"No") -> 0 | H12: =IF(B12=0,"-",_xlfn.MINIFS(Oportunidades!$J$2:$J$71,Oportunidades!$E$2:$E$71,$A12,Oportunidades!$H$2:$H$71,"Ganada",Oportunidades!$D$2:$D$71,"Sí",Oportunidades!$Z$2:$Z$71,$D$3)) -> - | I12: =IF(B12=0,"-",_xlfn.MAXIFS(Oportunidades!$I$2:$I$71,Oportunidades!$E$2:$E$71,$A12,Oportunidades!$H$2:$H$71,"Ganada",Oportunidades!$D$2:$D$71,"Sí",Oportunidades!$Z$2:$Z$71,$D$3)) -> - | J12: - | K12: -
A13: Durango (Gómez Palacio) | B13: =COUNTIFS(Oportunidades!$E$2:$E$71,$A13,Oportunidades!$H$2:$H$71,"Ganada",Oportunidades!$D$2:$D$71,"Sí",Oportunidades!$Z$2:$Z$71,$D$3) -> 0 | C13: =COUNTIFS(Oportunidades!$E$2:$E$71,$A13,Oportunidades!$H$2:$H$71,"Perdida",Oportunidades!$D$2:$D$71,"Sí",Oportunidades!$Z$2:$Z$71,$D$3) -> 1 | D13: =COUNTIFS(Oportunidades!$E$2:$E$71,$A13,Oportunidades!$H$2:$H$71,"Abierta",Oportunidades!$D$2:$D$71,"Sí",Oportunidades!$Z$2:$Z$71,$D$3) -> 0 | E13: =IF(B13+C13=0,"-",B13/(B13+C13)) -> 0 | F13: =SUMIFS(Oportunidades!$K$2:$K$71,Oportunidades!$E$2:$E$71,$A13,Oportunidades!$H$2:$H$71,"Ganada",Oportunidades!$D$2:$D$71,"Sí",Oportunidades!$Z$2:$Z$71,$D$3) -> 0 | G13: =SUMIFS(Oportunidades!$K$2:$K$71,Oportunidades!$E$2:$E$71,$A13,Oportunidades!$H$2:$H$71,"Ganada",Oportunidades!$D$2:$D$71,"Sí",Oportunidades!$Z$2:$Z$71,$D$3,Oportunidades!$L$2:$L$71,"No") -> 0 | H13: =IF(B13=0,"-",_xlfn.MINIFS(Oportunidades!$J$2:$J$71,Oportunidades!$E$2:$E$71,$A13,Oportunidades!$H$2:$H$71,"Ganada",Oportunidades!$D$2:$D$71,"Sí",Oportunidades!$Z$2:$Z$71,$D$3)) -> - | I13: =IF(B13=0,"-",_xlfn.MAXIFS(Oportunidades!$I$2:$I$71,Oportunidades!$E$2:$E$71,$A13,Oportunidades!$H$2:$H$71,"Ganada",Oportunidades!$D$2:$D$71,"Sí",Oportunidades!$Z$2:$Z$71,$D$3)) -> - | J13: - | K13: -
A14: San Luis Potosí | B14: =COUNTIFS(Oportunidades!$E$2:$E$71,$A14,Oportunidades!$H$2:$H$71,"Ganada",Oportunidades!$D$2:$D$71,"Sí",Oportunidades!$Z$2:$Z$71,$D$3) -> 0 | C14: =COUNTIFS(Oportunidades!$E$2:$E$71,$A14,Oportunidades!$H$2:$H$71,"Perdida",Oportunidades!$D$2:$D$71,"Sí",Oportunidades!$Z$2:$Z$71,$D$3) -> 0 | D14: =COUNTIFS(Oportunidades!$E$2:$E$71,$A14,Oportunidades!$H$2:$H$71,"Abierta",Oportunidades!$D$2:$D$71,"Sí",Oportunidades!$Z$2:$Z$71,$D$3) -> 0 | E14: =IF(B14+C14=0,"-",B14/(B14+C14)) -> - | F14: =SUMIFS(Oportunidades!$K$2:$K$71,Oportunidades!$E$2:$E$71,$A14,Oportunidades!$H$2:$H$71,"Ganada",Oportunidades!$D$2:$D$71,"Sí",Oportunidades!$Z$2:$Z$71,$D$3) -> 0 | G14: =SUMIFS(Oportunidades!$K$2:$K$71,Oportunidades!$E$2:$E$71,$A14,Oportunidades!$H$2:$H$71,"Ganada",Oportunidades!$D$2:$D$71,"Sí",Oportunidades!$Z$2:$Z$71,$D$3,Oportunidades!$L$2:$L$71,"No") -> 0 | H14: =IF(B14=0,"-",_xlfn.MINIFS(Oportunidades!$J$2:$J$71,Oportunidades!$E$2:$E$71,$A14,Oportunidades!$H$2:$H$71,"Ganada",Oportunidades!$D$2:$D$71,"Sí",Oportunidades!$Z$2:$Z$71,$D$3)) -> - | I14: =IF(B14=0,"-",_xlfn.MAXIFS(Oportunidades!$I$2:$I$71,Oportunidades!$E$2:$E$71,$A14,Oportunidades!$H$2:$H$71,"Ganada",Oportunidades!$D$2:$D$71,"Sí",Oportunidades!$Z$2:$Z$71,$D$3)) -> - | J14: - | K14: -
A15: Morelos (Cuautla) | B15: =COUNTIFS(Oportunidades!$E$2:$E$71,$A15,Oportunidades!$H$2:$H$71,"Ganada",Oportunidades!$D$2:$D$71,"Sí",Oportunidades!$Z$2:$Z$71,$D$3) -> 0 | C15: =COUNTIFS(Oportunidades!$E$2:$E$71,$A15,Oportunidades!$H$2:$H$71,"Perdida",Oportunidades!$D$2:$D$71,"Sí",Oportunidades!$Z$2:$Z$71,$D$3) -> 0 | D15: =COUNTIFS(Oportunidades!$E$2:$E$71,$A15,Oportunidades!$H$2:$H$71,"Abierta",Oportunidades!$D$2:$D$71,"Sí",Oportunidades!$Z$2:$Z$71,$D$3) -> 0 | E15: =IF(B15+C15=0,"-",B15/(B15+C15)) -> - | F15: =SUMIFS(Oportunidades!$K$2:$K$71,Oportunidades!$E$2:$E$71,$A15,Oportunidades!$H$2:$H$71,"Ganada",Oportunidades!$D$2:$D$71,"Sí",Oportunidades!$Z$2:$Z$71,$D$3) -> 0 | G15: =SUMIFS(Oportunidades!$K$2:$K$71,Oportunidades!$E$2:$E$71,$A15,Oportunidades!$H$2:$H$71,"Ganada",Oportunidades!$D$2:$D$71,"Sí",Oportunidades!$Z$2:$Z$71,$D$3,Oportunidades!$L$2:$L$71,"No") -> 0 | H15: =IF(B15=0,"-",_xlfn.MINIFS(Oportunidades!$J$2:$J$71,Oportunidades!$E$2:$E$71,$A15,Oportunidades!$H$2:$H$71,"Ganada",Oportunidades!$D$2:$D$71,"Sí",Oportunidades!$Z$2:$Z$71,$D$3)) -> - | I15: =IF(B15=0,"-",_xlfn.MAXIFS(Oportunidades!$I$2:$I$71,Oportunidades!$E$2:$E$71,$A15,Oportunidades!$H$2:$H$71,"Ganada",Oportunidades!$D$2:$D$71,"Sí",Oportunidades!$Z$2:$Z$71,$D$3)) -> - | J15: - | K15: -
A16: Total | B16: =SUM(B6:B15) -> 31 | C16: =SUM(C6:C15) -> 14 | D16: =SUM(D6:D15) -> 1 | E16: =B16/(B16+C16) -> 0.68888889 | F16: =SUM(F6:F15) -> 10591086 | G16: =SUM(G6:G15) -> 9318210.5
A19: Por grupo de línea (todas las zonas; según el universo elegido arriba)
A20: Grupo de línea | B20: Ganadas | C20: Perdidas | D20: Abiertas | E20: Tasa de ganancia | F20: Potencial anual ganadas, suma bruta MXN
A21: Bandas en V | B21: =COUNTIFS(Oportunidades!$P$2:$P$71,$A21,Oportunidades!$H$2:$H$71,"Ganada",Oportunidades!$D$2:$D$71,"Sí",Oportunidades!$Z$2:$Z$71,$D$3) -> 23 | C21: =COUNTIFS(Oportunidades!$P$2:$P$71,$A21,Oportunidades!$H$2:$H$71,"Perdida",Oportunidades!$D$2:$D$71,"Sí",Oportunidades!$Z$2:$Z$71,$D$3) -> 2 | D21: =COUNTIFS(Oportunidades!$P$2:$P$71,$A21,Oportunidades!$H$2:$H$71,"Abierta",Oportunidades!$D$2:$D$71,"Sí",Oportunidades!$Z$2:$Z$71,$D$3) -> 1 | E21: =IF(B21+C21=0,"-",B21/(B21+C21)) -> 0.92 | F21: =SUMIFS(Oportunidades!$K$2:$K$71,Oportunidades!$P$2:$P$71,$A21,Oportunidades!$H$2:$H$71,"Ganada",Oportunidades!$D$2:$D$71,"Sí",Oportunidades!$Z$2:$Z$71,$D$3) -> 9408540.7
A22: Bandas síncronas, poliuretano y micro-V | B22: =COUNTIFS(Oportunidades!$P$2:$P$71,$A22,Oportunidades!$H$2:$H$71,"Ganada",Oportunidades!$D$2:$D$71,"Sí",Oportunidades!$Z$2:$Z$71,$D$3) -> 1 | C22: =COUNTIFS(Oportunidades!$P$2:$P$71,$A22,Oportunidades!$H$2:$H$71,"Perdida",Oportunidades!$D$2:$D$71,"Sí",Oportunidades!$Z$2:$Z$71,$D$3) -> 6 | D22: =COUNTIFS(Oportunidades!$P$2:$P$71,$A22,Oportunidades!$H$2:$H$71,"Abierta",Oportunidades!$D$2:$D$71,"Sí",Oportunidades!$Z$2:$Z$71,$D$3) -> 0 | E22: =IF(B22+C22=0,"-",B22/(B22+C22)) -> 0.14285714 | F22: =SUMIFS(Oportunidades!$K$2:$K$71,Oportunidades!$P$2:$P$71,$A22,Oportunidades!$H$2:$H$71,"Ganada",Oportunidades!$D$2:$D$71,"Sí",Oportunidades!$Z$2:$Z$71,$D$3) -> 103166.25
A23: Manguera industrial | B23: =COUNTIFS(Oportunidades!$P$2:$P$71,$A23,Oportunidades!$H$2:$H$71,"Ganada",Oportunidades!$D$2:$D$71,"Sí",Oportunidades!$Z$2:$Z$71,$D$3) -> 5 | C23: =COUNTIFS(Oportunidades!$P$2:$P$71,$A23,Oportunidades!$H$2:$H$71,"Perdida",Oportunidades!$D$2:$D$71,"Sí",Oportunidades!$Z$2:$Z$71,$D$3) -> 1 | D23: =COUNTIFS(Oportunidades!$P$2:$P$71,$A23,Oportunidades!$H$2:$H$71,"Abierta",Oportunidades!$D$2:$D$71,"Sí",Oportunidades!$Z$2:$Z$71,$D$3) -> 0 | E23: =IF(B23+C23=0,"-",B23/(B23+C23)) -> 0.83333333 | F23: =SUMIFS(Oportunidades!$K$2:$K$71,Oportunidades!$P$2:$P$71,$A23,Oportunidades!$H$2:$H$71,"Ganada",Oportunidades!$D$2:$D$71,"Sí",Oportunidades!$Z$2:$Z$71,$D$3) -> 651385.46
A24: Manguera hidráulica y neumática | B24: =COUNTIFS(Oportunidades!$P$2:$P$71,$A24,Oportunidades!$H$2:$H$71,"Ganada",Oportunidades!$D$2:$D$71,"Sí",Oportunidades!$Z$2:$Z$71,$D$3) -> 1 | C24: =COUNTIFS(Oportunidades!$P$2:$P$71,$A24,Oportunidades!$H$2:$H$71,"Perdida",Oportunidades!$D$2:$D$71,"Sí",Oportunidades!$Z$2:$Z$71,$D$3) -> 4 | D24: =COUNTIFS(Oportunidades!$P$2:$P$71,$A24,Oportunidades!$H$2:$H$71,"Abierta",Oportunidades!$D$2:$D$71,"Sí",Oportunidades!$Z$2:$Z$71,$D$3) -> 0 | E24: =IF(B24+C24=0,"-",B24/(B24+C24)) -> 0.2 | F24: =SUMIFS(Oportunidades!$K$2:$K$71,Oportunidades!$P$2:$P$71,$A24,Oportunidades!$H$2:$H$71,"Ganada",Oportunidades!$D$2:$D$71,"Sí",Oportunidades!$Z$2:$Z$71,$D$3) -> 288865.44
A25: Otras o sin detalle de producto | B25: =COUNTIFS(Oportunidades!$P$2:$P$71,$A25,Oportunidades!$H$2:$H$71,"Ganada",Oportunidades!$D$2:$D$71,"Sí",Oportunidades!$Z$2:$Z$71,$D$3) -> 1 | C25: =COUNTIFS(Oportunidades!$P$2:$P$71,$A25,Oportunidades!$H$2:$H$71,"Perdida",Oportunidades!$D$2:$D$71,"Sí",Oportunidades!$Z$2:$Z$71,$D$3) -> 1 | D25: =COUNTIFS(Oportunidades!$P$2:$P$71,$A25,Oportunidades!$H$2:$H$71,"Abierta",Oportunidades!$D$2:$D$71,"Sí",Oportunidades!$Z$2:$Z$71,$D$3) -> 0 | E25: =IF(B25+C25=0,"-",B25/(B25+C25)) -> 0.5 | F25: =SUMIFS(Oportunidades!$K$2:$K$71,Oportunidades!$P$2:$P$71,$A25,Oportunidades!$H$2:$H$71,"Ganada",Oportunidades!$D$2:$D$71,"Sí",Oportunidades!$Z$2:$Z$71,$D$3) -> 139127.64
A28: Ganadas por año de cierre (cuentas Bachoco; según el universo elegido arriba)
A29: Año | B29: 2019 | C29: 2020 | D29: 2021 | E29: 2022 | F29: 2023 | G29: 2024 | H29: 2025 | I29: 2026
A30: Ganadas | B30: =COUNTIFS(Oportunidades!$J$2:$J$71,2019,Oportunidades!$H$2:$H$71,"Ganada",Oportunidades!$D$2:$D$71,"Sí",Oportunidades!$Z$2:$Z$71,$D$3) -> 2 | C30: =COUNTIFS(Oportunidades!$J$2:$J$71,2020,Oportunidades!$H$2:$H$71,"Ganada",Oportunidades!$D$2:$D$71,"Sí",Oportunidades!$Z$2:$Z$71,$D$3) -> 9 | D30: =COUNTIFS(Oportunidades!$J$2:$J$71,2021,Oportunidades!$H$2:$H$71,"Ganada",Oportunidades!$D$2:$D$71,"Sí",Oportunidades!$Z$2:$Z$71,$D$3) -> 5 | E30: =COUNTIFS(Oportunidades!$J$2:$J$71,2022,Oportunidades!$H$2:$H$71,"Ganada",Oportunidades!$D$2:$D$71,"Sí",Oportunidades!$Z$2:$Z$71,$D$3) -> 5 | F30: =COUNTIFS(Oportunidades!$J$2:$J$71,2023,Oportunidades!$H$2:$H$71,"Ganada",Oportunidades!$D$2:$D$71,"Sí",Oportunidades!$Z$2:$Z$71,$D$3) -> 4 | G30: =COUNTIFS(Oportunidades!$J$2:$J$71,2024,Oportunidades!$H$2:$H$71,"Ganada",Oportunidades!$D$2:$D$71,"Sí",Oportunidades!$Z$2:$Z$71,$D$3) -> 4 | H30: =COUNTIFS(Oportunidades!$J$2:$J$71,2025,Oportunidades!$H$2:$H$71,"Ganada",Oportunidades!$D$2:$D$71,"Sí",Oportunidades!$Z$2:$Z$71,$D$3) -> 1 | I30: =COUNTIFS(Oportunidades!$J$2:$J$71,2026,Oportunidades!$H$2:$H$71,"Ganada",Oportunidades!$D$2:$D$71,"Sí",Oportunidades!$Z$2:$Z$71,$D$3) -> 1
A31: 2026 es parcial. La base DETALLE tiene corte al 12-ago-2026; el archivo IR incluye registros hasta al menos el 31-ago-2026.
A34: Las 12 ganadas Elegibles con mayor potencial anual registrado
A35: Núm. de oportunidad | B35: Nomenclatura completa | C35: Zona | D35: Fecha de cierre | E35: Potencial anual MXN | F35: Posible re-registro | G35: Decisión del programa
A36: 569067 | B36: =INDEX(Oportunidades!$B$2:$B$71,MATCH($A36,Oportunidades!$A$2:$A$71,0)) -> 7.1 PTI- BACHOCO, S.A. DE C.V - Planta de alimentos division Bajio PT-V-BELTS-569067- RYASA QRO | C36: =INDEX(Oportunidades!$E$2:$E$71,MATCH($A36,Oportunidades!$A$2:$A$71,0)) -> Bajío (Celaya) | D36: =INDEX(Oportunidades!$I$2:$I$71,MATCH($A36,Oportunidades!$A$2:$A$71,0)) -> 44741 | E36: =INDEX(Oportunidades!$K$2:$K$71,MATCH($A36,Oportunidades!$A$2:$A$71,0)) -> 963376.43 | F36: =INDEX(Oportunidades!$L$2:$L$71,MATCH($A36,Oportunidades!$A$2:$A$71,0)) -> No | G36: =INDEX(Oportunidades!$Z$2:$Z$71,MATCH($A36,Oportunidades!$A$2:$A$71,0)) -> Elegible
A37: O-00244487 | B37: =INDEX(Oportunidades!$B$2:$B$71,MATCH($A37,Oportunidades!$A$2:$A$71,0)) -> 7.1 PTI-BACHOCO BAJIO-RYASA QRO | C37: =INDEX(Oportunidades!$E$2:$E$71,MATCH($A37,Oportunidades!$A$2:$A$71,0)) -> Bajío (Celaya) | D37: =INDEX(Oportunidades!$I$2:$I$71,MATCH($A37,Oportunidades!$A$2:$A$71,0)) -> 44188 | E37: =INDEX(Oportunidades!$K$2:$K$71,MATCH($A37,Oportunidades!$A$2:$A$71,0)) -> 927517.91 | F37: =INDEX(Oportunidades!$L$2:$L$71,MATCH($A37,Oportunidades!$A$2:$A$71,0)) -> No | G37: =INDEX(Oportunidades!$Z$2:$Z$71,MATCH($A37,Oportunidades!$A$2:$A$71,0)) -> Elegible
A38: 571620 | B38: =INDEX(Oportunidades!$B$2:$B$71,MATCH($A38,Oportunidades!$A$2:$A$71,0)) -> 7.1 V-Belts Bachoco Tecamachalco Lamuño Puebla. | C38: =INDEX(Oportunidades!$E$2:$E$71,MATCH($A38,Oportunidades!$A$2:$A$71,0)) -> Puebla (Tecamachalco) | D38: =INDEX(Oportunidades!$I$2:$I$71,MATCH($A38,Oportunidades!$A$2:$A$71,0)) -> 44771 | E38: =INDEX(Oportunidades!$K$2:$K$71,MATCH($A38,Oportunidades!$A$2:$A$71,0)) -> 613057.77 | F38: =INDEX(Oportunidades!$L$2:$L$71,MATCH($A38,Oportunidades!$A$2:$A$71,0)) -> No | G38: =INDEX(Oportunidades!$Z$2:$Z$71,MATCH($A38,Oportunidades!$A$2:$A$71,0)) -> Elegible
A39: O-00245158 | B39: =INDEX(Oportunidades!$B$2:$B$71,MATCH($A39,Oportunidades!$A$2:$A$71,0)) -> 2.2 Pti Bachoco RYASA | C39: =INDEX(Oportunidades!$E$2:$E$71,MATCH($A39,Oportunidades!$A$2:$A$71,0)) -> Bajío (Celaya) | D39: =INDEX(Oportunidades!$I$2:$I$71,MATCH($A39,Oportunidades!$A$2:$A$71,0)) -> 44065 | E39: =INDEX(Oportunidades!$K$2:$K$71,MATCH($A39,Oportunidades!$A$2:$A$71,0)) -> 556510.74 | F39: =INDEX(Oportunidades!$L$2:$L$71,MATCH($A39,Oportunidades!$A$2:$A$71,0)) -> No | G39: =INDEX(Oportunidades!$Z$2:$Z$71,MATCH($A39,Oportunidades!$A$2:$A$71,0)) -> Elegible
A40: 648860 | B40: =INDEX(Oportunidades!$B$2:$B$71,MATCH($A40,Oportunidades!$A$2:$A$71,0)) -> 7.1 V-Belts Bachoco Veracruz SNR Córdoba | C40: =INDEX(Oportunidades!$E$2:$E$71,MATCH($A40,Oportunidades!$A$2:$A$71,0)) -> Veracruz | D40: =INDEX(Oportunidades!$I$2:$I$71,MATCH($A40,Oportunidades!$A$2:$A$71,0)) -> 45015 | E40: =INDEX(Oportunidades!$K$2:$K$71,MATCH($A40,Oportunidades!$A$2:$A$71,0)) -> 538004.45 | F40: =INDEX(Oportunidades!$L$2:$L$71,MATCH($A40,Oportunidades!$A$2:$A$71,0)) -> No | G40: =INDEX(Oportunidades!$Z$2:$Z$71,MATCH($A40,Oportunidades!$A$2:$A$71,0)) -> Elegible
A41: 643201 | B41: =INDEX(Oportunidades!$B$2:$B$71,MATCH($A41,Oportunidades!$A$2:$A$71,0)) -> 7.1 V-Belts Bachoco, S.A. de C.V. - Planta procesadora de aves Guanajuato - Guanajuato PT-V-BELTS-643201 | C41: =INDEX(Oportunidades!$E$2:$E$71,MATCH($A41,Oportunidades!$A$2:$A$71,0)) -> Bajío (Celaya) | D41: =INDEX(Oportunidades!$I$2:$I$71,MATCH($A41,Oportunidades!$A$2:$A$71,0)) -> 45043 | E41: =INDEX(Oportunidades!$K$2:$K$71,MATCH($A41,Oportunidades!$A$2:$A$71,0)) -> 538004.45 | F41: =INDEX(Oportunidades!$L$2:$L$71,MATCH($A41,Oportunidades!$A$2:$A$71,0)) -> No | G41: =INDEX(Oportunidades!$Z$2:$Z$71,MATCH($A41,Oportunidades!$A$2:$A$71,0)) -> Elegible
A42: 555451 | B42: =INDEX(Oportunidades!$B$2:$B$71,MATCH($A42,Oportunidades!$A$2:$A$71,0)) -> 2.2 PTI Optibelt Bachoco, S.A. de C.V. - Planta procesadora de aves Guanajuato - Guanajuato PT-V-BELTS-555451- Ryasa Qro. | C42: =INDEX(Oportunidades!$E$2:$E$71,MATCH($A42,Oportunidades!$A$2:$A$71,0)) -> Bajío (Celaya) | D42: =INDEX(Oportunidades!$I$2:$I$71,MATCH($A42,Oportunidades!$A$2:$A$71,0)) -> 44589 | E42: =INDEX(Oportunidades!$K$2:$K$71,MATCH($A42,Oportunidades!$A$2:$A$71,0)) -> 525478.07 | F42: =INDEX(Oportunidades!$L$2:$L$71,MATCH($A42,Oportunidades!$A$2:$A$71,0)) -> No | G42: =INDEX(Oportunidades!$Z$2:$Z$71,MATCH($A42,Oportunidades!$A$2:$A$71,0)) -> Elegible
A43: 555609 | B43: =INDEX(Oportunidades!$B$2:$B$71,MATCH($A43,Oportunidades!$A$2:$A$71,0)) -> 2.2 PTI Optibelt Bachoco, S.A. de C.V. - Planta procesadora de aves Guanajuato - Guanajuato PT-V-BELTS-555609- Ryasa Qro | C43: =INDEX(Oportunidades!$E$2:$E$71,MATCH($A43,Oportunidades!$A$2:$A$71,0)) -> Bajío (Celaya) | D43: =INDEX(Oportunidades!$I$2:$I$71,MATCH($A43,Oportunidades!$A$2:$A$71,0)) -> 44589 | E43: =INDEX(Oportunidades!$K$2:$K$71,MATCH($A43,Oportunidades!$A$2:$A$71,0)) -> 525478.07 | F43: =INDEX(Oportunidades!$L$2:$L$71,MATCH($A43,Oportunidades!$A$2:$A$71,0)) -> Sí | G43: =INDEX(Oportunidades!$Z$2:$Z$71,MATCH($A43,Oportunidades!$A$2:$A$71,0)) -> Elegible
A44: 521646 | B44: =INDEX(Oportunidades!$B$2:$B$71,MATCH($A44,Oportunidades!$A$2:$A$71,0)) -> 7.1 Bachoco, S.A. de C.V. - Planta procesadora de aves Guanajuato - Guanajuato PT-V-BELTS-521646 | C44: =INDEX(Oportunidades!$E$2:$E$71,MATCH($A44,Oportunidades!$A$2:$A$71,0)) -> Bajío (Celaya) | D44: =INDEX(Oportunidades!$I$2:$I$71,MATCH($A44,Oportunidades!$A$2:$A$71,0)) -> 44286 | E44: =INDEX(Oportunidades!$K$2:$K$71,MATCH($A44,Oportunidades!$A$2:$A$71,0)) -> 437898.36 | F44: =INDEX(Oportunidades!$L$2:$L$71,MATCH($A44,Oportunidades!$A$2:$A$71,0)) -> No | G44: =INDEX(Oportunidades!$Z$2:$Z$71,MATCH($A44,Oportunidades!$A$2:$A$71,0)) -> Elegible
A45: 544435 | B45: =INDEX(Oportunidades!$B$2:$B$71,MATCH($A45,Oportunidades!$A$2:$A$71,0)) -> 2.2 PTI-Bachoco, S.A. de C.V. - Planta procesadora de aves Guanajuato - Guanajuato PT-V-BELTS-Ryasa Qro | C45: =INDEX(Oportunidades!$E$2:$E$71,MATCH($A45,Oportunidades!$A$2:$A$71,0)) -> Bajío (Celaya) | D45: =INDEX(Oportunidades!$I$2:$I$71,MATCH($A45,Oportunidades!$A$2:$A$71,0)) -> 44435 | E45: =INDEX(Oportunidades!$K$2:$K$71,MATCH($A45,Oportunidades!$A$2:$A$71,0)) -> 437898.36 | F45: =INDEX(Oportunidades!$L$2:$L$71,MATCH($A45,Oportunidades!$A$2:$A$71,0)) -> Sí | G45: =INDEX(Oportunidades!$Z$2:$Z$71,MATCH($A45,Oportunidades!$A$2:$A$71,0)) -> Elegible
A46: 807192 | B46: =INDEX(Oportunidades!$B$2:$B$71,MATCH($A46,Oportunidades!$A$2:$A$71,0)) -> 7.1 V-Belts Tripower AX60 Bachoco Tecamachalco RILSA2000 Puebla. | C46: =INDEX(Oportunidades!$E$2:$E$71,MATCH($A46,Oportunidades!$A$2:$A$71,0)) -> Puebla (Tecamachalco) | D46: =INDEX(Oportunidades!$I$2:$I$71,MATCH($A46,Oportunidades!$A$2:$A$71,0)) -> 46216 | E46: =INDEX(Oportunidades!$K$2:$K$71,MATCH($A46,Oportunidades!$A$2:$A$71,0)) -> 394199.93 | F46: =INDEX(Oportunidades!$L$2:$L$71,MATCH($A46,Oportunidades!$A$2:$A$71,0)) -> No | G46: =INDEX(Oportunidades!$Z$2:$Z$71,MATCH($A46,Oportunidades!$A$2:$A$71,0)) -> Elegible
A47: O-00249207 | B47: =INDEX(Oportunidades!$B$2:$B$71,MATCH($A47,Oportunidades!$A$2:$A$71,0)) -> 2.2 V-Belts-Bachoco Tecamachalco Lamuño Puebla | C47: =INDEX(Oportunidades!$E$2:$E$71,MATCH($A47,Oportunidades!$A$2:$A$71,0)) -> Puebla (Tecamachalco) | D47: =INDEX(Oportunidades!$I$2:$I$71,MATCH($A47,Oportunidades!$A$2:$A$71,0)) -> 44064 | E47: =INDEX(Oportunidades!$K$2:$K$71,MATCH($A47,Oportunidades!$A$2:$A$71,0)) -> 371007.16 | F47: =INDEX(Oportunidades!$L$2:$L$71,MATCH($A47,Oportunidades!$A$2:$A$71,0)) -> No | G47: =INDEX(Oportunidades!$Z$2:$Z$71,MATCH($A47,Oportunidades!$A$2:$A$71,0)) -> Elegible

Sheet Zona x Línea
A1: Oportunidades de las cuentas Bachoco por zona y línea de producto
A2: Son conteos de oportunidades del CRM (no pesos). La línea sale de la nomenclatura de cada oportunidad; "Zona" agrupa cuentas por lugar. Celda amarilla: elige "Solo Elegible" (regla del programa) o "Todo el CRM". Un cero significa que no hay registro, no que no se pueda vender. Culiacán y Ciénega de Flores aparecen en cero con "Solo Elegible" porque el programa no marcó Elegibles sus oportunidades (ver hoja Clasificación dudosa).
A3: Universo (elige): | B3: Solo Elegible | C3: criterio: | D3: =IF(B3="Solo Elegible","Elegible","*") -> Elegible
A5: GANADAS
A6: Zona | B6: Bandas en V | C6: Bandas síncronas, poliuretano y micro-V | D6: Manguera industrial | E6: Manguera hidráulica y neumática | F6: Otras o sin detalle de producto | G6: Total
A7: Bajío (Celaya) | B7: =COUNTIFS(Oportunidades!$E$2:$E$71,$A7,Oportunidades!$P$2:$P$71,B$6,Oportunidades!$H$2:$H$71,"Ganada",Oportunidades!$D$2:$D$71,"Sí",Oportunidades!$Z$2:$Z$71,$D$3) -> 13 | C7: =COUNTIFS(Oportunidades!$E$2:$E$71,$A7,Oportunidades!$P$2:$P$71,C$6,Oportunidades!$H$2:$H$71,"Ganada",Oportunidades!$D$2:$D$71,"Sí",Oportunidades!$Z$2:$Z$71,$D$3) -> 0 | D7: =COUNTIFS(Oportunidades!$E$2:$E$71,$A7,Oportunidades!$P$2:$P$71,D$6,Oportunidades!$H$2:$H$71,"Ganada",Oportunidades!$D$2:$D$71,"Sí",Oportunidades!$Z$2:$Z$71,$D$3) -> 0 | E7: =COUNTIFS(Oportunidades!$E$2:$E$71,$A7,Oportunidades!$P$2:$P$71,E$6,Oportunidades!$H$2:$H$71,"Ganada",Oportunidades!$D$2:$D$71,"Sí",Oportunidades!$Z$2:$Z$71,$D$3) -> 0 | F7: =COUNTIFS(Oportunidades!$E$2:$E$71,$A7,Oportunidades!$P$2:$P$71,F$6,Oportunidades!$H$2:$H$71,"Ganada",Oportunidades!$D$2:$D$71,"Sí",Oportunidades!$Z$2:$Z$71,$D$3) -> 1 | G7: =SUM(B7:F7) -> 14
A8: Puebla (Tecamachalco) | B8: =COUNTIFS(Oportunidades!$E$2:$E$71,$A8,Oportunidades!$P$2:$P$71,B$6,Oportunidades!$H$2:$H$71,"Ganada",Oportunidades!$D$2:$D$71,"Sí",Oportunidades!$Z$2:$Z$71,$D$3) -> 6 | C8: =COUNTIFS(Oportunidades!$E$2:$E$71,$A8,Oportunidades!$P$2:$P$71,C$6,Oportunidades!$H$2:$H$71,"Ganada",Oportunidades!$D$2:$D$71,"Sí",Oportunidades!$Z$2:$Z$71,$D$3) -> 0 | D8: =COUNTIFS(Oportunidades!$E$2:$E$71,$A8,Oportunidades!$P$2:$P$71,D$6,Oportunidades!$H$2:$H$71,"Ganada",Oportunidades!$D$2:$D$71,"Sí",Oportunidades!$Z$2:$Z$71,$D$3) -> 4 | E8: =COUNTIFS(Oportunidades!$E$2:$E$71,$A8,Oportunidades!$P$2:$P$71,E$6,Oportunidades!$H$2:$H$71,"Ganada",Oportunidades!$D$2:$D$71,"Sí",Oportunidades!$Z$2:$Z$71,$D$3) -> 0 | F8: =COUNTIFS(Oportunidades!$E$2:$E$71,$A8,Oportunidades!$P$2:$P$71,F$6,Oportunidades!$H$2:$H$71,"Ganada",Oportunidades!$D$2:$D$71,"Sí",Oportunidades!$Z$2:$Z$71,$D$3) -> 0 | G8: =SUM(B8:F8) -> 10
A9: Sinaloa (Culiacán) | B9: =COUNTIFS(Oportunidades!$E$2:$E$71,$A9,Oportunidades!$P$2:$P$71,B$6,Oportunidades!$H$2:$H$71,"Ganada",Oportunidades!$D$2:$D$71,"Sí",Oportunidades!$Z$2:$Z$71,$D$3) -> 0 | C9: =COUNTIFS(Oportunidades!$E$2:$E$71,$A9,Oportunidades!$P$2:$P$71,C$6,Oportunidades!$H$2:$H$71,"Ganada",Oportunidades!$D$2:$D$71,"Sí",Oportunidades!$Z$2:$Z$71,$D$3) -> 0 | D9: =COUNTIFS(Oportunidades!$E$2:$E$71,$A9,Oportunidades!$P$2:$P$71,D$6,Oportunidades!$H$2:$H$71,"Ganada",Oportunidades!$D$2:$D$71,"Sí",Oportunidades!$Z$2:$Z$71,$D$3) -> 0 | E9: =COUNTIFS(Oportunidades!$E$2:$E$71,$A9,Oportunidades!$P$2:$P$71,E$6,Oportunidades!$H$2:$H$71,"Ganada",Oportunidades!$D$2:$D$71,"Sí",Oportunidades!$Z$2:$Z$71,$D$3) -> 0 | F9: =COUNTIFS(Oportunidades!$E$2:$E$71,$A9,Oportunidades!$P$2:$P$71,F$6,Oportunidades!$H$2:$H$71,"Ganada",Oportunidades!$D$2:$D$71,"Sí",Oportunidades!$Z$2:$Z$71,$D$3) -> 0 | G9: =SUM(B9:F9) -> 0
A10: Veracruz | B10: =COUNTIFS(Oportunidades!$E$2:$E$71,$A10,Oportunidades!$P$2:$P$71,B$6,Oportunidades!$H$2:$H$71,"Ganada",Oportunidades!$D$2:$D$71,"Sí",Oportunidades!$Z$2:$Z$71,$D$3) -> 3 | C10: =COUNTIFS(Oportunidades!$E$2:$E$71,$A10,Oportunidades!$P$2:$P$71,C$6,Oportunidades!$H$2:$H$71,"Ganada",Oportunidades!$D$2:$D$71,"Sí",Oportunidades!$Z$2:$Z$71,$D$3) -> 0 | D10: =COUNTIFS(Oportunidades!$E$2:$E$71,$A10,Oportunidades!$P$2:$P$71,D$6,Oportunidades!$H$2:$H$71,"Ganada",Oportunidades!$D$2:$D$71,"Sí",Oportunidades!$Z$2:$Z$71,$D$3) -> 0 | E10: =COUNTIFS(Oportunidades!$E$2:$E$71,$A10,Oportunidades!$P$2:$P$71,E$6,Oportunidades!$H$2:$H$71,"Ganada",Oportunidades!$D$2:$D$71,"Sí",Oportunidades!$Z$2:$Z$71,$D$3) -> 1 | F10: =COUNTIFS(Oportunidades!$E$2:$E$71,$A10,Oportunidades!$P$2:$P$71,F$6,Oportunidades!$H$2:$H$71,"Ganada",Oportunidades!$D$2:$D$71,"Sí",Oportunidades!$Z$2:$Z$71,$D$3) -> 0 | G10: =SUM(B10:F10) -> 4
A11: Yucatán (Mérida/Umán) | B11: =COUNTIFS(Oportunidades!$E$2:$E$71,$A11,Oportunidades!$P$2:$P$71,B$6,Oportunidades!$H$2:$H$71,"Ganada",Oportunidades!$D$2:$D$71,"Sí",Oportunidades!$Z$2:$Z$71,$D$3) -> 1 | C11: =COUNTIFS(Oportunidades!$E$2:$E$71,$A11,Oportunidades!$P$2:$P$71,C$6,Oportunidades!$H$2:$H$71,"Ganada",Oportunidades!$D$2:$D$71,"Sí",Oportunidades!$Z$2:$Z$71,$D$3) -> 1 | D11: =COUNTIFS(Oportunidades!$E$2:$E$71,$A11,Oportunidades!$P$2:$P$71,D$6,Oportunidades!$H$2:$H$71,"Ganada",Oportunidades!$D$2:$D$71,"Sí",Oportunidades!$Z$2:$Z$71,$D$3) -> 1 | E11: =COUNTIFS(Oportunidades!$E$2:$E$71,$A11,Oportunidades!$P$2:$P$71,E$6,Oportunidades!$H$2:$H$71,"Ganada",Oportunidades!$D$2:$D$71,"Sí",Oportunidades!$Z$2:$Z$71,$D$3) -> 0 | F11: =COUNTIFS(Oportunidades!$E$2:$E$71,$A11,Oportunidades!$P$2:$P$71,F$6,Oportunidades!$H$2:$H$71,"Ganada",Oportunidades!$D$2:$D$71,"Sí",Oportunidades!$Z$2:$Z$71,$D$3) -> 0 | G11: =SUM(B11:F11) -> 3
A12: Nuevo León (Ciénega de Flores) | B12: =COUNTIFS(Oportunidades!$E$2:$E$71,$A12,Oportunidades!$P$2:$P$71,B$6,Oportunidades!$H$2:$H$71,"Ganada",Oportunidades!$D$2:$D$71,"Sí",Oportunidades!$Z$2:$Z$71,$D$3) -> 0 | C12: =COUNTIFS(Oportunidades!$E$2:$E$71,$A12,Oportunidades!$P$2:$P$71,C$6,Oportunidades!$H$2:$H$71,"Ganada",Oportunidades!$D$2:$D$71,"Sí",Oportunidades!$Z$2:$Z$71,$D$3) -> 0 | D12: =COUNTIFS(Oportunidades!$E$2:$E$71,$A12,Oportunidades!$P$2:$P$71,D$6,Oportunidades!$H$2:$H$71,"Ganada",Oportunidades!$D$2:$D$71,"Sí",Oportunidades!$Z$2:$Z$71,$D$3) -> 0 | E12: =COUNTIFS(Oportunidades!$E$2:$E$71,$A12,Oportunidades!$P$2:$P$71,E$6,Oportunidades!$H$2:$H$71,"Ganada",Oportunidades!$D$2:$D$71,"Sí",Oportunidades!$Z$2:$Z$71,$D$3) -> 0 | F12: =COUNTIFS(Oportunidades!$E$2:$E$71,$A12,Oportunidades!$P$2:$P$71,F$6,Oportunidades!$H$2:$H$71,"Ganada",Oportunidades!$D$2:$D$71,"Sí",Oportunidades!$Z$2:$Z$71,$D$3) -> 0 | G12: =SUM(B12:F12) -> 0
A13: Noroeste (Sonora/BC) | B13: =COUNTIFS(Oportunidades!$E$2:$E$71,$A13,Oportunidades!$P$2:$P$71,B$6,Oportunidades!$H$2:$H$71,"Ganada",Oportunidades!$D$2:$D$71,"Sí",Oportunidades!$Z$2:$Z$71,$D$3) -> 0 | C13: =COUNTIFS(Oportunidades!$E$2:$E$71,$A13,Oportunidades!$P$2:$P$71,C$6,Oportunidades!$H$2:$H$71,"Ganada",Oportunidades!$D$2:$D$71,"Sí",Oportunidades!$Z$2:$Z$71,$D$3) -> 0 | D13: =COUNTIFS(Oportunidades!$E$2:$E$71,$A13,Oportunidades!$P$2:$P$71,D$6,Oportunidades!$H$2:$H$71,"Ganada",Oportunidades!$D$2:$D$71,"Sí",Oportunidades!$Z$2:$Z$71,$D$3) -> 0 | E13: =COUNTIFS(Oportunidades!$E$2:$E$71,$A13,Oportunidades!$P$2:$P$71,E$6,Oportunidades!$H$2:$H$71,"Ganada",Oportunidades!$D$2:$D$71,"Sí",Oportunidades!$Z$2:$Z$71,$D$3) -> 0 | F13: =COUNTIFS(Oportunidades!$E$2:$E$71,$A13,Oportunidades!$P$2:$P$71,F$6,Oportunidades!$H$2:$H$71,"Ganada",Oportunidades!$D$2:$D$71,"Sí",Oportunidades!$Z$2:$Z$71,$D$3) -> 0 | G13: =SUM(B13:F13) -> 0
A14: Durango (Gómez Palacio) | B14: =COUNTIFS(Oportunidades!$E$2:$E$71,$A14,Oportunidades!$P$2:$P$71,B$6,Oportunidades!$H$2:$H$71,"Ganada",Oportunidades!$D$2:$D$71,"Sí",Oportunidades!$Z$2:$Z$71,$D$3) -> 0 | C14: =COUNTIFS(Oportunidades!$E$2:$E$71,$A14,Oportunidades!$P$2:$P$71,C$6,Oportunidades!$H$2:$H$71,"Ganada",Oportunidades!$D$2:$D$71,"Sí",Oportunidades!$Z$2:$Z$71,$D$3) -> 0 | D14: =COUNTIFS(Oportunidades!$E$2:$E$71,$A14,Oportunidades!$P$2:$P$71,D$6,Oportunidades!$H$2:$H$71,"Ganada",Oportunidades!$D$2:$D$71,"Sí",Oportunidades!$Z$2:$Z$71,$D$3) -> 0 | E14: =COUNTIFS(Oportunidades!$E$2:$E$71,$A14,Oportunidades!$P$2:$P$71,E$6,Oportunidades!$H$2:$H$71,"Ganada",Oportunidades!$D$2:$D$71,"Sí",Oportunidades!$Z$2:$Z$71,$D$3) -> 0 | F14: =COUNTIFS(Oportunidades!$E$2:$E$71,$A14,Oportunidades!$P$2:$P$71,F$6,Oportunidades!$H$2:$H$71,"Ganada",Oportunidades!$D$2:$D$71,"Sí",Oportunidades!$Z$2:$Z$71,$D$3) -> 0 | G14: =SUM(B14:F14) -> 0
A15: San Luis Potosí | B15: =COUNTIFS(Oportunidades!$E$2:$E$71,$A15,Oportunidades!$P$2:$P$71,B$6,Oportunidades!$H$2:$H$71,"Ganada",Oportunidades!$D$2:$D$71,"Sí",Oportunidades!$Z$2:$Z$71,$D$3) -> 0 | C15: =COUNTIFS(Oportunidades!$E$2:$E$71,$A15,Oportunidades!$P$2:$P$71,C$6,Oportunidades!$H$2:$H$71,"Ganada",Oportunidades!$D$2:$D$71,"Sí",Oportunidades!$Z$2:$Z$71,$D$3) -> 0 | D15: =COUNTIFS(Oportunidades!$E$2:$E$71,$A15,Oportunidades!$P$2:$P$71,D$6,Oportunidades!$H$2:$H$71,"Ganada",Oportunidades!$D$2:$D$71,"Sí",Oportunidades!$Z$2:$Z$71,$D$3) -> 0 | E15: =COUNTIFS(Oportunidades!$E$2:$E$71,$A15,Oportunidades!$P$2:$P$71,E$6,Oportunidades!$H$2:$H$71,"Ganada",Oportunidades!$D$2:$D$71,"Sí",Oportunidades!$Z$2:$Z$71,$D$3) -> 0 | F15: =COUNTIFS(Oportunidades!$E$2:$E$71,$A15,Oportunidades!$P$2:$P$71,F$6,Oportunidades!$H$2:$H$71,"Ganada",Oportunidades!$D$2:$D$71,"Sí",Oportunidades!$Z$2:$Z$71,$D$3) -> 0 | G15: =SUM(B15:F15) -> 0
A16: Morelos (Cuautla) | B16: =COUNTIFS(Oportunidades!$E$2:$E$71,$A16,Oportunidades!$P$2:$P$71,B$6,Oportunidades!$H$2:$H$71,"Ganada",Oportunidades!$D$2:$D$71,"Sí",Oportunidades!$Z$2:$Z$71,$D$3) -> 0 | C16: =COUNTIFS(Oportunidades!$E$2:$E$71,$A16,Oportunidades!$P$2:$P$71,C$6,Oportunidades!$H$2:$H$71,"Ganada",Oportunidades!$D$2:$D$71,"Sí",Oportunidades!$Z$2:$Z$71,$D$3) -> 0 | D16: =COUNTIFS(Oportunidades!$E$2:$E$71,$A16,Oportunidades!$P$2:$P$71,D$6,Oportunidades!$H$2:$H$71,"Ganada",Oportunidades!$D$2:$D$71,"Sí",Oportunidades!$Z$2:$Z$71,$D$3) -> 0 | E16: =COUNTIFS(Oportunidades!$E$2:$E$71,$A16,Oportunidades!$P$2:$P$71,E$6,Oportunidades!$H$2:$H$71,"Ganada",Oportunidades!$D$2:$D$71,"Sí",Oportunidades!$Z$2:$Z$71,$D$3) -> 0 | F16: =COUNTIFS(Oportunidades!$E$2:$E$71,$A16,Oportunidades!$P$2:$P$71,F$6,Oportunidades!$H$2:$H$71,"Ganada",Oportunidades!$D$2:$D$71,"Sí",Oportunidades!$Z$2:$Z$71,$D$3) -> 0 | G16: =SUM(B16:F16) -> 0
A17: Total | B17: =SUM(B7:B16) -> 23 | C17: =SUM(C7:C16) -> 1 | D17: =SUM(D7:D16) -> 5 | E17: =SUM(E7:E16) -> 1 | F17: =SUM(F7:F16) -> 1 | G17: =SUM(G7:G16) -> 31
A20: PERDIDAS
A21: Zona | B21: Bandas en V | C21: Bandas síncronas, poliuretano y micro-V | D21: Manguera industrial | E21: Manguera hidráulica y neumática | F21: Otras o sin detalle de producto | G21: Total
A22: Bajío (Celaya) | B22: =COUNTIFS(Oportunidades!$E$2:$E$71,$A22,Oportunidades!$P$2:$P$71,B$21,Oportunidades!$H$2:$H$71,"Perdida",Oportunidades!$D$2:$D$71,"Sí",Oportunidades!$Z$2:$Z$71,$D$3) -> 0 | C22: =COUNTIFS(Oportunidades!$E$2:$E$71,$A22,Oportunidades!$P$2:$P$71,C$21,Oportunidades!$H$2:$H$71,"Perdida",Oportunidades!$D$2:$D$71,"Sí",Oportunidades!$Z$2:$Z$71,$D$3) -> 2 | D22: =COUNTIFS(Oportunidades!$E$2:$E$71,$A22,Oportunidades!$P$2:$P$71,D$21,Oportunidades!$H$2:$H$71,"Perdida",Oportunidades!$D$2:$D$71,"Sí",Oportunidades!$Z$2:$Z$71,$D$3) -> 0 | E22: =COUNTIFS(Oportunidades!$E$2:$E$71,$A22,Oportunidades!$P$2:$P$71,E$21,Oportunidades!$H$2:$H$71,"Perdida",Oportunidades!$D$2:$D$71,"Sí",Oportunidades!$Z$2:$Z$71,$D$3) -> 0 | F22: =COUNTIFS(Oportunidades!$E$2:$E$71,$A22,Oportunidades!$P$2:$P$71,F$21,Oportunidades!$H$2:$H$71,"Perdida",Oportunidades!$D$2:$D$71,"Sí",Oportunidades!$Z$2:$Z$71,$D$3) -> 1 | G22: =SUM(B22:F22) -> 3
A23: Puebla (Tecamachalco) | B23: =COUNTIFS(Oportunidades!$E$2:$E$71,$A23,Oportunidades!$P$2:$P$71,B$21,Oportunidades!$H$2:$H$71,"Perdida",Oportunidades!$D$2:$D$71,"Sí",Oportunidades!$Z$2:$Z$71,$D$3) -> 1 | C23: =COUNTIFS(Oportunidades!$E$2:$E$71,$A23,Oportunidades!$P$2:$P$71,C$21,Oportunidades!$H$2:$H$71,"Perdida",Oportunidades!$D$2:$D$71,"Sí",Oportunidades!$Z$2:$Z$71,$D$3) -> 0 | D23: =COUNTIFS(Oportunidades!$E$2:$E$71,$A23,Oportunidades!$P$2:$P$71,D$21,Oportunidades!$H$2:$H$71,"Perdida",Oportunidades!$D$2:$D$71,"Sí",Oportunidades!$Z$2:$Z$71,$D$3) -> 1 | E23: =COUNTIFS(Oportunidades!$E$2:$E$71,$A23,Oportunidades!$P$2:$P$71,E$21,Oportunidades!$H$2:$H$71,"Perdida",Oportunidades!$D$2:$D$71,"Sí",Oportunidades!$Z$2:$Z$71,$D$3) -> 1 | F23: =COUNTIFS(Oportunidades!$E$2:$E$71,$A23,Oportunidades!$P$2:$P$71,F$21,Oportunidades!$H$2:$H$71,"Perdida",Oportunidades!$D$2:$D$71,"Sí",Oportunidades!$Z$2:$Z$71,$D$3) -> 0 | G23: =SUM(B23:F23) -> 3
A24: Sinaloa (Culiacán) | B24: =COUNTIFS(Oportunidades!$E$2:$E$71,$A24,Oportunidades!$P$2:$P$71,B$21,Oportunidades!$H$2:$H$71,"Perdida",Oportunidades!$D$2:$D$71,"Sí",Oportunidades!$Z$2:$Z$71,$D$3) -> 0 | C24: =COUNTIFS(Oportunidades!$E$2:$E$71,$A24,Oportunidades!$P$2:$P$71,C$21,Oportunidades!$H$2:$H$71,"Perdida",Oportunidades!$D$2:$D$71,"Sí",Oportunidades!$Z$2:$Z$71,$D$3) -> 0 | D24: =COUNTIFS(Oportunidades!$E$2:$E$71,$A24,Oportunidades!$P$2:$P$71,D$21,Oportunidades!$H$2:$H$71,"Perdida",Oportunidades!$D$2:$D$71,"Sí",Oportunidades!$Z$2:$Z$71,$D$3) -> 0 | E24: =COUNTIFS(Oportunidades!$E$2:$E$71,$A24,Oportunidades!$P$2:$P$71,E$21,Oportunidades!$H$2:$H$71,"Perdida",Oportunidades!$D$2:$D$71,"Sí",Oportunidades!$Z$2:$Z$71,$D$3) -> 0 | F24: =COUNTIFS(Oportunidades!$E$2:$E$71,$A24,Oportunidades!$P$2:$P$71,F$21,Oportunidades!$H$2:$H$71,"Perdida",Oportunidades!$D$2:$D$71,"Sí",Oportunidades!$Z$2:$Z$71,$D$3) -> 0 | G24: =SUM(B24:F24) -> 0
A25: Veracruz | B25: =COUNTIFS(Oportunidades!$E$2:$E$71,$A25,Oportunidades!$P$2:$P$71,B$21,Oportunidades!$H$2:$H$71,"Perdida",Oportunidades!$D$2:$D$71,"Sí",Oportunidades!$Z$2:$Z$71,$D$3) -> 0 | C25: =COUNTIFS(Oportunidades!$E$2:$E$71,$A25,Oportunidades!$P$2:$P$71,C$21,Oportunidades!$H$2:$H$71,"Perdida",Oportunidades!$D$2:$D$71,"Sí",Oportunidades!$Z$2:$Z$71,$D$3) -> 0 | D25: =COUNTIFS(Oportunidades!$E$2:$E$71,$A25,Oportunidades!$P$2:$P$71,D$21,Oportunidades!$H$2:$H$71,"Perdida",Oportunidades!$D$2:$D$71,"Sí",Oportunidades!$Z$2:$Z$71,$D$3) -> 0 | E25: =COUNTIFS(Oportunidades!$E$2:$E$71,$A25,Oportunidades!$P$2:$P$71,E$21,Oportunidades!$H$2:$H$71,"Perdida",Oportunidades!$D$2:$D$71,"Sí",Oportunidades!$Z$2:$Z$71,$D$3) -> 1 | F25: =COUNTIFS(Oportunidades!$E$2:$E$71,$A25,Oportunidades!$P$2:$P$71,F$21,Oportunidades!$H$2:$H$71,"Perdida",Oportunidades!$D$2:$D$71,"Sí",Oportunidades!$Z$2:$Z$71,$D$3) -> 0 | G25: =SUM(B25:F25) -> 1
A26: Yucatán (Mérida/Umán) | B26: =COUNTIFS(Oportunidades!$E$2:$E$71,$A26,Oportunidades!$P$2:$P$71,B$21,Oportunidades!$H$2:$H$71,"Perdida",Oportunidades!$D$2:$D$71,"Sí",Oportunidades!$Z$2:$Z$71,$D$3) -> 0 | C26: =COUNTIFS(Oportunidades!$E$2:$E$71,$A26,Oportunidades!$P$2:$P$71,C$21,Oportunidades!$H$2:$H$71,"Perdida",Oportunidades!$D$2:$D$71,"Sí",Oportunidades!$Z$2:$Z$71,$D$3) -> 0 | D26: =COUNTIFS(Oportunidades!$E$2:$E$71,$A26,Oportunidades!$P$2:$P$71,D$21,Oportunidades!$H$2:$H$71,"Perdida",Oportunidades!$D$2:$D$71,"Sí",Oportunidades!$Z$2:$Z$71,$D$3) -> 0 | E26: =COUNTIFS(Oportunidades!$E$2:$E$71,$A26,Oportunidades!$P$2:$P$71,E$21,Oportunidades!$H$2:$H$71,"Perdida",Oportunidades!$D$2:$D$71,"Sí",Oportunidades!$Z$2:$Z$71,$D$3) -> 0 | F26: =COUNTIFS(Oportunidades!$E$2:$E$71,$A26,Oportunidades!$P$2:$P$71,F$21,Oportunidades!$H$2:$H$71,"Perdida",Oportunidades!$D$2:$D$71,"Sí",Oportunidades!$Z$2:$Z$71,$D$3) -> 0 | G26: =SUM(B26:F26) -> 0
A27: Nuevo León (Ciénega de Flores) | B27: =COUNTIFS(Oportunidades!$E$2:$E$71,$A27,Oportunidades!$P$2:$P$71,B$21,Oportunidades!$H$2:$H$71,"Perdida",Oportunidades!$D$2:$D$71,"Sí",Oportunidades!$Z$2:$Z$71,$D$3) -> 0 | C27: =COUNTIFS(Oportunidades!$E$2:$E$71,$A27,Oportunidades!$P$2:$P$71,C$21,Oportunidades!$H$2:$H$71,"Perdida",Oportunidades!$D$2:$D$71,"Sí",Oportunidades!$Z$2:$Z$71,$D$3) -> 0 | D27: =COUNTIFS(Oportunidades!$E$2:$E$71,$A27,Oportunidades!$P$2:$P$71,D$21,Oportunidades!$H$2:$H$71,"Perdida",Oportunidades!$D$2:$D$71,"Sí",Oportunidades!$Z$2:$Z$71,$D$3) -> 0 | E27: =COUNTIFS(Oportunidades!$E$2:$E$71,$A27,Oportunidades!$P$2:$P$71,E$21,Oportunidades!$H$2:$H$71,"Perdida",Oportunidades!$D$2:$D$71,"Sí",Oportunidades!$Z$2:$Z$71,$D$3) -> 0 | F27: =COUNTIFS(Oportunidades!$E$2:$E$71,$A27,Oportunidades!$P$2:$P$71,F$21,Oportunidades!$H$2:$H$71,"Perdida",Oportunidades!$D$2:$D$71,"Sí",Oportunidades!$Z$2:$Z$71,$D$3) -> 0 | G27: =SUM(B27:F27) -> 0
A28: Noroeste (Sonora/BC) | B28: =COUNTIFS(Oportunidades!$E$2:$E$71,$A28,Oportunidades!$P$2:$P$71,B$21,Oportunidades!$H$2:$H$71,"Perdida",Oportunidades!$D$2:$D$71,"Sí",Oportunidades!$Z$2:$Z$71,$D$3) -> 1 | C28: =COUNTIFS(Oportunidades!$E$2:$E$71,$A28,Oportunidades!$P$2:$P$71,C$21,Oportunidades!$H$2:$H$71,"Perdida",Oportunidades!$D$2:$D$71,"Sí",Oportunidades!$Z$2:$Z$71,$D$3) -> 3 | D28: =COUNTIFS(Oportunidades!$E$2:$E$71,$A28,Oportunidades!$P$2:$P$71,D$21,Oportunidades!$H$2:$H$71,"Perdida",Oportunidades!$D$2:$D$71,"Sí",Oportunidades!$Z$2:$Z$71,$D$3) -> 0 | E28: =COUNTIFS(Oportunidades!$E$2:$E$71,$A28,Oportunidades!$P$2:$P$71,E$21,Oportunidades!$H$2:$H$71,"Perdida",Oportunidades!$D$2:$D$71,"Sí",Oportunidades!$Z$2:$Z$71,$D$3) -> 2 | F28: =COUNTIFS(Oportunidades!$E$2:$E$71,$A28,Oportunidades!$P$2:$P$71,F$21,Oportunidades!$H$2:$H$71,"Perdida",Oportunidades!$D$2:$D$71,"Sí",Oportunidades!$Z$2:$Z$71,$D$3) -> 0 | G28: =SUM(B28:F28) -> 6
A29: Durango (Gómez Palacio) | B29: =COUNTIFS(Oportunidades!$E$2:$E$71,$A29,Oportunidades!$P$2:$P$71,B$21,Oportunidades!$H$2:$H$71,"Perdida",Oportunidades!$D$2:$D$71,"Sí",Oportunidades!$Z$2:$Z$71,$D$3) -> 0 | C29: =COUNTIFS(Oportunidades!$E$2:$E$71,$A29,Oportunidades!$P$2:$P$71,C$21,Oportunidades!$H$2:$H$71,"Perdida",Oportunidades!$D$2:$D$71,"Sí",Oportunidades!$Z$2:$Z$71,$D$3) -> 1 | D29: =COUNTIFS(Oportunidades!$E$2:$E$71,$A29,Oportunidades!$P$2:$P$71,D$21,Oportunidades!$H$2:$H$71,"Perdida",Oportunidades!$D$2:$D$71,"Sí",Oportunidades!$Z$2:$Z$71,$D$3) -> 0 | E29: =COUNTIFS(Oportunidades!$E$2:$E$71,$A29,Oportunidades!$P$2:$P$71,E$21,Oportunidades!$H$2:$H$71,"Perdida",Oportunidades!$D$2:$D$71,"Sí",Oportunidades!$Z$2:$Z$71,$D$3) -> 0 | F29: =COUNTIFS(Oportunidades!$E$2:$E$71,$A29,Oportunidades!$P$2:$P$71,F$21,Oportunidades!$H$2:$H$71,"Perdida",Oportunidades!$D$2:$D$71,"Sí",Oportunidades!$Z$2:$Z$71,$D$3) -> 0 | G29: =SUM(B29:F29) -> 1
A30: San Luis Potosí | B30: =COUNTIFS(Oportunidades!$E$2:$E$71,$A30,Oportunidades!$P$2:$P$71,B$21,Oportunidades!$H$2:$H$71,"Perdida",Oportunidades!$D$2:$D$71,"Sí",Oportunidades!$Z$2:$Z$71,$D$3) -> 0 | C30: =COUNTIFS(Oportunidades!$E$2:$E$71,$A30,Oportunidades!$P$2:$P$71,C$21,Oportunidades!$H$2:$H$71,"Perdida",Oportunidades!$D$2:$D$71,"Sí",Oportunidades!$Z$2:$Z$71,$D$3) -> 0 | D30: =COUNTIFS(Oportunidades!$E$2:$E$71,$A30,Oportunidades!$P$2:$P$71,D$21,Oportunidades!$H$2:$H$71,"Perdida",Oportunidades!$D$2:$D$71,"Sí",Oportunidades!$Z$2:$Z$71,$D$3) -> 0 | E30: =COUNTIFS(Oportunidades!$E$2:$E$71,$A30,Oportunidades!$P$2:$P$71,E$21,Oportunidades!$H$2:$H$71,"Perdida",Oportunidades!$D$2:$D$71,"Sí",Oportunidades!$Z$2:$Z$71,$D$3) -> 0 | F30: =COUNTIFS(Oportunidades!$E$2:$E$71,$A30,Oportunidades!$P$2:$P$71,F$21,Oportunidades!$H$2:$H$71,"Perdida",Oportunidades!$D$2:$D$71,"Sí",Oportunidades!$Z$2:$Z$71,$D$3) -> 0 | G30: =SUM(B30:F30) -> 0
A31: Morelos (Cuautla) | B31: =COUNTIFS(Oportunidades!$E$2:$E$71,$A31,Oportunidades!$P$2:$P$71,B$21,Oportunidades!$H$2:$H$71,"Perdida",Oportunidades!$D$2:$D$71,"Sí",Oportunidades!$Z$2:$Z$71,$D$3) -> 0 | C31: =COUNTIFS(Oportunidades!$E$2:$E$71,$A31,Oportunidades!$P$2:$P$71,C$21,Oportunidades!$H$2:$H$71,"Perdida",Oportunidades!$D$2:$D$71,"Sí",Oportunidades!$Z$2:$Z$71,$D$3) -> 0 | D31: =COUNTIFS(Oportunidades!$E$2:$E$71,$A31,Oportunidades!$P$2:$P$71,D$21,Oportunidades!$H$2:$H$71,"Perdida",Oportunidades!$D$2:$D$71,"Sí",Oportunidades!$Z$2:$Z$71,$D$3) -> 0 | E31: =COUNTIFS(Oportunidades!$E$2:$E$71,$A31,Oportunidades!$P$2:$P$71,E$21,Oportunidades!$H$2:$H$71,"Perdida",Oportunidades!$D$2:$D$71,"Sí",Oportunidades!$Z$2:$Z$71,$D$3) -> 0 | F31: =COUNTIFS(Oportunidades!$E$2:$E$71,$A31,Oportunidades!$P$2:$P$71,F$21,Oportunidades!$H$2:$H$71,"Perdida",Oportunidades!$D$2:$D$71,"Sí",Oportunidades!$Z$2:$Z$71,$D$3) -> 0 | G31: =SUM(B31:F31) -> 0
A32: Total | B32: =SUM(B22:B31) -> 2 | C32: =SUM(C22:C31) -> 6 | D32: =SUM(D22:D31) -> 1 | E32: =SUM(E22:E31) -> 4 | F32: =SUM(F22:F31) -> 1 | G32: =SUM(G22:G31) -> 14
A35: ABIERTAS
A36: Zona | B36: Bandas en V | C36: Bandas síncronas, poliuretano y micro-V | D36: Manguera industrial | E36: Manguera hidráulica y neumática | F36: Otras o sin detalle de producto | G36: Total
A37: Bajío (Celaya) | B37: =COUNTIFS(Oportunidades!$E$2:$E$71,$A37,Oportunidades!$P$2:$P$71,B$36,Oportunidades!$H$2:$H$71,"Abierta",Oportunidades!$D$2:$D$71,"Sí",Oportunidades!$Z$2:$Z$71,$D$3) -> 0 | C37: =COUNTIFS(Oportunidades!$E$2:$E$71,$A37,Oportunidades!$P$2:$P$71,C$36,Oportunidades!$H$2:$H$71,"Abierta",Oportunidades!$D$2:$D$71,"Sí",Oportunidades!$Z$2:$Z$71,$D$3) -> 0 | D37: =COUNTIFS(Oportunidades!$E$2:$E$71,$A37,Oportunidades!$P$2:$P$71,D$36,Oportunidades!$H$2:$H$71,"Abierta",Oportunidades!$D$2:$D$71,"Sí",Oportunidades!$Z$2:$Z$71,$D$3) -> 0 | E37: =COUNTIFS(Oportunidades!$E$2:$E$71,$A37,Oportunidades!$P$2:$P$71,E$36,Oportunidades!$H$2:$H$71,"Abierta",Oportunidades!$D$2:$D$71,"Sí",Oportunidades!$Z$2:$Z$71,$D$3) -> 0 | F37: =COUNTIFS(Oportunidades!$E$2:$E$71,$A37,Oportunidades!$P$2:$P$71,F$36,Oportunidades!$H$2:$H$71,"Abierta",Oportunidades!$D$2:$D$71,"Sí",Oportunidades!$Z$2:$Z$71,$D$3) -> 0 | G37: =SUM(B37:F37) -> 0
A38: Puebla (Tecamachalco) | B38: =COUNTIFS(Oportunidades!$E$2:$E$71,$A38,Oportunidades!$P$2:$P$71,B$36,Oportunidades!$H$2:$H$71,"Abierta",Oportunidades!$D$2:$D$71,"Sí",Oportunidades!$Z$2:$Z$71,$D$3) -> 0 | C38: =COUNTIFS(Oportunidades!$E$2:$E$71,$A38,Oportunidades!$P$2:$P$71,C$36,Oportunidades!$H$2:$H$71,"Abierta",Oportunidades!$D$2:$D$71,"Sí",Oportunidades!$Z$2:$Z$71,$D$3) -> 0 | D38: =COUNTIFS(Oportunidades!$E$2:$E$71,$A38,Oportunidades!$P$2:$P$71,D$36,Oportunidades!$H$2:$H$71,"Abierta",Oportunidades!$D$2:$D$71,"Sí",Oportunidades!$Z$2:$Z$71,$D$3) -> 0 | E38: =COUNTIFS(Oportunidades!$E$2:$E$71,$A38,Oportunidades!$P$2:$P$71,E$36,Oportunidades!$H$2:$H$71,"Abierta",Oportunidades!$D$2:$D$71,"Sí",Oportunidades!$Z$2:$Z$71,$D$3) -> 0 | F38: =COUNTIFS(Oportunidades!$E$2:$E$71,$A38,Oportunidades!$P$2:$P$71,F$36,Oportunidades!$H$2:$H$71,"Abierta",Oportunidades!$D$2:$D$71,"Sí",Oportunidades!$Z$2:$Z$71,$D$3) -> 0 | G38: =SUM(B38:F38) -> 0
A39: Sinaloa (Culiacán) | B39: =COUNTIFS(Oportunidades!$E$2:$E$71,$A39,Oportunidades!$P$2:$P$71,B$36,Oportunidades!$H$2:$H$71,"Abierta",Oportunidades!$D$2:$D$71,"Sí",Oportunidades!$Z$2:$Z$71,$D$3) -> 0 | C39: =COUNTIFS(Oportunidades!$E$2:$E$71,$A39,Oportunidades!$P$2:$P$71,C$36,Oportunidades!$H$2:$H$71,"Abierta",Oportunidades!$D$2:$D$71,"Sí",Oportunidades!$Z$2:$Z$71,$D$3) -> 0 | D39: =COUNTIFS(Oportunidades!$E$2:$E$71,$A39,Oportunidades!$P$2:$P$71,D$36,Oportunidades!$H$2:$H$71,"Abierta",Oportunidades!$D$2:$D$71,"Sí",Oportunidades!$Z$2:$Z$71,$D$3) -> 0 | E39: =COUNTIFS(Oportunidades!$E$2:$E$71,$A39,Oportunidades!$P$2:$P$71,E$36,Oportunidades!$H$2:$H$71,"Abierta",Oportunidades!$D$2:$D$71,"Sí",Oportunidades!$Z$2:$Z$71,$D$3) -> 0 | F39: =COUNTIFS(Oportunidades!$E$2:$E$71,$A39,Oportunidades!$P$2:$P$71,F$36,Oportunidades!$H$2:$H$71,"Abierta",Oportunidades!$D$2:$D$71,"Sí",Oportunidades!$Z$2:$Z$71,$D$3) -> 0 | G39: =SUM(B39:F39) -> 0
A40: Veracruz | B40: =COUNTIFS(Oportunidades!$E$2:$E$71,$A40,Oportunidades!$P$2:$P$71,B$36,Oportunidades!$H$2:$H$71,"Abierta",Oportunidades!$D$2:$D$71,"Sí",Oportunidades!$Z$2:$Z$71,$D$3) -> 0 | C40: =COUNTIFS(Oportunidades!$E$2:$E$71,$A40,Oportunidades!$P$2:$P$71,C$36,Oportunidades!$H$2:$H$71,"Abierta",Oportunidades!$D$2:$D$71,"Sí",Oportunidades!$Z$2:$Z$71,$D$3) -> 0 | D40: =COUNTIFS(Oportunidades!$E$2:$E$71,$A40,Oportunidades!$P$2:$P$71,D$36,Oportunidades!$H$2:$H$71,"Abierta",Oportunidades!$D$2:$D$71,"Sí",Oportunidades!$Z$2:$Z$71,$D$3) -> 0 | E40: =COUNTIFS(Oportunidades!$E$2:$E$71,$A40,Oportunidades!$P$2:$P$71,E$36,Oportunidades!$H$2:$H$71,"Abierta",Oportunidades!$D$2:$D$71,"Sí",Oportunidades!$Z$2:$Z$71,$D$3) -> 0 | F40: =COUNTIFS(Oportunidades!$E$2:$E$71,$A40,Oportunidades!$P$2:$P$71,F$36,Oportunidades!$H$2:$H$71,"Abierta",Oportunidades!$D$2:$D$71,"Sí",Oportunidades!$Z$2:$Z$71,$D$3) -> 0 | G40: =SUM(B40:F40) -> 0
A41: Yucatán (Mérida/Umán) | B41: =COUNTIFS(Oportunidades!$E$2:$E$71,$A41,Oportunidades!$P$2:$P$71,B$36,Oportunidades!$H$2:$H$71,"Abierta",Oportunidades!$D$2:$D$71,"Sí",Oportunidades!$Z$2:$Z$71,$D$3) -> 1 | C41: =COUNTIFS(Oportunidades!$E$2:$E$71,$A41,Oportunidades!$P$2:$P$71,C$36,Oportunidades!$H$2:$H$71,"Abierta",Oportunidades!$D$2:$D$71,"Sí",Oportunidades!$Z$2:$Z$71,$D$3) -> 0 | D41: =COUNTIFS(Oportunidades!$E$2:$E$71,$A41,Oportunidades!$P$2:$P$71,D$36,Oportunidades!$H$2:$H$71,"Abierta",Oportunidades!$D$2:$D$71,"Sí",Oportunidades!$Z$2:$Z$71,$D$3) -> 0 | E41: =COUNTIFS(Oportunidades!$E$2:$E$71,$A41,Oportunidades!$P$2:$P$71,E$36,Oportunidades!$H$2:$H$71,"Abierta",Oportunidades!$D$2:$D$71,"Sí",Oportunidades!$Z$2:$Z$71,$D$3) -> 0 | F41: =COUNTIFS(Oportunidades!$E$2:$E$71,$A41,Oportunidades!$P$2:$P$71,F$36,Oportunidades!$H$2:$H$71,"Abierta",Oportunidades!$D$2:$D$71,"Sí",Oportunidades!$Z$2:$Z$71,$D$3) -> 0 | G41: =SUM(B41:F41) -> 1
A42: Nuevo León (Ciénega de Flores) | B42: =COUNTIFS(Oportunidades!$E$2:$E$71,$A42,Oportunidades!$P$2:$P$71,B$36,Oportunidades!$H$2:$H$71,"Abierta",Oportunidades!$D$2:$D$71,"Sí",Oportunidades!$Z$2:$Z$71,$D$3) -> 0 | C42: =COUNTIFS(Oportunidades!$E$2:$E$71,$A42,Oportunidades!$P$2:$P$71,C$36,Oportunidades!$H$2:$H$71,"Abierta",Oportunidades!$D$2:$D$71,"Sí",Oportunidades!$Z$2:$Z$71,$D$3) -> 0 | D42: =COUNTIFS(Oportunidades!$E$2:$E$71,$A42,Oportunidades!$P$2:$P$71,D$36,Oportunidades!$H$2:$H$71,"Abierta",Oportunidades!$D$2:$D$71,"Sí",Oportunidades!$Z$2:$Z$71,$D$3) -> 0 | E42: =COUNTIFS(Oportunidades!$E$2:$E$71,$A42,Oportunidades!$P$2:$P$71,E$36,Oportunidades!$H$2:$H$71,"Abierta",Oportunidades!$D$2:$D$71,"Sí",Oportunidades!$Z$2:$Z$71,$D$3) -> 0 | F42: =COUNTIFS(Oportunidades!$E$2:$E$71,$A42,Oportunidades!$P$2:$P$71,F$36,Oportunidades!$H$2:$H$71,"Abierta",Oportunidades!$D$2:$D$71,"Sí",Oportunidades!$Z$2:$Z$71,$D$3) -> 0 | G42: =SUM(B42:F42) -> 0
A43: Noroeste (Sonora/BC) | B43: =COUNTIFS(Oportunidades!$E$2:$E$71,$A43,Oportunidades!$P$2:$P$71,B$36,Oportunidades!$H$2:$H$71,"Abierta",Oportunidades!$D$2:$D$71,"Sí",Oportunidades!$Z$2:$Z$71,$D$3) -> 0 | C43: =COUNTIFS(Oportunidades!$E$2:$E$71,$A43,Oportunidades!$P$2:$P$71,C$36,Oportunidades!$H$2:$H$71,"Abierta",Oportunidades!$D$2:$D$71,"Sí",Oportunidades!$Z$2:$Z$71,$D$3) -> 0 | D43: =COUNTIFS(Oportunidades!$E$2:$E$71,$A43,Oportunidades!$P$2:$P$71,D$36,Oportunidades!$H$2:$H$71,"Abierta",Oportunidades!$D$2:$D$71,"Sí",Oportunidades!$Z$2:$Z$71,$D$3) -> 0 | E43: =COUNTIFS(Oportunidades!$E$2:$E$71,$A43,Oportunidades!$P$2:$P$71,E$36,Oportunidades!$H$2:$H$71,"Abierta",Oportunidades!$D$2:$D$71,"Sí",Oportunidades!$Z$2:$Z$71,$D$3) -> 0 | F43: =COUNTIFS(Oportunidades!$E$2:$E$71,$A43,Oportunidades!$P$2:$P$71,F$36,Oportunidades!$H$2:$H$71,"Abierta",Oportunidades!$D$2:$D$71,"Sí",Oportunidades!$Z$2:$Z$71,$D$3) -> 0 | G43: =SUM(B43:F43) -> 0
A44: Durango (Gómez Palacio) | B44: =COUNTIFS(Oportunidades!$E$2:$E$71,$A44,Oportunidades!$P$2:$P$71,B$36,Oportunidades!$H$2:$H$71,"Abierta",Oportunidades!$D$2:$D$71,"Sí",Oportunidades!$Z$2:$Z$71,$D$3) -> 0 | C44: =COUNTIFS(Oportunidades!$E$2:$E$71,$A44,Oportunidades!$P$2:$P$71,C$36,Oportunidades!$H$2:$H$71,"Abierta",Oportunidades!$D$2:$D$71,"Sí",Oportunidades!$Z$2:$Z$71,$D$3) -> 0 | D44: =COUNTIFS(Oportunidades!$E$2:$E$71,$A44,Oportunidades!$P$2:$P$71,D$36,Oportunidades!$H$2:$H$71,"Abierta",Oportunidades!$D$2:$D$71,"Sí",Oportunidades!$Z$2:$Z$71,$D$3) -> 0 | E44: =COUNTIFS(Oportunidades!$E$2:$E$71,$A44,Oportunidades!$P$2:$P$71,E$36,Oportunidades!$H$2:$H$71,"Abierta",Oportunidades!$D$2:$D$71,"Sí",Oportunidades!$Z$2:$Z$71,$D$3) -> 0 | F44: =COUNTIFS(Oportunidades!$E$2:$E$71,$A44,Oportunidades!$P$2:$P$71,F$36,Oportunidades!$H$2:$H$71,"Abierta",Oportunidades!$D$2:$D$71,"Sí",Oportunidades!$Z$2:$Z$71,$D$3) -> 0 | G44: =SUM(B44:F44) -> 0
A45: San Luis Potosí | B45: =COUNTIFS(Oportunidades!$E$2:$E$71,$A45,Oportunidades!$P$2:$P$71,B$36,Oportunidades!$H$2:$H$71,"Abierta",Oportunidades!$D$2:$D$71,"Sí",Oportunidades!$Z$2:$Z$71,$D$3) -> 0 | C45: =COUNTIFS(Oportunidades!$E$2:$E$71,$A45,Oportunidades!$P$2:$P$71,C$36,Oportunidades!$H$2:$H$71,"Abierta",Oportunidades!$D$2:$D$71,"Sí",Oportunidades!$Z$2:$Z$71,$D$3) -> 0 | D45: =COUNTIFS(Oportunidades!$E$2:$E$71,$A45,Oportunidades!$P$2:$P$71,D$36,Oportunidades!$H$2:$H$71,"Abierta",Oportunidades!$D$2:$D$71,"Sí",Oportunidades!$Z$2:$Z$71,$D$3) -> 0 | E45: =COUNTIFS(Oportunidades!$E$2:$E$71,$A45,Oportunidades!$P$2:$P$71,E$36,Oportunidades!$H$2:$H$71,"Abierta",Oportunidades!$D$2:$D$71,"Sí",Oportunidades!$Z$2:$Z$71,$D$3) -> 0 | F45: =COUNTIFS(Oportunidades!$E$2:$E$71,$A45,Oportunidades!$P$2:$P$71,F$36,Oportunidades!$H$2:$H$71,"Abierta",Oportunidades!$D$2:$D$71,"Sí",Oportunidades!$Z$2:$Z$71,$D$3) -> 0 | G45: =SUM(B45:F45) -> 0
A46: Morelos (Cuautla) | B46: =COUNTIFS(Oportunidades!$E$2:$E$71,$A46,Oportunidades!$P$2:$P$71,B$36,Oportunidades!$H$2:$H$71,"Abierta",Oportunidades!$D$2:$D$71,"Sí",Oportunidades!$Z$2:$Z$71,$D$3) -> 0 | C46: =COUNTIFS(Oportunidades!$E$2:$E$71,$A46,Oportunidades!$P$2:$P$71,C$36,Oportunidades!$H$2:$H$71,"Abierta",Oportunidades!$D$2:$D$71,"Sí",Oportunidades!$Z$2:$Z$71,$D$3) -> 0 | D46: =COUNTIFS(Oportunidades!$E$2:$E$71,$A46,Oportunidades!$P$2:$P$71,D$36,Oportunidades!$H$2:$H$71,"Abierta",Oportunidades!$D$2:$D$71,"Sí",Oportunidades!$Z$2:$Z$71,$D$3) -> 0 | E46: =COUNTIFS(Oportunidades!$E$2:$E$71,$A46,Oportunidades!$P$2:$P$71,E$36,Oportunidades!$H$2:$H$71,"Abierta",Oportunidades!$D$2:$D$71,"Sí",Oportunidades!$Z$2:$Z$71,$D$3) -> 0 | F46: =COUNTIFS(Oportunidades!$E$2:$E$71,$A46,Oportunidades!$P$2:$P$71,F$36,Oportunidades!$H$2:$H$71,"Abierta",Oportunidades!$D$2:$D$71,"Sí",Oportunidades!$Z$2:$Z$71,$D$3) -> 0 | G46: =SUM(B46:F46) -> 0
A47: Total | B47: =SUM(B37:B46) -> 1 | C47: =SUM(C37:C46) -> 0 | D47: =SUM(D37:D46) -> 0 | E47: =SUM(E37:E46) -> 0 | F47: =SUM(F37:F46) -> 0 | G47: =SUM(G37:G46) -> 1

Sheet Clasificación dudosa
A1: Oportunidades de cuentas Bachoco que el programa no marcó Elegible (se reportan, no se cambiaron)
A2: Regla del proyecto: solo las Elegibles sustentan casos; las Excluidas y en Revisar no entran en resultados, pero una clasificación dudosa se reporta. La columna "Lo que se reporta" es nuestra lectura de por qué parece dudosa; la decisión de corregir es de quien lleva la cuenta y del administrador del CRM.
A4: Núm. de oportunidad | B4: Nomenclatura completa | C4: Cuenta en el CRM | D4: Estatus | E4: Fecha de cierre | F4: Potencial anual MXN (registrado) | G4: Decisión del programa | H4: Motivo del programa | I4: Lo que se reporta
A5: O-00221100 | B5: 4.1 PTI-BACHOCO BAJIO-RYASA CELAYA | C5: BACHOCO S.A. DE C.V. | D5: Ganada | E5: 43585 | F5: 1855036 | G5: Revisar | H5: Nomenclatura no concluyente | I5: El programa no pudo concluir con el nombre (solo trae PTI o la familia). No se cambió.
A6: O-00228877 | B6: 4.2 Pti Bachoco-Ryasa Cly | C6: Bachoco S.A. de C.V - Guanajuato | D6: Ganada | E6: 43643 | F6: 463759.04 | G6: Revisar | H6: Nomenclatura no concluyente | I6: El programa no pudo concluir con el nombre (solo trae PTI o la familia). No se cambió.
A7: O-00232580 | B7: 4.2 Pti Bachoco-Ryasa Cly_O-00232580 | C7: Bachoco S.A. de C.V - Guanajuato | D7: Ganada | E7: 43701 | F7: 278255.46 | G7: Revisar | H7: Nomenclatura no concluyente | I7: El programa no pudo concluir con el nombre (solo trae PTI o la familia). No se cambió.
A8: O-00244318 | B8: 4.2 PTI BACHOCO-RYASA CLY | C8: BACHOCO S.A. DE C.V. | D8: Ganada | E8: 43945 | F8: 371007.16 | G8: Revisar | H8: Nomenclatura no concluyente | I8: El programa no pudo concluir con el nombre (solo trae PTI o la familia). No se cambió.
A9: 545700 | B9: 2.1 PTI-BACHOCO S.A. DE C.V. PT-V-BELTS- RYASA QRO--545700 | C9: BACHOCO S.A. DE C.V. | D9: Ganada | E9: 44527 | F9: 788217.01 | G9: Excluida | H9: ID de distribuidores / jobbers; Descripción con ID de distribuidor / jobber | I9: El nombre lleva ID 2.1 (conversión de distribuidores) aunque el cliente es el usuario final: posible ID mal capturado.
A10: 575363 | B10: 2.1 PTI-Bachoco, S.A. de C.V. - Planta procesadora de aves Guanajuato - Guanajuato PT-V-BELTS-575363 | C10: Bachoco, S.A. de C.V. - Planta procesadora de aves Guanajuato - Guanajuato | D10: Ganada | E10: 44833 | F10: 437898.36 | G10: Excluida | H10: ID de distribuidores / jobbers; Descripción con ID de distribuidor / jobber | I10: El nombre lleva ID 2.1 (conversión de distribuidores) aunque el cliente es el usuario final: posible ID mal capturado.
A11: 584242 | B11: 7.1 V-BELTS Bachoco S.A. de C.V. - Planta Culiacan PT-V-BELTS-584242 | C11: Bachoco S.A. de C.V. - Planta Culiacan | D11: Ganada | E11: 44855 | F11: 656847.54 | G11: Excluida | H11: OEM / primer equipo | I11: La cuenta está segmentada como OEM. HIPÓTESIS por confirmar: si la compra es para mantener equipos propios de la planta, sería usuario final (contexto/OBJETIVO_RICARDO.md: una manufacturera es usuario final cuando compra para mantenimiento de su propia operación). Decide quien lleva la cuenta.
A12: 653398 | B12: 3.1 MXT Bachoco S.A. de C.V. - Planta Culiacan FP-HYDRAULICS-653398 | C12: Bachoco S.A. de C.V. - Planta Culiacan | D12: Ganada | E12: 45099 | F12: 511104.27 | G12: Excluida | H12: OEM / primer equipo | I12: La cuenta está segmentada como OEM. HIPÓTESIS por confirmar: si la compra es para mantener equipos propios de la planta, sería usuario final (contexto/OBJETIVO_RICARDO.md: una manufacturera es usuario final cuando compra para mantenimiento de su propia operación). Decide quien lleva la cuenta.
A13: 650190 | B13: 7.1 HID BACHOCO Planta Culiacan RYASA Culiacan | C13: BACHOCO Planta Culiacan | D13: Ganada | E13: 45225 | F13: 896674.02 | G13: Revisar | H13: Validar uso propio de mantenimiento y segmento | I13: La cuenta está segmentada Corporate (segunda cuenta de Culiacán); falta validar uso propio y segmento.
A14: 662447 | B14: 3.1 Plant Master Xtreme 501 Bachoco S.A. de C.V. - Planta Culiacan FP-IND HOSE & CPLG-662447 | C14: Bachoco S.A. de C.V. - Planta Culiacan | D14: Ganada | E14: 45240 | F14: 448337.01 | G14: Excluida | H14: OEM / primer equipo | I14: La cuenta está segmentada como OEM. HIPÓTESIS por confirmar: si la compra es para mantener equipos propios de la planta, sería usuario final (contexto/OBJETIVO_RICARDO.md: una manufacturera es usuario final cuando compra para mantenimiento de su propia operación). Decide quien lleva la cuenta.
A15: 703452 | B15: 3.1 35W Bachoco S.A. de C.V. - Planta Culiacan FP-IND HOSE & CPLG-703452 | C15: Bachoco S.A. de C.V. - Planta Culiacan | D15: Ganada | E15: 45320 | F15: 876912.89 | G15: Excluida | H15: OEM / primer equipo | I15: La cuenta está segmentada como OEM. HIPÓTESIS por confirmar: si la compra es para mantener equipos propios de la planta, sería usuario final (contexto/OBJETIVO_RICARDO.md: una manufacturera es usuario final cuando compra para mantenimiento de su propia operación). Decide quien lleva la cuenta.
A16: 682290 | B16: 7.1 HID BACHOCO PLANTA CULIACAN- RYASA CULIACAN | C16: Bachoco S.A. de C.V. - Planta Culiacan | D16: Ganada | E16: 45520 | F16: 361081.8 | G16: Excluida | H16: OEM / primer equipo | I16: La cuenta está segmentada como OEM. HIPÓTESIS por confirmar: si la compra es para mantener equipos propios de la planta, sería usuario final (contexto/OBJETIVO_RICARDO.md: una manufacturera es usuario final cuando compra para mantenimiento de su propia operación). Decide quien lleva la cuenta.
... A26: 812811 | B26: 2.2 Parker Bachoco San Luis Potosi Ryasa SLP -812811 | C26: Bachoco S.A. de C.V. - San Luis Potosi | D26: Abierta | E26: 46353 | F26: 199999.98 | G26: Sin decisión (posterior al corte) | H26: - | I26: Posterior al corte de DETALLE (12-ago-2026): sin decisión del programa.
A28: Ganadas no Elegibles | B28: =COUNTIF(D5:D26,"Ganada") -> 13
A29: Potencial anual registrado de esas ganadas (MXN) | B29: =SUMIFS(F5:F26,D5:D26,"Ganada") -> 8365530.5

Sheet Réplicas por validar
A1: Candidatas de réplica: de dónde sale el caso y a dónde llevarlo
A2: Ninguna réplica está confirmada. El dictamen es del especialista en aplicaciones (texto completo en datos_trabajo/BACHOCO_REPLICAS_DICTAMEN.csv). Cada fila dice qué hechos la apoyan y qué falta comprobar antes de ofrecerla. El CRM no registra la aplicación ni el equipo de ninguna oportunidad: antes de visitar un destino hay que documentarlos en el origen.
A4: # | B4: Caso fuente (zona y línea) | C4: Oportunidades de ejemplo (nomenclatura completa) | D4: Sitio destino | E4: Cuenta CRM del destino | F4: Qué se sabe del destino (con fuente) | G4: Quién se mueve hoy en el destino | H4: A favor y en contra | I4: Dictamen del especialista en aplicaciones | J4: Qué falta validar en lo técnico | K4: Preguntas para la visita | L4: Estado
A5: R1 | B5: Bajío (Celaya), banda en V: la cuenta "Planta procesadora de aves Guanajuato - Guanajuato" tiene 11 ganadas de dic-2020 a jun-2024: 10 Elegibles y 1 Excluida (575363, ID 2.1). Todas con propietario marcado inactivo. | C5: 643201 7.1 V-Belts Bachoco, S.A. de C.V. - Planta procesadora de aves Guanajuato - Guanajuato PT-V-BELTS-643201 (ganada, Elegible, 2023-04-27, 538,004 MXN potencial anual registrado) 555451 2.2 PTI Optibelt Bachoco, S.A. de C.V. - Planta procesadora de aves Guanajuato - Guanajuato PT-V-BELTS-555451- Ryasa Qro. (ganada, Elegible, 2022-01-28, 525,478 MXN potencial anual registrado) 631793 2.2 PTI Optibelt Bachoco, S.A. de C.V. - Planta procesadora de aves Guanajuato - Guanajuato PT-V-BELTS-631793 (ganada, Elegible, 2022-12-29, 341,089 MXN potencial anual registrado) | D5: Rastro TIF A-183, Unión de San Antonio, Jalisco (complejo "Lagos"; BCH-011). | E5: No hay cuenta en el CRM. La oportunidad O-00218689 "7.1 PCC C2B-Bachoco Lagos- Bamac Guadalajara" (perdida, 2020, PCC) quedó capturada en la cuenta de Celaya; que se refiera a este sitio es HIPÓTESIS (solo por el nombre). | F5: Rastro de aves de Bachoco, S.A. de C.V. (SENASICA 2024, confirmado). Incendio el 3-may-2026 en una planta de Lagos de Moreno (solo prensa; podría ser el mismo sitio); operaciones suspendidas una semana, rehabilitación en curso al 11-may-2026; reapertura PENDIENTE. Una rehabilitación no es demanda de reposición. | G5: Sin cuenta ni abiertas conocidas. Marcos mencionó que otras regiones atienden Bachoco, sin precisar si incluyen Lagos (pendiente). | H5: A FAVOR: misma familia (banda en V de transmisión) y misma razón social en rastros de aves; el origen tiene más ganadas de banda en V que cualquier otra cuenta del grupo. EN CONTRA O FALTA: el CRM no registra equipo ni aplicación en ninguna de las 11; el origen no está ligado con certeza al rastro de Celaya; sin ganadas ni abiertas después de jun-2024; la única historia del destino es otra familia (PCC) y se perdió. | I5: PARCIAL. Misma familia (banda en V de transmisión) y mismo tipo de operación (rastro de aves TIF de la misma razón social), con más ganadas de banda en V que cualquier otra cuenta del grupo. No sube a SÍ porque: el predio físico del origen no está confirmado, ninguna de las 11 ganadas registra equipo ni aplicación, el destino no tiene un solo accionamiento documentado y su operación tras el incendio está PENDIENTE. Confianza: HIPÓTESIS - media-baja. Origen sólido en CRM (CONFIRMADO), destino débil (sin cuenta, sin equipo conocido, operación PENDIENTE tras el incendio). Sube a SÍ solo si se documentan los equipos del origen y se confirma que A-183 opera con accionamientos equivalentes. Nota del Excel: las cifras de este dictamen cuentan todo el CRM salvo que diga Elegible. | J5: 1) ORIGEN primero: en qué equipos va la banda en V comprada desde 2020 (por equipo: perfil y sección, longitud, bandas por juego, poleas, potencia y velocidad del motor) y con qué frecuencia real se cambia (dato de planta, no del CRM). 2) DESTINO: si el sitio TIF A-183 es el mismo que el siniestrado; qué áreas operan y cuáles se reconstruyen; inventario de accionamientos por banda en V y marca instalada. 3) Equipo contra equipo: misma familia no es mismo número de parte; si el destino usa otra sección o banda síncrona (su única historia es PCC), sería otra oferta, no réplica. 4) Condiciones de servicio a medir: humedad y químicos de lavado cerca de los accionamientos, frío o calor (cuartos fríos, calderas, rendimiento), polvo o grasa, turnos. 5) Solo cuenta la banda que transmite potencia del motor al equipo, no la banda o cinta que mueve producto. Ningún equipo se da por existente hasta verlo. | K5: MANTENIMIENTO (destino): 1) ¿La planta de la carretera Lagos - Unión de San Antonio Km 13.5 (TIF A-183) es la que se incendió el 2026-05-03? ¿Qué áreas operan hoy y cuáles siguen en rehabilitación? 2) ¿Qué equipos tienen transmisión por banda en V, con qué perfil, medida y marca, y cuáles fallan más por humedad, lavado o calor? COMPRAS (destino): 3) ¿A quién compran hoy la banda en V, quién autoriza un cambio de marca (la planta o el corporativo de Celaya) y qué pasó con la propuesta de 2020 registrada como '7.1 PCC C2B-Bachoco Lagos- Bamac Guadalajara'? ORIGEN (antes de visitar Lagos): ¿en qué equipos se instaló la banda en V comprada de 2020 a 2024 y por qué no hay oportunidades registradas después de junio de 2024? | L5: Por validar
A6: R2a | B6: Tecamachalco: 4 ganadas Elegibles de manguera industrial Plant Master (la última, sep-2025). Como referencia con clasificación dudosa (ninguna es Elegible): Culiacán, 6 ganadas, 5 de manguera. | C6: ORIGEN ELEGIBLE (Tecamachalco): O-00249657 3.1 Plant Master Xtreme 325 (19B) Bachoco Tecamachalco Lamuño Puebla (ganada, Elegible, 2020-09-22, 92,752 MXN potencial anual registrado) O-00251750 3.1 PlantMaster Xtreme 501 Bachoco Tecamachalco Binasa Puebla (ganada, Elegible, 2020-10-23, 111,302 MXN potencial anual registrado) O-00254712 3.1 PlantMaster Terminator Bachoco Tecamachalco Lamuño Puebla (ganada, Elegible, 2020-12-24, 74,201 MXN potencial anual registrado) 789991 7.1 PlantMaster Xtreme 501 (Terminator) Bachoco Tecamachalco Lamuño Puebla (ganada, Elegible, 2025-09-15, 187,626 MXN potencial anual registrado) REFERENCIA, NO ELEGIBLES (Culiacán): 703452 3.1 35W Bachoco S.A. de C.V. - Planta Culiacan FP-IND HOSE & CPLG-703452 (ganada, Excluida, 2024-01-29, 876,913 MXN potencial anual registrado) 662447 3.1 Plant Master Xtreme 501 Bachoco S.A. de C.V. - Planta Culiacan FP-IND HOSE & CPLG-662447 (ganada, Excluida, 2023-11-10, 448,337 MXN potencial anual registrado) 653398 3.1 MXT Bachoco S.A. de C.V. - Planta Culiacan FP-HYDRAULICS-653398 (ganada, Excluida, 2023-06-22, 511,104 MXN potencial anual registrado) | D6: Rastro TIF A-363, Celaya (BCH-010). | E6: Celaya: "Planta procesadora de aves Guanajuato - Guanajuato" (cruce por confirmar) y 4 cuentas más de Celaya. | F6: Celaya suma 14 ganadas Elegibles de transmisión (20 con todo el CRM) y ninguna oportunidad de manguera (ni ganada, ni perdida, ni abierta); distribuidor en las ganadas: RYASA Querétaro y Celaya. | G6: La cuenta con más ganadas de Celaya tiene propietario marcado inactivo; otras 4 cuentas de Celaya figuran a nombre de Ulises Sánchez (confirmar vigencia). Responsable vigente PENDIENTE. | H6: A FAVOR: manguera industrial Plant Master ganada en dos cuentas distintas (Culiacán = rastro A-124 por domicilio; Tecamachalco = rastro A-326 por confirmar) con distribuidores distintos; Tecamachalco la volvió a ganar en 2025. Solo las de Tecamachalco son Elegibles. EN CONTRA O FALTA: para manguera hidráulica NO se sostiene (con todo el CRM, 4 ganadas contra 5 perdidas; con solo Elegibles, 1 contra 3); las ganadas de manguera de Culiacán no son Elegibles (cuenta OEM, 4 Excluidas y 1 en Revisar), así que con la regla del programa el origen es solo Tecamachalco; "cero registros" en Celaya no prueba que usen manguera; el producto "35W" no está identificado. | I6: PARCIAL para manguera industrial (Plant Master); NO sostenida todavía para manguera hidráulica. Industrial: ganadas repetidas en dos cuentas del grupo (Culiacán = rastro A-124 por domicilio; Tecamachalco = rastro A-326 por confirmar) y destino del mismo tipo de operación, pero sin aplicación conocida en el origen ni uso confirmado en el destino. Hidráulica: historial del grupo dividido (Culiacán 3 ganadas y 1 perdida; Tecamachalco y Mexicali 0 ganadas y 4 perdidas; Coatzacoalcos 1 ganada) y ningún equipo hidráulico conocido en Celaya. Confianza: HIPÓTESIS - media para manguera industrial (dos plantas origen con ganadas repetidas y mismo tipo de operación confirmado); baja para hidráulica (historial dividido, sin equipo conocido en el destino). Nota del Excel: las cifras de este dictamen cuentan todo el CRM salvo que diga Elegible. Con la regla del programa el origen de manguera industrial es una sola planta (Tecamachalco), porque Culiacán no tiene oportunidades Elegibles; la confianza del especialista se apoyó en dos plantas origen, así que queda condicionada a que se reclasifique Culiacán (ver Pendientes). | J6: 1) Documentar el origen: servicio de cada Plant Master ganada (fluido, presión de trabajo, temperatura, químico de limpieza y concentración, diámetro, largo, tipo de cople) y qué equipo lleva la manguera MXT/HID en Culiacán. Sin esto no hay caso que replicar. 2) Celaya: si existen los mismos servicios y en qué condiciones (agua caliente o vapor, lavado a presión con químicos, aire, contacto con grasa animal, frío); si cambian presión, temperatura o químico puede cambiar la referencia correcta aunque la familia sea la misma. 3) Hidráulica: inventario de equipos con circuito hidráulico en el rastro y en la planta de rendimiento (BCH-020); presión, fluido, temperatura, norma de terminales; quién arma las mangueras (planta o distribuidor). 4) Canal de compra: planta o contrato del corporativo (mismo municipio, BCH-001). Ningún servicio ni equipo se da por existente hasta verlo. | K6: MANTENIMIENTO: 1) ¿En qué servicios usan manguera industrial (lavado sanitario, agua caliente, vapor, aire, químicos), con qué presión, temperatura y químico, cuál es la falla más frecuente y cada cuánto la cambian? 2) ¿Qué equipos del rastro y de la planta de rendimiento tienen circuitos hidráulicos y quién arma esas mangueras? COMPRAS: 3) ¿A qué proveedor y por qué canal compran hoy manguera industrial e hidráulica, la compra es de la planta o del corporativo, y quién aprueba probar otra marca? ORIGEN (antes de la visita): ¿qué servicio atienden 662447, 703452 y las Plant Master de Tecamachalco, y qué producto es '35W'? | L6: Por validar
A7: R2b | B7: Mismo origen que R2a. | C7: ORIGEN (Tecamachalco): O-00251750 3.1 PlantMaster Xtreme 501 Bachoco Tecamachalco Binasa Puebla (ganada, Elegible, 2020-10-23, 111,302 MXN potencial anual registrado) 789991 7.1 PlantMaster Xtreme 501 (Terminator) Bachoco Tecamachalco Lamuño Puebla (ganada, Elegible, 2025-09-15, 187,626 MXN potencial anual registrado) DESTINO (Ciénega de Flores): 804237 2.2 VBelt BACHOCO/ RYASA - Cienega de Flores PT & FP-804237 (ganada, Excluida, 2026-07-24, 420,400 MXN potencial anual registrado) 811939 2.2 BACHOCO/ RYASA - Cienega de Flores PT-MV BELTS-811939 (abierta, Excluida, 2026-10-09, 291,252 MXN potencial anual registrado) | D7: Rastro TIF A-423, Ciénega de Flores, Nuevo León (BCH-013). | E7: "BACHOCO SA de CV - Cienega de Flores" (cruce por domicilio, confirmado). | F7: Cuenta creada el 6-abr-2026, segmentada Exporter/Trading Company. 1 ganada (804237 "2.2 VBelt BACHOCO/ RYASA - Cienega de Flores PT & FP-804237", jul-2026) y 1 abierta (811939 "2.2 BACHOCO/ RYASA - Cienega de Flores PT-MV BELTS-811939", potencial anual registrado 291,252, cierre registrado 2026-10-09: fecha ya pasada). Las dos están Excluidas por el programa (segmento intermediario). | G7: Propietario en el CRM de la región 34 (Noreste); atiende RYASA San Nicolás de los Garza. | H7: A FAVOR: rastro de aves de la misma razón social, con cuenta activa y relación reciente. EN CONTRA O FALTA: el sufijo "PT & FP" de la ganada sugiere que ya se vendió algo de potencia fluida (podría ser ampliación y no réplica); la cuenta es nueva; el programa excluyó sus oportunidades por segmento intermediario. | I7: PARCIAL, más débil que Celaya. Mismo tipo de operación confirmado y cuenta activa, pero la cuenta tiene 6 meses en el CRM y su única ganada ya trae un componente FP sin detalle: la manguera podría estar ya atendida y entonces sería ampliación, no réplica. Confianza: HIPÓTESIS - baja-media. Operación equivalente confirmada por tipo de planta, pero historial de la cuenta muy corto y contenido FP de 804237 PENDIENTE. Nota del Excel: las cifras de este dictamen cuentan todo el CRM salvo que diga Elegible. Con la regla del programa el origen de manguera industrial es una sola planta (Tecamachalco), porque Culiacán no tiene oportunidades Elegibles; la confianza del especialista se apoyó en dos plantas origen, así que queda condicionada a que se reclasifique Culiacán (ver Pendientes). | J7: 1) Primero: qué se vendió como FP en 804237 (familia, servicio, equipo). 2) Las mismas validaciones de servicio que en Celaya: fluido, presión, temperatura, químicos de lavado, diámetros y coples; equipos con circuito hidráulico en el rastro y en la planta de rendimiento (BCH-025). 3) Condiciones de entorno a medir, no suponer: temperatura ambiente y del agua de servicio, si el lavado usa agua caliente o vapor, exposición al sol de mangueras en patios o andenes. 4) Confirmar que la compra es para mantenimiento propio (segmentación Exporter/Trading en el CRM). | K7: MANTENIMIENTO: 1) ¿Entró algún producto de potencia fluida en el cambio de proveedor de julio de 2026 y, si entró, en qué servicio se instaló? 2) ¿En qué servicios usan manguera industrial e hidráulica, con qué presión, temperatura y químicos, y qué marca tienen hoy? COMPRAS: 3) ¿La planta compra para su propio mantenimiento o a través de otra empresa del grupo, y quién aprueba agregar manguera al proveedor actual de bandas? | L7: Por validar
A8: R3 | B8: Oportunidades 2.2 PTI que nombran a Optibelt en el Bajío (555451, 555609, 631793: 3 ganadas, banda en V). El CRM las tipifica Replacement / Existing Business, no Competitive Share Gain; que hayan desplazado a Optibelt es HIPÓTESIS. | C8: 555451 2.2 PTI Optibelt Bachoco, S.A. de C.V. - Planta procesadora de aves Guanajuato - Guanajuato PT-V-BELTS-555451- Ryasa Qro. (ganada, Elegible, 2022-01-28, 525,478 MXN potencial anual registrado) 555609 2.2 PTI Optibelt Bachoco, S.A. de C.V. - Planta procesadora de aves Guanajuato - Guanajuato PT-V-BELTS-555609- Ryasa Qro (ganada, Elegible, 2022-01-28, 525,478 MXN potencial anual registrado) 631793 2.2 PTI Optibelt Bachoco, S.A. de C.V. - Planta procesadora de aves Guanajuato - Guanajuato PT-V-BELTS-631793 (ganada, Elegible, 2022-12-29, 341,089 MXN potencial anual registrado) 679801 2.2 PTI Optibelt Bachoco DBS Hermosillo (perdida, Elegible, 2023-12-01, 179,335 MXN potencial anual registrado) | D8: Hermosillo, Sonora y resto del Noroeste. | E8: "Bchoco S.A. de C.V. - Planta Hermosillo" (cruce por confirmar con BCH-018). La oportunidad 679801 está capturada en la cuenta "Bachoco" de Cd. Obregón aunque su nombre dice Hermosillo. | F8: La oferta ya se presentó en Sonora y se perdió (679801, dic-2023). El Noroeste suma 6 perdidas Elegibles (7 con todo el CRM) y 0 ganadas; solo una perdida es de banda en V. No hay rastro de aves de Bachoco con fuente oficial en Sonora. El archivo no trae el motivo de pérdida. | G8: Sin abiertas. Los propietarios históricos de las 7 perdidas están marcados inactivos (región 37); responsable vigente PENDIENTE. | H8: A FAVOR: la banda en V se ganó en una planta del grupo y esa misma cuenta perdió intentos en 2019 antes de ganar. EN CONTRA O FALTA: instalación destino no identificada; no está claro que las del origen hayan sido conversiones; 555451 y 555609 podrían ser captura duplicada; no se sabe qué se sustituyó. | I8: NO sostenida hoy. No hay destino técnico definido (no se sabe si es planta de aves, de rendimiento, rastro de cerdo de Norson o CEDIS), la conversión del origen no está registrada como tal en el CRM y la misma oferta ya se presentó en Sonora y se perdió sin motivo registrado. Repetirla sin esos datos sería un reintento, no una réplica. Confianza: PENDIENTE - baja. Reabrir como HIPÓTESIS solo si se identifica la instalación destino, se conoce el motivo de la pérdida de 679801 y se documenta qué se sustituyó en el origen. Nota del Excel: las cifras de este dictamen cuentan todo el CRM salvo que diga Elegible. | J8: 1) Identificar la instalación destino: aves, rendimiento, cerdo (Norson) o CEDIS; cada una tiene otros equipos y otras condiciones, y solo una planta de aves sería equivalente al origen. 2) Origen: qué se sustituyó en 2022 (banda Optibelt instalada cambiada a Gates en los mismos equipos, o cotización contra equivalencias) y en qué equipos; sin eso no hay argumento técnico que llevar. 3) Destino: inventario de accionamientos por banda en V, perfil y marca instalada, y si la marca la fija un estándar del grupo. 4) Condiciones de servicio a medir, no suponer: temperatura ambiente y polvo, lavado y humedad, horas de operación. 5) Cobertura técnica del distribuidor en la plaza (en 2023 fue DBS Hermosillo). | K8: MANTENIMIENTO: 1) ¿Qué instalación de Bachoco en Sonora recibió la propuesta de banda en V de 2023 ('2.2 PTI Optibelt Bachoco DBS Hermosillo') y qué equipos con banda en V tiene, con qué marca y perfil? 2) ¿Qué problema tienen hoy con esas bandas (vida, tensión, deslizamiento, lavado, calor, polvo)? COMPRAS: 3) ¿Por qué no se aceptó esa propuesta (precio, prueba técnica, disponibilidad del distribuidor o estándar de marca del grupo) y quién decide la marca de banda en V: la planta o el corporativo? ORIGEN (antes): ¿qué se sustituyó exactamente en 555451, 555609 y 631793? | L8: No recomendada por ahora

Sheet Reglas de homologación
A1: Cómo dejar las cuentas Bachoco registradas de la misma forma (propuesta)
A2: Son propuestas. No se cambió nada en el CRM ni en datos_originales. Los valores salen de la tabla oficial de End Market de Gates (guía de alta de oportunidades). Lo que no se pudo confirmar queda como pregunta.
A4: # | B4: Campo | C4: Cómo está hoy (CONFIRMADO en el CRM) | D4: Propuesta | E4: Cuentas u oportunidades afectadas (fórmula)
A5: 1 | B5: Nombre de la cuenta | C5: Formatos mezclados ("Bachoco S.A. de C.V. - X", "Bachoco, S.A. De C.V. - X", "BACHOCO SA de CV - X", "Industrias Bachoco ..."); un error de ortografía ("Bchoco" en Hermosillo); un nombre que contradice el domicilio ("Planta procesadora de aves Sonora" con domicilio en Mexicali, BC); cuatro cuentas en Celaya y una en "San Isidro Crespo", y dos nombres que dicen "Guanajuato". | D5: Un solo formato: "Bachoco, S.A. de C.V. - {Municipio}" y, si hay más de un sitio en el mismo municipio, agregar " - {tipo de instalación}" (por ejemplo "- Corporativo"). El municipio sale del domicilio verificado, no del nombre. Ver columna "PROPUESTA: nombre". | E5: -
A6: 2 | B6: End Market (categoría) | C6: 20 cuentas en Food & Beverage y 1 en Agriculture (la creada por integración el 15-abr-2026). | D6: Food & Beverage para plantas de proceso (la tabla de Gates dice: planta de alimentos = Food & Beverage). Queda como pregunta si las plantas de alimento balanceado, incubadoras y granjas deben ir en Agriculture; hoy no hay cuentas de ese tipo. | E6: =COUNTIF('Cuentas CRM y homologación'!$J$2:$J$22,"<>Food & Beverage") -> 1
A7: 3 | B7: End Market (subcategoría) | C7: 15 con "Manufacturing - Food Processing", 5 vacías y 1 con "Agriculture Equipment". | D7: "Manufacturing - Food Processing" (es la que usa la guía de alta para plantas de proceso alimentario y la que ya tiene la mayoría). | E7: =COUNTIF('Cuentas CRM y homologación'!$K$2:$K$22,"<>Manufacturing - Food Processing") -> 6
A8: 4 | B8: Segmentación del cliente | C8: 18 End User, 1 OEM (Culiacán), 1 Exporter/Trading Company (Ciénega de Flores) y 1 Corporate (segunda cuenta de Culiacán). La cuenta que se llama "Corp" está como End User. | D8: End User para todas las plantas: en la guía de alta, End User es la empresa que usa el producto en su proceso y OEM es la que fabrica productos. Ojo: el programa dejó fuera (Excluida) 5 ganadas de Culiacán por "OEM / primer equipo" y 1 de Ciénega de Flores por "Segmento intermediario", y puso en Revisar 1 de la segunda cuenta de Culiacán. Quién lleva esas cuentas decide; la corrección no se hizo. Las 7 están en la hoja Clasificación dudosa. | E8: =COUNTIF('Cuentas CRM y homologación'!$I$2:$I$22,"<>End User") -> 3
A9: 5 | B9: Industria primaria | C9: Vacía en las 21 cuentas. | D9: Definir con el administrador del CRM un solo valor para Bachoco y llenarlo en todas. No se propone un valor porque la lista oficial no la tengo. | E9: =COUNTIF('Cuentas CRM y homologación'!$L$2:$L$22,"(vacío)") -> 21
A10: 6 | B10: Propietario | C10: 1 cuenta con propietario marcado inactivo; 5 cuentas con propietarios que no aparecen en la hoja Team del archivo IR (Cesar Vázquez, 4 cuentas; Dan Weller, 1); 2 cuentas (Mérida y Umán) con el NSM como propietario. 16 de las 20 ganadas del Bajío (todo el CRM) están a nombre de un propietario marcado inactivo. | D10: Que el gerente regional o el NSM designe a un responsable vigente por sitio y quién recupera los expedientes de los propietarios inactivos, antes de asignar trabajo. Esta hoja solo señala; no asigna a nadie. | E10: =SUMPRODUCT(--ISNUMBER(SEARCH("inactive",'Cuentas CRM y homologación'!$G$2:$G$22)))+COUNTIF('Cuentas CRM y homologación'!$G$2:$G$22,"Cesar Vázquez")+COUNTIF('Cuentas CRM y homologación'!$G$2:$G$22,"Dan Weller")+COUNTIF('Cuentas CRM y homologación'!$G$2:$G$22,"Ricardo Narvaez") -> 8
A11: 7 | B11: Cuenta corporativa y cuentas repetidas | C11: La cuenta "Corp" está en Celaya (Av. Tecnológico 401). Tres cuentas de Celaya ("BACHOCO S.A. DE C.V.", "Corp" y "Guanajuato") comparten el mismo contacto principal. Culiacán tiene dos cuentas con el mismo domicilio. Obregón tiene dos y Mérida tiene dos en la misma Ciudad Industrial (CP 97288). | D11: Una cuenta corporativa y las plantas ligadas a ella, si el CRM maneja jerarquía de cuentas (el archivo que pasaste no trae la columna de cuenta padre). Unir las cuentas repetidas conservando el historial de oportunidades, con el administrador del CRM. | E11: -
A12: 8 | B12: Contacto principal | C12: 2 cuentas sin contacto principal (Obregón y Cuautla); 7 sin correo del contacto principal. | D12: Capturar al menos un contacto de mantenimiento o compras por sitio. Se completa en la visita, no se inventa. | E12: =COUNTIF('Cuentas CRM y homologación'!$O$2:$O$22,"No") -> 2
A13: 9 | B13: End Market de las oportunidades | C13: 24 de las 68 oportunidades de cuentas Bachoco tienen una categoría distinta a Food & Beverage (22 con Manufacturing - General, 1 con Mining y 1 sin especificar) aunque la cuenta es de alimentos. | D13: Que cada oportunidad herede el End Market y la subcategoría de la cuenta (la guía de alta dice que vienen pre-llenados desde la cuenta). Lo corrige el propietario de cada oportunidad. | E13: =COUNTIFS(Oportunidades!$D$2:$D$71,"Sí",Oportunidades!$X$2:$X$71,"<>Food & Beverage") -> 24
A14: 10 | B14: ID de proyecto en la nomenclatura | C14: Dos ganadas de Bachoco llevan ID 2.1 (conversión de distribuidores) aunque el cliente es el usuario final: 545700 "2.1 PTI-BACHOCO S.A. DE C.V. PT-V-BELTS- RYASA QRO--545700" y 575363 "2.1 PTI-Bachoco, S.A. de C.V. - Planta procesadora de aves Guanajuato - Guanajuato PT-V-BELTS-575363". Por eso el programa las excluyó. | D14: Revisar con quien las capturó si debían ser 2.2 (conversión de usuario final). Mientras no se corrija, quedan fuera del programa (Excluida); siguen contando en los totales de todo el CRM. | E14: =COUNTIFS(Oportunidades!$D$2:$D$71,"Sí",Oportunidades!$M$2:$M$71,2.1) -> 0

Sheet Pendientes y preguntas
A1: Lo que falta confirmar
A3: # | B3: Pendiente o pregunta | C3: Por qué importa | D3: Quién puede responder
A4: 1 | B4: Documentar en el origen en qué equipo y servicio se usa cada producto ganado (banda en V en Celaya; Plant Master, MXT e HID en Culiacán y Tecamachalco; qué es el producto "35W"). | C4: Sin saber dónde va cada producto no hay caso técnico que replicar: el CRM no registra la aplicación ni el equipo de ninguna oportunidad. | D4: Los distribuidores que surtieron esas ganadas (RYASA Querétaro, RYASA Culiacán, Lamuño y Binasa Puebla) y el responsable vigente de cada cuenta (en Celaya, el que designe el gerente del Bajío; ver la pregunta sobre quién lleva hoy el Bajío).
A5: 2 | B5: ¿Qué instalación es cada una de las 6 cuentas "por confirmar" y de las 9 sin sitio público? (Mexicali, San Luis Potosí, Tierra Blanca, Gómez Palacio, Obregón-Navojoa, 3 de Celaya y 1 de Mérida.) | C5: Sin saber qué es cada una no se puede decidir si es una planta nueva por abrir, un duplicado o una oficina. | D5: Quien lleva hoy cada cuenta, con su distribuidor (RYASA, DBS, EISSA, etc.).
A6: 3 | B6: ¿Quién lleva hoy el Bajío y Celaya? 16 de las 20 ganadas del Bajío (todo el CRM) y la cuenta con más ganadas están a nombre de un propietario marcado inactivo. | C6: Regla del proyecto: no asignar trabajo a inactivos; primero hay que designar quién recupera el expediente. | D6: El gerente de la región Bajío o el NSM lo designa.
A7: 4 | B7: ¿Qué plantas atienden las otras regiones? Hay abiertas de otros propietarios: región 34 (Ciénega de Flores), 35 (Gómez Palacio), 36 (Mérida) y dos en San Luis Potosí (propietario distinto de ti, también en la región 32). | C7: Marcos dijo que otras regiones ya atienden Bachoco; la campaña debe coordinarse con ellas y no duplicar. | D7: Marcos, con los propietarios de las abiertas y el NSM.
A8: 5 | B8: ¿Alguien atiende la planta de Lagos / Unión de San Antonio? ¿Reabrió después del incendio del 3-may-2026? | C8: Es el único rastro de aves con fuente oficial sin cuenta en el CRM. Una reparación posterior a un incendio no es demanda confirmada. | D8: Distribuidor de Guadalajara (BAMAC) y otras regiones; prensa local.
A9: 6 | B9: Motivo de pérdida de las 6 perdidas Elegibles del Noroeste y de las 6 de bandas síncronas, poliuretano y micro-V. | C9: Motivo no disponible: el CRM no tiene ese campo. Sin saberlo no conviene replicar ahí. | D9: El gerente de la región Noroeste designa quién recupera el expediente (los propietarios históricos están marcados inactivos); el distribuidor DBS o RYASA puede aportar lo que recuerde.
A10: 7 | B10: ¿La segmentación correcta de Culiacán es End User, y la de Ciénega de Flores también? | C10: Con OEM o Exporter/Trading el programa dejó fuera 6 ganadas (Excluida) y, por la cuenta Corporate, puso 1 en Revisar: 4.2 millones bruto en total. La guía de alta dice que End User es quien usa el producto en su proceso. Si se corrigen, Culiacán podría sustentar un caso. | D10: Marcos (Culiacán) y el propietario de Ciénega de Flores en el CRM.
A11: 8 | B11: ¿El CRM tiene jerarquía de cuentas (cuenta padre y plantas hijas)? El archivo que pasaste no trae esa columna. | C11: Si existe, "Corp" debería ser la cuenta padre y las plantas colgar de ella. | D11: Administrador del CRM.
A12: 9 | B12: ¿Qué End Market y subcategoría usa Gates para granjas, incubadoras y plantas de alimento balanceado? | C12: Hoy no hay cuentas de ese tipo, pero si se dan de alta hay que usar el mismo valor en todas. | D12: Administrador del CRM / gerencia comercial.
A13: 10 | B13: ¿Cuáles cuentas repetidas se unen? (Culiacán 2, Celaya 3 a 5, Obregón 2, Mérida 2.) | C13: Unir cuentas cambia el historial; no lo hice ni lo propongo sin tu visto bueno y el del administrador. | D13: Marcos y el administrador del CRM.
A14: 11 | B14: Verificar con Bachoco o su distribuidor la vigencia 2026 de las plantas de la lista pública. | C14: Las direcciones de los rastros vienen del directorio de SENASICA 2024 (el vigente, del 13-oct-2026, no se pudo leer) y los datos de las plantas de alimento vienen de páginas sin fecha. | D14: Investigación de plantas, con visita o llamada.
A15: 12 | B15: La oportunidad O-00231727 "2.2 PT - Bachoco - Ryasa - MID" (perdida, 2020) y la O-00222445 "8 BACHOCO - Tuxtla Gutierrez" (perdida, 2019) están capturadas en cuentas de distribuidor. | C15: Sugieren sitios de Bachoco en Mérida y Tuxtla Gutiérrez que no están como cuenta propia. No hay sitio público en Tuxtla. | D15: El propietario en el CRM de esas oportunidades (cuentas especiales, región 45/46).
... A17: 14 | B17: Dos abiertas ya pasaron su fecha de cierre registrada: 811939 "2.2 BACHOCO/ RYASA - Cienega de Flores PT-MV BELTS-811939" (2026-10-09) y 810579 "2.2 PTV Continental Bachoco Mérida Eissa Mérida" (2026-09-18). | C17: Pueden estar vencidas o ganadas sin actualizar; cambia el conteo de abiertas. | D17: Los propietarios de esas oportunidades en el CRM (regiones 34 y 36).

Sheet Oportunidades
A1: Núm. de oportunidad | B1: Nomenclatura completa (campo Nombre de oportunidad) | C1: Cuenta en el CRM | D1: ¿Cuenta Bachoco? | E1: Zona | F1: Municipio de la cuenta | G1: Estado de la cuenta | H1: Estatus | I1: Fecha de cierre | J1: Año | K1: Potencial anual MXN (registrado; NO es facturación) | L1: Posible re-registro (mismo monto en la misma zona) | M1: ID de proyecto | N1: Tipo (CRM) | O1: Línea según la nomenclatura | P1: Grupo de línea | Q1: Base de la clasificación | R1: Competidor nombrado en la nomenclatura | S1: Distribuidor (Supplier) | T1: Región CRM | U1: Propietario CRM (histórico) | V1: ¿Propietario marcado inactivo? | W1: Segmentación en la oportunidad | X1: End Market en la oportunidad | Y1: Subcategoría en la oportunidad | Z1: Decisión del programa | AA1: Motivo del programa | AB1: Nota | AC1: Categoría del tipo de oportunidad (CRM)
A2: 650190 | B2: 7.1 HID BACHOCO Planta Culiacan RYASA Culiacan | C2: BACHOCO Planta Culiacan | D2: Sí | E2: Sinaloa (Culiacán) | F2: Culiacán | G2: Sinaloa | H2: Ganada | I2: 45225 | J2: 2023 | K2: 896674.02 | L2: No | M2: 7.1 | N2: Incremental | O2: Manguera hidráulica (FP-HYDRAULICS) | P2: Manguera hidráulica y neumática | Q2: abreviatura en el nombre | S2: Rodamientos y accesorios, S.A. de C.V. - 100807 - Culiacan | T2: 32 Pacífico | U2: Marcos Arevalo | V2: No | W2: Corporate | X2: Food & Beverage | Y2: Manufacturing - Food Processing | Z2: Revisar | AA2: Validar uso propio de mantenimiento y segmento | AC2: Adding Different Product Line
A3: O-00221100 | B3: 4.1 PTI-BACHOCO BAJIO-RYASA CELAYA | C3: BACHOCO S.A. DE C.V. | D3: Sí | E3: Bajío (Celaya) | F3: Celaya | G3: Guanajuato | H3: Ganada | I3: 43585 | J3: 2019 | K3: 1855036 | L3: No | M3: 4.1 | N3: Replacement | O3: Banda en V / transmisión (PT-V-BELTS) | P3: Bandas en V | Q3: abreviatura en el nombre | S3: Rodamientos Y Accesorios S.A. de C.V. - 050308 - Celaya | T3: 38 Bajío | U3: Froylan Santiago Inactive Alcántara | V3: Sí | W3: End User | X3: Manufacturing - General | Y3: Other | Z3: Revisar | AA3: Nomenclatura no concluyente | AC3: Existing Business
A4: O-00244318 | B4: 4.2 PTI BACHOCO-RYASA CLY | C4: BACHOCO S.A. DE C.V. | D4: Sí | E4: Bajío (Celaya) | F4: Celaya | G4: Guanajuato | H4: Ganada | I4: 43945 | J4: 2020 | K4: 371007.16 | L4: No | M4: 4.2 | N4: Replacement | O4: Banda en V / transmisión (PT-V-BELTS) | P4: Bandas en V | Q4: abreviatura en el nombre | S4: Rodamientos Y Accesorios S.A. de C.V. - 050308 - Celaya | T4: 38 Bajío | U4: Froylan Santiago Inactive Alcántara | V4: Sí | W4: End User | X4: Manufacturing - General | Y4: Manufacturing - Food Processing | Z4: Revisar | AA4: Nomenclatura no concluyente | AC4: Existing Business
A5: 545700 | B5: 2.1 PTI-BACHOCO S.A. DE C.V. PT-V-BELTS- RYASA QRO--545700 | C5: BACHOCO S.A. DE C.V. | D5: Sí | E5: Bajío (Celaya) | F5: Celaya | G5: Guanajuato | H5: Ganada | I5: 44527 | J5: 2021 | K5: 788217.01 | L5: No | M5: 2.1 | N5: Incremental | O5: Banda en V / transmisión (PT-V-BELTS) | P5: Bandas en V | Q5: sufijo de línea en el nombre | T5: 38 Bajío | U5: Froylan Santiago Inactive Alcántara | V5: Sí | W5: End User | X5: Food & Beverage | Y5: Manufacturing - Food Processing | Z5: Excluida | AA5: ID de distribuidores / jobbers; Descripción con ID de distribuidor / jobber | AC5: Competitive Share Gain - Branch Changeover
A6: 804237 | B6: 2.2 VBelt BACHOCO/ RYASA - Cienega de Flores PT & FP-804237 | C6: BACHOCO SA de CV - Cienega de Flores | D6: Sí | E6: Nuevo León (Ciénega de Flores) | F6: Ciénega de Flores | G6: Nuevo León | H6: Ganada | I6: 46227 | J6: 2026 | K6: 420399.95 | L6: No | M6: 2.2 | N6: Incremental | O6: Mixta PT y FP | P6: Otras o sin detalle de producto | Q6: sufijo de línea en el nombre | S6: RODAMIENTOS Y ACCESORIOS, S.A. DE C - 30902 - SAN NICOLAS DE LOS GARZA | T6: 34 Noreste | U6: Emmanuel Quintanilla | V6: No | W6: Exporter/Trading Company | X6: Food & Beverage | Y6: Manufacturing - Food Processing | Z6: Excluida | AA6: Segmento intermediario | AC6: Competitive Share Gain - Branch Changeover
A7: 811939 | B7: 2.2 BACHOCO/ RYASA - Cienega de Flores PT-MV BELTS-811939 | C7: BACHOCO SA de CV - Cienega de Flores | D7: Sí | E7: Nuevo León (Ciénega de Flores) | F7: Ciénega de Flores | G7: Nuevo León | H7: Abierta | I7: 46304 | J7: 2026 | K7: 291251.99 | L7: No | M7: 2.2 | N7: Incremental | O7: Banda micro-V (PT-MV BELTS) | P7: Bandas síncronas, poliuretano y micro-V | Q7: sufijo de línea en el nombre | S7: RODAMIENTOS Y ACCESORIOS, S.A. DE C - 30902 - SAN NICOLAS DE LOS GARZA | T7: 34 Noreste | U7: Emmanuel Quintanilla | V7: No | W7: Exporter/Trading Company | X7: Food & Beverage | Y7: Manufacturing - Food Processing | Z7: Excluida | AA7: Segmento intermediario | AC7: Competitive Share Gain - Branch Changeover
A8: O-00245158 | B8: 2.2 Pti Bachoco RYASA | C8: BACHOCO, S.A. DE C.V - Planta de alimentos division Bajio | D8: Sí | E8: Bajío (Celaya) | F8: Celaya | G8: Guanajuato | H8: Ganada | I8: 44065 | J8: 2020 | K8: 556510.74 | L8: No | M8: 2.2 | N8: Replacement | O8: Banda en V / transmisión (PT-V-BELTS) | P8: Bandas en V | Q8: abreviatura en el nombre | S8: RODAMIENTOS Y ACCESORIOS S.A. DE C.V. - 050308 - QUERETARO | T8: 38 Bajío | U8: Ulises Sanchez | V8: No | W8: End User | X8: Manufacturing - General | Y8: Manufacturing - Food Processing | Z8: Elegible | AA8: End User y aplicación identificable por nomenclatura; sujeto a validación comercial | AC8: Existing Business
A9: 569067 | B9: 7.1 PTI- BACHOCO, S.A. DE C.V - Planta de alimentos division Bajio PT-V-BELTS-569067- RYASA QRO | C9: BACHOCO, S.A. DE C.V - Planta de alimentos division Bajio | D9: Sí | E9: Bajío (Celaya) | F9: Celaya | G9: Guanajuato | H9: Ganada | I9: 44741 | J9: 2022 | K9: 963376.43 | L9: No | M9: 7.1 | N9: Replacement | O9: Banda en V / transmisión (PT-V-BELTS) | P9: Bandas en V | Q9: sufijo de línea en el nombre | S9: RODAMIENTOS Y ACCESORIOS S.A. DE C.V. - 050308 - QUERETARO | T9: 38 Bajío | U9: Froylan Santiago Inactive Alcántara | V9: Sí | W9: End User | X9: Food & Beverage | Y9: Manufacturing - Food Processing | Z9: Elegible | AA9: End User y aplicación identificable por nomenclatura; sujeto a validación comercial | AC9: Existing Business
A10: 679801 | B10: 2.2 PTI Optibelt Bachoco DBS Hermosillo | C10: Bachoco | D10: Sí | E10: Noroeste (Sonora/BC) | F10: Ciudad Obregón | G10: Sonora | H10: Perdida | I10: 45261 | J10: 2023 | K10: 179334.87 | L10: No | M10: 2.2 | N10: Incremental | O10: Banda en V / transmisión (PT-V-BELTS) | P10: Bandas en V | Q10: abreviatura en el nombre | R10: Optibelt | S10: DISTRIBUIDORA DE BALEROS DEL SURESTE S.A. DE C.V. - 040718 - HERMOSILLO | T10: 37 Noroeste | U10: Johnatan Inactive Murillo | V10: Sí | W10: End User | X10: Food & Beverage | Y10: Manufacturing - Food Processing | Z10: Elegible | AA10: End User y aplicación identificable por nomenclatura; sujeto a validación comercial | AC10: Competitive Share Gain - Branch Changeover
A11: 680789 | B11: 7.1 PCC Bachoco Obregon Ryasa Obregon | C11: Bachoco | D11: Sí | E11: Noroeste (Sonora/BC) | F11: Ciudad Obregón | G11: Sonora | H11: Perdida | I11: 45421 | J11: 2024 | K11: 305372.03 | L11: No | M11: 7.1 | N11: Incremental | O11: Banda síncrona Poly Chain (PCC) | P11: Bandas síncronas, poliuretano y micro-V | Q11: abreviatura en el nombre | S11: Rodamientos y Accesorios, S.A. DE C.V. - 50411 - Cd. Obregon. | T11: 37 Noroeste | U11: Johnatan Inactive Murillo | V11: Sí | W11: End User | X11: Food & Beverage | Y11: Manufacturing - Food Processing | Z11: Excluida | AA11: Tipo de oportunidad de distribución | AC11: New Outlet / Branch Set Up
A12: 544347 | B12: 7.1 TPU Bachoco S.A. DE C.V. - Planta procesadora de aves Sonora PT-PU BELTS-544347 | C12: Bachoco S.A. DE C.V. - Planta procesadora de aves Sonora | D12: Sí | E12: Noroeste (Sonora/BC) | F12: Mexicali | G12: Baja California | H12: Perdida | I12: 44729 | J12: 2022 | K12: 131369.47 | L12: No | M12: 7.1 | N12: Incremental | O12: Banda poliuretano / TPU (PT-PU BELTS) | P12: Bandas síncronas, poliuretano y micro-V | Q12: sufijo de línea en el nombre | S12: Rodamientos y Accesorios S.A. de C.V. 10610 Mexicali | T12: 37 Noroeste | U12: Abel Inactive Valenzuela | V12: Sí | W12: End User | X12: Food & Beverage | Y12: Manufacturing - Food Processing | Z12: Elegible | AA12: End User y aplicación identificable por nomenclatura; sujeto a validación comercial | AC12: Adding Different Product Line
A13: 573657 | B13: 7.1 MXT Bachoco S.A. DE C.V. Planta Mexicali | C13: Bachoco S.A. DE C.V. - Planta procesadora de aves Sonora | D13: Sí | E13: Noroeste (Sonora/BC) | F13: Mexicali | G13: Baja California | H13: Perdida | I13: 44785 | J13: 2022 | K13: 131369.47 | L13: No | M13: 7.1 | N13: Incremental | O13: Manguera hidráulica (FP-HYDRAULICS) | P13: Manguera hidráulica y neumática | Q13: abreviatura en el nombre | T13: 37 Noroeste | U13: Abel Inactive Valenzuela | V13: Sí | W13: End User | X13: Food & Beverage | Y13: Manufacturing - Food Processing | Z13: Elegible | AA13: End User y aplicación identificable por nomenclatura; sujeto a validación comercial | AC13: Adding Different Product Line
A14: 573658 | B14: 7.1 MXT Bachoco S.A. DE C.V. - Planta procesadora de aves Mexicali | C14: Bachoco S.A. DE C.V. - Planta procesadora de aves Sonora | D14: Sí | E14: Noroeste (Sonora/BC) | F14: Mexicali | G14: Baja California | H14: Perdida | I14: 44894 | J14: 2022 | K14: 131369.47 | L14: No | M14: 7.1 | N14: Incremental | O14: Manguera hidráulica (FP-HYDRAULICS) | P14: Manguera hidráulica y neumática | Q14: abreviatura en el nombre | S14: Rodamientos y Accesorios S.A. de C.V. 10610 Mexicali | T14: 37 Noroeste | U14: Abel Inactive Valenzuela | V14: Sí | W14: End User | X14: Food & Beverage | Y14: Manufacturing - Food Processing | Z14: Elegible | AA14: End User y aplicación identificable por nomenclatura; sujeto a validación comercial | AC14: Adding Different Product Line
A15: 562416 | B15: 7.1 TPU Posiclean Bachoco Hermosillo DBS Hermosillo | C15: Bachoco S.A. DE C.V. - Planta procesadora de aves Sonora | D15: Sí | E15: Noroeste (Sonora/BC) | F15: Mexicali | G15: Baja California | H15: Perdida | I15: 44945 | J15: 2023 | K15: 85272.27 | L15: No | M15: 7.1 | N15: Incremental | O15: Banda poliuretano / TPU (PT-PU BELTS) | P15: Bandas síncronas, poliuretano y micro-V | Q15: abreviatura en el nombre | S15: DISTRIBUIDORA DE BALEROS DEL SURESTE S.A. DE C.V. - 040718 - HERMOSILLO | T15: 37 Noroeste | U15: Johnatan Inactive Murillo | V15: Sí | W15: End User | X15: Food & Beverage | Y15: Manufacturing - Food Processing | Z15: Elegible | AA15: End User y aplicación identificable por nomenclatura; sujeto a validación comercial | AC15: Adding Different Product Line
A16: O-00222514 | B16: 2.2 PTI Rexon Bachoco Ryasa Ver | C16: Bachoco S.A. De C.V. - Veracruz | D16: Sí | E16: Veracruz | F16: Tierra Blanca | G16: Veracruz | H16: Ganada | I16: 43497 | J16: 2019 | K16: 78838.97 | L16: No | M16: 2.2 | N16: Replacement | O16: Banda en V / transmisión (PT-V-BELTS) | P16: Bandas en V | Q16: abreviatura en el nombre | R16: Rexon | S16: RODAMIENTOS Y ACCESORIOS, S.A. DE C - 20407 - VERACRUZ | T16: 36 Península | U16: Eliasib Luna | V16: No | W16: End User | X16: Manufacturing - General | Y16: Manufacturing - Food Processing | Z16: Elegible | AA16: End User y aplicación identificable por nomenclatura; sujeto a validación comercial | AC16: Existing Business
A17: 552710 | B17: 7.1 V-Belts Bachoco Veracruz Ryasa Veracruz | C17: Bachoco S.A. De C.V. - Veracruz | D17: Sí | E17: Veracruz | F17: Tierra Blanca | G17: Veracruz | H17: Ganada | I17: 44553 | J17: 2021 | K17: 87579.71 | L17: No | M17: 7.1 | N17: Replacement | O17: Banda en V / transmisión (PT-V-BELTS) | P17: Bandas en V | Q17: abreviatura en el nombre | S17: RODAMIENTOS Y ACCESORIOS, S.A. DE C - 20407 - VERACRUZ | T17: 36 Península | U17: Eliasib Luna | V17: No | W17: End User | X17: Food & Beverage | Y17: Manufacturing - Food Processing | Z17: Elegible | AA17: End User y aplicación identificable por nomenclatura; sujeto a validación comercial | AC17: Existing Business
A18: 648860 | B18: 7.1 V-Belts Bachoco Veracruz SNR Córdoba | C18: Bachoco S.A. De C.V. - Veracruz | D18: Sí | E18: Veracruz | F18: Tierra Blanca | G18: Veracruz | H18: Ganada | I18: 45015 | J18: 2023 | K18: 538004.45 | L18: No | M18: 7.1 | N18: Replacement | O18: Banda en V / transmisión (PT-V-BELTS) | P18: Bandas en V | Q18: abreviatura en el nombre | S18: SURTIDORA NACIONAL DE RODAMIENTOS, - 10406 - CORDOBA | T18: 36 Península | U18: Eliasib Luna | V18: No | W18: End User | X18: Food & Beverage | Y18: Manufacturing - Food Processing | Z18: Elegible | AA18: End User y aplicación identificable por nomenclatura; sujeto a validación comercial | AC18: Existing Business
A19: O-00224369 | B19: 2.2 PT-Bachoco-Ryasa | C19: Bachoco S.A. de C.V - Guanajuato | D19: Sí | E19: Bajío (Celaya) | F19: Celaya | G19: Guanajuato | H19: Ganada | I19: 43584 | J19: 2019 | K19: 139127.64 | L19: No | M19: 2.2 | N19: Replacement | O19: Transmisión de potencia (sin detalle de producto) | P19: Otras o sin detalle de producto | Q19: PT / competidor de transmisión en el nombre | S19: Rodamientos Y Accesorios S.A. de C.V. - 050308 - Celaya | T19: 38 Bajío | U19: Ulises Sanchez | V19: No | W19: End User | X19: Manufacturing - General | Y19: Manufacturing - Food Processing | Z19: Elegible | AA19: End User y aplicación identificable por nomenclatura; sujeto a validación comercial | AC19: Existing Business
A20: O-00228877 | B20: 4.2 Pti Bachoco-Ryasa Cly | C20: Bachoco S.A. de C.V - Guanajuato | D20: Sí | E20: Bajío (Celaya) | F20: Celaya | G20: Guanajuato | H20: Ganada | I20: 43643 | J20: 2019 | K20: 463759.04 | L20: No | M20: 4.2 | N20: Replacement | O20: Banda en V / transmisión (PT-V-BELTS) | P20: Bandas en V | Q20: abreviatura en el nombre | S20: Rodamientos Y Accesorios S.A. de C.V. - 050308 - Celaya | T20: 38 Bajío | U20: Ulises Sanchez | V20: No | W20: End User | X20: Mining | Y20: Mining | Z20: Revisar | AA20: Nomenclatura no concluyente | AC20: Existing Business
